Workbook

Sheet tous Tabelles
A1: Table PRODUITS | E1: Table ACHETEURS | H1: Table DEPENSES
A2: produit_id (PK) | B2: INT | E2: acheteur_id (PK) | F2: INT | H2: depense_id (PK) | I2: INT
A3: code_produit | B3: VARCHAR | E3: nom_acheteur | F3: VARCHAR | H3: date_depense | I3: DATE
A4: nom_produit | B4: VARCHAR | H4: motif | I4: VARCHAR | L4: 510000
A5: categorie | B5: VARCHAR | H5: montant | I5: DECIMAL | M5: =383600+95000 -> 478600 | N5: depence
A6: unite | B6: VARCHAR | M6: =L4-M5 -> 31400 | N6: reste
A7: stock_min | B7: INT
A8: date_creation | B8: DATE | M8: =M6+30000-44000 -> 17400
A10: Table VENTES | E10: Table ACHATS | H10: Table PRODUITS_PERDUS
A11: vente_id (PK) | B11: INT | E11: achat_id (PK) | F11: INT | H11: perte_id (PK) | I11: INT
A12: date_vente | B12: DATETIME | E12: date_achat | F12: DATE | H12: date_perte | I12: DATE
A13: vendeur_id (FK) | B13: INT | E13: numero_facture | F13: VARCHAR | H13: produit_id (FK) | I13: INT
A14: total_vente | B14: DECIMAL | E14: acheteur_id (FK) | F14: INT | H14: quantite | I14: INT | L14: 17400
E15: frais_enlevement | F15: DECIMAL | H15: motif_perte | I15: VARCHAR | L15: 700000
E16: total_facture | F16: DECIMAL | H16: valeur_unitaire | I16: DECIMAL | M16: 681300 | N16: achat
H17: valeur_totale | I17: DECIMAL | M17: 10000 | N17: caburant
H18: utilisateur | I18: VARCHAR | M18: 800 | N18: photocopie et scaner
A19: Table LIGNES_VENTE | E19: Table LIGNES_ACHAT
A20: ligne_vente_id (PK) | B20: INT | E20: ligne_achat_id (PK) | F20: INT | L20: =SUM(L14:L15) -> 717400 | M20: =SUM(M16:M18) -> 692100
A21: vente_id (FK) | B21: INT | E21: achat_id (FK) | F21: INT
A22: produit_id (FK) | B22: INT | E22: produit_id (FK) | F22: INT | M22: =L20-M20 -> 25300 | N22: reste
A23: quantite | B23: INT | E23: quantite | F23: INT
A24: pu_vente | B24: DECIMAL | E24: qte_bouteilles | F24: INT | M24: 10000
A25: montant_ligne | B25: DECIMAL | E25: pu_achat | F25: DECIMAL
E26: total_achat | F26: DECIMAL | M26: =M22-M24 -> 15300
A27: Table VENDEURS
A28: vendeur_id (PK) | B28: INT
A29: nom_vendeur | B29: VARCHAR

Sheet caise
C1: TOTAL | G1: Caise Actuel
C2: =SUM(Tabelle1[Entre]) -> 1876825 | D2: =SUM(Tabelle1[Achat]) -> 1518150 | E2: =SUM(Tabelle1[autre depence]) -> 183000 | G2: =C2-D2-E2+B4 -> 515575
A3: Date | B3: Depart | C3: Entre | D3: Achat | E3: autre depence | F3: Details | G3: Spalte1
A4: 46174 | B4: 339900
A5: 46174 | D5: 107200
A6: 46174 | E6: 50000 | F6: Salaire
A7: 46174 | E7: 3000 | F7: verre
A8: 46175 | C8: 15350
A9: 46176 | C9: 17550
A10: 46176 | D10: 153800
A11: 46176 | E11: 1500 | F11: Taxi
A12: 46177 | C12: 9550 | D12: 27000
A13: 46178 | C13: 9500 | E13: 2500 | F13: Taxi
A14: 46179 | C14: 82750 | D14: 70700
A15: 46180 | C15: 70100
A16: 46182 | C16: 85400 | D16: 71300
A17: 46183 | C17: 34150 | D17: 151800
A18: 46184 | C18: 55850 | E18: 10000 | F18: canaplus
A19: 46185 | C19: 12700
A20: 46186 | C20: 45000
A21: 46187 | C21: 16650
A22: 46189 | C22: 45200 | D22: 137200
A23: 46190 | C23: 22100 | D23: 57000
A24: 46191 | C24: 37500 | D24: 24800 | E24: 500 | F24: photocopie
A25: 46192 | C25: 43500 | E25: 30000 | F25: complement rechargement boutique
A26: 46193 | C26: 51600
A27: 46194 | C27: 15400
A28: 46196 | C28: 63850
A29: 46197 | C29: 16725 | D29: 7050
A30: 46198 | C30: 35300
A31: 46199 | C31: 111875 | D31: 51000
A32: 46200 | C32: 63150 | D32: 51000
A33: 46201 | C33: 54350 | E33: 2000 | F33: repas controleur
A34: 46203 | C34: 147650 | E34: 8000 | F34: Lumiere
A35: 46204 | C35: 20925 | D35: =174300+15600 -> 189900
A36: 46205 | C36: 20775
A37: 46206 | C37: 72775
A38: 46207 | C38: 43575
A39: 46208 | C39: 74075
A40: 46210 | C40: 41550 | D40: 155900 | E40: 50000 | F40: Salaire
C41: 15000
A42: 46211 | C42: 36200 | E42: 25000 | F42: cable
A43: 46212 | C43: 59050 | E43: 500 | F43: photocopie
A44: 46213 | C44: 36625
A45: 46214 | C45: 49800
A46: 46215 | C46: 10050
A47: 46217 | C47: 44475
A48: 46218 | C48: 28750 | D48: 183400
A49: 46219 | C49: 34700
A50: 46220 | C50: 52100 | D50: 49700
A51: 46221 | C51: 51750
A52: 46222 | C52: 21900 | D52: 29400

Sheet dim_date
A1: date_id | B1: jour | C1: mois | D1: annee | E1: trimestre | F1: nom_mois
A2: 46173 | B2: =DAY(A2) -> 31 | C2: =MONTH(A2) -> 5 | D2: =YEAR(A2) -> 2026 | E2: ="T"&ROUNDUP(MONTH(A2)/3,0) -> T2 | F2: =TEXT(A2,"MMMM") -> Mai
A3: 46174 | B3: =DAY(A3) -> 1 | C3: =MONTH(A3) -> 6 | D3: =YEAR(A3) -> 2026 | E3: ="T"&ROUNDUP(MONTH(A3)/3,0) -> T2 | F3: =TEXT(A3,"MMMM") -> Juni
A4: 46175 | B4: =DAY(A4) -> 2 | C4: =MONTH(A4) -> 6 | D4: =YEAR(A4) -> 2026 | E4: ="T"&ROUNDUP(MONTH(A4)/3,0) -> T2 | F4: =TEXT(A4,"MMMM") -> Juni
A5: 46176 | B5: =DAY(A5) -> 3 | C5: =MONTH(A5) -> 6 | D5: =YEAR(A5) -> 2026 | E5: ="T"&ROUNDUP(MONTH(A5)/3,0) -> T2 | F5: =TEXT(A5,"MMMM") -> Juni
A6: 46177 | B6: =DAY(A6) -> 4 | C6: =MONTH(A6) -> 6 | D6: =YEAR(A6) -> 2026 | E6: ="T"&ROUNDUP(MONTH(A6)/3,0) -> T2 | F6: =TEXT(A6,"MMMM") -> Juni
A7: 46178 | B7: =DAY(A7) -> 5 | C7: =MONTH(A7) -> 6 | D7: =YEAR(A7) -> 2026 | E7: ="T"&ROUNDUP(MONTH(A7)/3,0) -> T2 | F7: =TEXT(A7,"MMMM") -> Juni
A8: 46179 | B8: =DAY(A8) -> 6 | C8: =MONTH(A8) -> 6 | D8: =YEAR(A8) -> 2026 | E8: ="T"&ROUNDUP(MONTH(A8)/3,0) -> T2 | F8: =TEXT(A8,"MMMM") -> Juni
A9: 46180 | B9: =DAY(A9) -> 7 | C9: =MONTH(A9) -> 6 | D9: =YEAR(A9) -> 2026 | E9: ="T"&ROUNDUP(MONTH(A9)/3,0) -> T2 | F9: =TEXT(A9,"MMMM") -> Juni
A10: 46181 | B10: =DAY(A10) -> 8 | C10: =MONTH(A10) -> 6 | D10: =YEAR(A10) -> 2026 | E10: ="T"&ROUNDUP(MONTH(A10)/3,0) -> T2 | F10: =TEXT(A10,"MMMM") -> Juni
A11: 46182 | B11: =DAY(A11) -> 9 | C11: =MONTH(A11) -> 6 | D11: =YEAR(A11) -> 2026 | E11: ="T"&ROUNDUP(MONTH(A11)/3,0) -> T2 | F11: =TEXT(A11,"MMMM") -> Juni
A12: 46183 | B12: =DAY(A12) -> 10 | C12: =MONTH(A12) -> 6 | D12: =YEAR(A12) -> 2026 | E12: ="T"&ROUNDUP(MONTH(A12)/3,0) -> T2 | F12: =TEXT(A12,"MMMM") -> Juni
A13: 46184 | B13: =DAY(A13) -> 11 | C13: =MONTH(A13) -> 6 | D13: =YEAR(A13) -> 2026 | E13: ="T"&ROUNDUP(MONTH(A13)/3,0) -> T2 | F13: =TEXT(A13,"MMMM") -> Juni
... A33: 46204 | B33: =DAY(A33) -> 1 | C33: =MONTH(A33) -> 7 | D33: =YEAR(A33) -> 2026 | E33: ="T"&ROUNDUP(MONTH(A33)/3,0) -> T3 | F33: =TEXT(A33,"MMMM") -> Juli

Sheet dim_categories
A1: categorie_id | B1: code_categorie | C1: nom_categorie | D1: description | E1: date_creation
A2: 1 | B2: =IF(ISNUMBER(SEARCH(" ",C2)),UPPER(LEFT(C2,2)&LEFT(_xlfn.TEXTAFTER(C2," "),1)),UPPER(LEFT(C2,3))) -> ASS | C2: Assaisonnement | D2: Produits servant à assaisonner les aliments (Maggi, épices, sel, bouillons, etc.). | E2: 46023
A3: =A2+1 -> 2 | B3: BIS | C3: Biscuits | D3: Biscuits sucrés, salés, crackers et produits similaires. | E3: 46023
A4: =A3+1 -> 3 | B4: BEN | C4: Boisson Energisante | D4: Boissons énergisantes telles que XXL, Predator, Red Bull, etc. | E4: 46023
A5: =A4+1 -> 4 | B5: BOG | C5: Boisson Gazeuse | D5: Boissons gazeuses non alcoolisées (Coca-Cola, Fanta, Sprite, Top, etc.). | E5: 46023
A6: =A5+1 -> 5 | B6: BRB | C6: Brasserie Biere | D6: Bières produites par les brasseries locales ou internationales. | E6: 46023
A7: =A6+1 -> 6 | B7: CAN | C7: Canette | D7: Boissons conditionnées en canette (bières, sodas, boissons énergisantes). | E7: 46023
A8: =A7+1 -> 7 | B8: COM | C8: Combustible | D8: Produits destinés à la cuisson ou à l'éclairage (charbon, gaz, pétrole, etc.). | E8: 46023
A9: =A8+1 -> 8 | B9: TOM | C9: Concentré Tomate | D9: Concentrés de tomate en sachet, boîte ou tube. | E9: 46023
A10: =A9+1 -> 9 | B10: CNF | C10: Confiserie | D10: Bonbons, chewing-gums, chocolats et autres friandises. | E10: 46023
A11: =A10+1 -> 10 | B11: CSV | C11: Conserve | D11: Conserves alimentaires en boîte ou en bocal. | E11: 46023
A12: =A11+1 -> 11 | B12: CSG | C12: Consigne | D12: Bouteilles consignées et emballages retournables. | E12: 46023
A13: =A12+1 -> 12 | B13: EAU | C13: Eau | D13: Eaux minérales et eaux de table. | E13: 46023
A14: =A13+1 -> 13 | B14: ELE | C14: Electricite | D14: Produits ou services liés à l'électricité (ampoules, recharge, etc.). | E14: 46023
... A33: =A32+1 -> 32 | B33: DIV | C33: Divers | D33: Produits ne pouvant être classés dans aucune autre catégorie. | E33: 46023

Sheet dim_produits
A1: produit_id | B1: code_produit | C1: nom_produit | D1: categorie_id | E1: nom_categorie | F1: unite | G1: qte_par_carton | H1: stock_min | I1: actif | J1: date_creation | N1: manque dans fact_inventaire
A2: 1 | B2: =IF(ISNUMBER(SEARCH(" ",E2)), LEFT(UPPER(E2),2)&MID(UPPER(E2),SEARCH(" ",E2)+1,1), LEFT(UPPER(E2),3)) & TEXT(COUNTIF($E$2:E2,E2),"000") -> ASS001 | C2: CUBE MAGGI ETOILE 25 X100X4G | D2: =IFERROR(INDEX(dim_categories!$A:$A,MATCH(E2,dim_categories!$C:$C,0)),"") -> 1 | E2: Assaisonnement | F2: Cube | G2: 100 | H2: =G2/10 -> 10 | I2: TRUE | J2: 46174 | N2: =IF(ISNUMBER(MATCH(C2,fact_inventaire!$E:$E,0)),"OK","MANQUANT") -> OK
A3: =A2+1 -> 2 | B3: =IF(ISNUMBER(SEARCH(" ",E3)), LEFT(UPPER(E3),2)&MID(UPPER(E3),SEARCH(" ",E3)+1,1), LEFT(UPPER(E3),3)) & TEXT(COUNTIF($E$2:E3,E3),"000") -> BIS001 | C3: BISCUIT PARLE G 4X60X14G | D3: =IFERROR(INDEX(dim_categories!$A:$A,MATCH(E3,dim_categories!$C:$C,0)),"") -> 2 | E3: Biscuits | F3: Pièce | G3: 240 | H3: =G3/24 -> 10 | I3: TRUE | J3: 46174 | N3: =IF(ISNUMBER(MATCH(C3,fact_inventaire!$E:$E,0)),"OK","MANQUANT") -> OK
A4: =A3+1 -> 3 | B4: =IF(ISNUMBER(SEARCH(" ",E4)), LEFT(UPPER(E4),2)&MID(UPPER(E4),SEARCH(" ",E4)+1,1), LEFT(UPPER(E4),3)) & TEXT(COUNTIF($E$2:E4,E4),"000") -> BIS002 | C4: BISCUIT PARLE G 31 56 3X120 | D4: =IFERROR(INDEX(dim_categories!$A:$A,MATCH(E4,dim_categories!$C:$C,0)),"") -> 2 | E4: Biscuits | F4: Pièce | G4: 120 | H4: =G4/12 -> 10 | I4: TRUE | J4: 46174 | N4: =IF(ISNUMBER(MATCH(C4,fact_inventaire!$E:$E,0)),"OK","MANQUANT") -> OK
A5: =A4+1 -> 4 | B5: =IF(ISNUMBER(SEARCH(" ",E5)), LEFT(UPPER(E5),2)&MID(UPPER(E5),SEARCH(" ",E5)+1,1), LEFT(UPPER(E5),3)) & TEXT(COUNTIF($E$2:E5,E5),"000") -> BIS003 | C5: BISCUIT ABC X120 | D5: =IFERROR(INDEX(dim_categories!$A:$A,MATCH(E5,dim_categories!$C:$C,0)),"") -> 2 | E5: Biscuits | F5: Pièce | G5: 120 | H5: =G5/12 -> 10 | I5: TRUE | J5: 46174 | N5: =IF(ISNUMBER(MATCH(C5,fact_inventaire!$E:$E,0)),"OK","MANQUANT") -> OK
A6: =A5+1 -> 5 | B6: =IF(ISNUMBER(SEARCH(" ",E6)), LEFT(UPPER(E6),2)&MID(UPPER(E6),SEARCH(" ",E6)+1,1), LEFT(UPPER(E6),3)) & TEXT(COUNTIF($E$2:E6,E6),"000") -> BOE001 | C6: JUS REAKTOR DARK POWER PET 0,5L | D6: =IFERROR(INDEX(dim_categories!$A:$A,MATCH(E6,dim_categories!$C:$C,0)),"") -> 3 | E6: Boisson Energisante | F6: Canette | G6: 10 | H6: =G6/2 -> 5 | I6: TRUE | J6: 46174 | N6: =IF(ISNUMBER(MATCH(C6,fact_inventaire!$E:$E,0)),"OK","MANQUANT") -> OK
A7: =A6+1 -> 6 | B7: =IF(ISNUMBER(SEARCH(" ",E7)), LEFT(UPPER(E7),2)&MID(UPPER(E7),SEARCH(" ",E7)+1,1), LEFT(UPPER(E7),3)) & TEXT(COUNTIF($E$2:E7,E7),"000") -> BOE002 | C7: JUS REAKTOR GOLD POWER 0,5L | D7: =IFERROR(INDEX(dim_categories!$A:$A,MATCH(E7,dim_categories!$C:$C,0)),"") -> 3 | E7: Boisson Energisante | F7: Canette | G7: 11 | H7: =G7/2 -> 5.5 | I7: TRUE | J7: 46174 | N7: =IF(ISNUMBER(MATCH(C7,fact_inventaire!$E:$E,0)),"OK","MANQUANT") -> OK
A8: =A7+1 -> 7 | B8: =IF(ISNUMBER(SEARCH(" ",E8)), LEFT(UPPER(E8),2)&MID(UPPER(E8),SEARCH(" ",E8)+1,1), LEFT(UPPER(E8),3)) & TEXT(COUNTIF($E$2:E8,E8),"000") -> BOG001 | C8: BOSTER COLA 0,65L | D8: =IFERROR(INDEX(dim_categories!$A:$A,MATCH(E8,dim_categories!$C:$C,0)),"") -> 4 | E8: Boisson Gazeuse | F8: Bouteille | G8: 12 | H8: =G8/1 -> 12 | I8: TRUE | J8: 46174 | N8: =IF(ISNUMBER(MATCH(C8,fact_inventaire!$E:$E,0)),"OK","MANQUANT") -> OK
A9: =A8+1 -> 8 | B9: =IF(ISNUMBER(SEARCH(" ",E9)), LEFT(UPPER(E9),2)&MID(UPPER(E9),SEARCH(" ",E9)+1,1), LEFT(UPPER(E9),3)) & TEXT(COUNTIF($E$2:E9,E9),"000") -> BOG002 | C9: BOSTER DJIM TONIC 0,65L | D9: =IFERROR(INDEX(dim_categories!$A:$A,MATCH(E9,dim_categories!$C:$C,0)),"") -> 4 | E9: Boisson Gazeuse | F9: Bouteille | G9: 12 | H9: =G9/1 -> 12 | I9: TRUE | J9: 46174 | N9: =IF(ISNUMBER(MATCH(C9,fact_inventaire!$E:$E,0)),"OK","MANQUANT") -> MANQUANT
A10: =A9+1 -> 9 | B10: =IF(ISNUMBER(SEARCH(" ",E10)), LEFT(UPPER(E10),2)&MID(UPPER(E10),SEARCH(" ",E10)+1,1), LEFT(UPPER(E10),3)) & TEXT(COUNTIF($E$2:E10,E10),"000") -> BRB001 | C10: 33 EXPORT 0,65L | D10: =IFERROR(INDEX(dim_categories!$A:$A,MATCH(E10,dim_categories!$C:$C,0)),"") -> 5 | E10: Brasserie Biere | F10: Bouteille | G10: 12 | H10: =G10/1 -> 12 | I10: TRUE | J10: 46174 | N10: =IF(ISNUMBER(MATCH(C10,fact_inventaire!$E:$E,0)),"OK","MANQUANT") -> OK
A11: =A10+1 -> 10 | B11: =IF(ISNUMBER(SEARCH(" ",E11)), LEFT(UPPER(E11),2)&MID(UPPER(E11),SEARCH(" ",E11)+1,1), LEFT(UPPER(E11),3)) & TEXT(COUNTIF($E$2:E11,E11),"000") -> BRB002 | C11: BEAUFORT ORDINAIRE 0,65L | D11: =IFERROR(INDEX(dim_categories!$A:$A,MATCH(E11,dim_categories!$C:$C,0)),"") -> 5 | E11: Brasserie Biere | F11: Bouteille | G11: 12 | H11: =G11/1 -> 12 | I11: TRUE | J11: 46174 | N11: =IF(ISNUMBER(MATCH(C11,fact_inventaire!$E:$E,0)),"OK","MANQUANT") -> OK
A12: =A11+1 -> 11 | B12: =IF(ISNUMBER(SEARCH(" ",E12)), LEFT(UPPER(E12),2)&MID(UPPER(E12),SEARCH(" ",E12)+1,1), LEFT(UPPER(E12),3)) & TEXT(COUNTIF($E$2:E12,E12),"000") -> BRB003 | C12: CASTEL 0,5L | D12: =IFERROR(INDEX(dim_categories!$A:$A,MATCH(E12,dim_categories!$C:$C,0)),"") -> 5 | E12: Brasserie Biere | F12: Bouteille | G12: 12 | H12: =G12/1 -> 12 | I12: TRUE | J12: 46174 | N12: =IF(ISNUMBER(MATCH(C12,fact_inventaire!$E:$E,0)),"OK","MANQUANT") -> OK
A13: =A12+1 -> 12 | B13: =IF(ISNUMBER(SEARCH(" ",E13)), LEFT(UPPER(E13),2)&MID(UPPER(E13),SEARCH(" ",E13)+1,1), LEFT(UPPER(E13),3)) & TEXT(COUNTIF($E$2:E13,E13),"000") -> BRB004 | C13: DOPPEL 0,65L | D13: =IFERROR(INDEX(dim_categories!$A:$A,MATCH(E13,dim_categories!$C:$C,0)),"") -> 5 | E13: Brasserie Biere | F13: Bouteille | G13: 12 | H13: =G13/1 -> 12 | I13: TRUE | J13: 46174 | N13: =IF(ISNUMBER(MATCH(C13,fact_inventaire!$E:$E,0)),"OK","MANQUANT") -> OK
A14: =A13+1 -> 13 | B14: =IF(ISNUMBER(SEARCH(" ",E14)), LEFT(UPPER(E14),2)&MID(UPPER(E14),SEARCH(" ",E14)+1,1), LEFT(UPPER(E14),3)) & TEXT(COUNTIF($E$2:E14,E14),"000") -> BRB005 | C14: HARP BRASSERIE 0,6L | D14: =IFERROR(INDEX(dim_categories!$A:$A,MATCH(E14,dim_categories!$C:$C,0)),"") -> 5 | E14: Brasserie Biere | F14: Bouteille | G14: 12 | H14: =G14/1 -> 12 | I14: TRUE | J14: 46174 | N14: =IF(ISNUMBER(MATCH(C14,fact_inventaire!$E:$E,0)),"OK","MANQUANT") -> OK
A15: =A14+1 -> 14 | B15: =IF(ISNUMBER(SEARCH(" ",E15)), LEFT(UPPER(E15),2)&MID(UPPER(E15),SEARCH(" ",E15)+1,1), LEFT(UPPER(E15),3)) & TEXT(COUNTIF($E$2:E15,E15),"000") -> BRB006 | C15: SMINOFF ICE ANANA 0,33L | D15: =IFERROR(INDEX(dim_categories!$A:$A,MATCH(E15,dim_categories!$C:$C,0)),"") -> 5 | E15: Brasserie Biere | F15: Bouteille | G15: 12 | H15: =G15/1 -> 12 | I15: TRUE | J15: 46174 | N15: =IF(ISNUMBER(MATCH(C15,fact_inventaire!$E:$E,0)),"OK","MANQUANT") -> OK
A16: =A15+1 -> 15 | B16: =IF(ISNUMBER(SEARCH(" ",E16)), LEFT(UPPER(E16),2)&MID(UPPER(E16),SEARCH(" ",E16)+1,1), LEFT(UPPER(E16),3)) & TEXT(COUNTIF($E$2:E16,E16),"000") -> BRB007 | C16: ISEMBECK 0,65L | D16: =IFERROR(INDEX(dim_categories!$A:$A,MATCH(E16,dim_categories!$C:$C,0)),"") -> 5 | E16: Brasserie Biere | F16: Bouteille | G16: 12 | H16: =G16/1 -> 12 | I16: TRUE | J16: 46174 | N16: =IF(ISNUMBER(MATCH(C16,fact_inventaire!$E:$E,0)),"OK","MANQUANT") -> OK
A17: =A16+1 -> 16 | B17: =IF(ISNUMBER(SEARCH(" ",E17)), LEFT(UPPER(E17),2)&MID(UPPER(E17),SEARCH(" ",E17)+1,1), LEFT(UPPER(E17),3)) & TEXT(COUNTIF($E$2:E17,E17),"000") -> BRB008 | C17: KADJI BIER 0,65L | D17: =IFERROR(INDEX(dim_categories!$A:$A,MATCH(E17,dim_categories!$C:$C,0)),"") -> 5 | E17: Brasserie Biere | F17: Bouteille | G17: 12 | H17: =G17/1 -> 12 | I17: TRUE | J17: 46174 | N17: =IF(ISNUMBER(MATCH(C17,fact_inventaire!$E:$E,0)),"OK","MANQUANT") -> OK
A18: =A17+1 -> 17 | B18: =IF(ISNUMBER(SEARCH(" ",E18)), LEFT(UPPER(E18),2)&MID(UPPER(E18),SEARCH(" ",E18)+1,1), LEFT(UPPER(E18),3)) & TEXT(COUNTIF($E$2:E18,E18),"000") -> BRB009 | C18: MANYAN 0,65L | D18: =IFERROR(INDEX(dim_categories!$A:$A,MATCH(E18,dim_categories!$C:$C,0)),"") -> 5 | E18: Brasserie Biere | F18: Bouteille | G18: 12 | H18: =G18/1 -> 12 | I18: TRUE | J18: 46174 | N18: =IF(ISNUMBER(MATCH(C18,fact_inventaire!$E:$E,0)),"OK","MANQUANT") -> OK
A19: =A18+1 -> 18 | B19: =IF(ISNUMBER(SEARCH(" ",E19)), LEFT(UPPER(E19),2)&MID(UPPER(E19),SEARCH(" ",E19)+1,1), LEFT(UPPER(E19),3)) & TEXT(COUNTIF($E$2:E19,E19),"000") -> BRB010 | C19: MUTZIG 0,65L | D19: =IFERROR(INDEX(dim_categories!$A:$A,MATCH(E19,dim_categories!$C:$C,0)),"") -> 5 | E19: Brasserie Biere | F19: Bouteille | G19: 12 | H19: =G19/1 -> 12 | I19: TRUE | J19: 46174 | N19: =IF(ISNUMBER(MATCH(C19,fact_inventaire!$E:$E,0)),"OK","MANQUANT") -> OK
A20: =A19+1 -> 19 | B20: =IF(ISNUMBER(SEARCH(" ",E20)), LEFT(UPPER(E20),2)&MID(UPPER(E20),SEARCH(" ",E20)+1,1), LEFT(UPPER(E20),3)) & TEXT(COUNTIF($E$2:E20,E20),"000") -> CAN001 | C20: BOSTER COLA CANETTE 0,5L | D20: =IFERROR(INDEX(dim_categories!$A:$A,MATCH(E20,dim_categories!$C:$C,0)),"") -> 6 | E20: Canette | F20: Canette | G20: 24 | H20: =G20/4 -> 6 | I20: TRUE | J20: 46174 | N20: =IF(ISNUMBER(MATCH(C20,fact_inventaire!$E:$E,0)),"OK","MANQUANT") -> OK
A21: =A20+1 -> 20 | B21: =IF(ISNUMBER(SEARCH(" ",E21)), LEFT(UPPER(E21),2)&MID(UPPER(E21),SEARCH(" ",E21)+1,1), LEFT(UPPER(E21),3)) & TEXT(COUNTIF($E$2:E21,E21),"000") -> CAN002 | C21: BEAUFORT ORDINAIRE CANETTE 0,5L | D21: =IFERROR(INDEX(dim_categories!$A:$A,MATCH(E21,dim_categories!$C:$C,0)),"") -> 6 | E21: Canette | F21: Canette | G21: 24 | H21: =G21/4 -> 6 | I21: TRUE | J21: 46174 | N21: =IF(ISNUMBER(MATCH(C21,fact_inventaire!$E:$E,0)),"OK","MANQUANT") -> OK
A22: =A21+1 -> 21 | B22: =IF(ISNUMBER(SEARCH(" ",E22)), LEFT(UPPER(E22),2)&MID(UPPER(E22),SEARCH(" ",E22)+1,1), LEFT(UPPER(E22),3)) & TEXT(COUNTIF($E$2:E22,E22),"000") -> CAN003 | C22: MUTZIG CANETTE 0,5L | D22: =IFERROR(INDEX(dim_categories!$A:$A,MATCH(E22,dim_categories!$C:$C,0)),"") -> 6 | E22: Canette | F22: Canette | G22: 24 | H22: =G22/4 -> 6 | I22: TRUE | J22: 46174 | N22: =IF(ISNUMBER(MATCH(C22,fact_inventaire!$E:$E,0)),"OK","MANQUANT") -> OK
A23: =A22+1 -> 22 | B23: =IF(ISNUMBER(SEARCH(" ",E23)), LEFT(UPPER(E23),2)&MID(UPPER(E23),SEARCH(" ",E23)+1,1), LEFT(UPPER(E23),3)) & TEXT(COUNTIF($E$2:E23,E23),"000") -> CAN004 | C23: CASTEL CANETTE 0,5L | D23: =IFERROR(INDEX(dim_categories!$A:$A,MATCH(E23,dim_categories!$C:$C,0)),"") -> 6 | E23: Canette | F23: Canette | G23: 24 | H23: =G23/4 -> 6 | I23: TRUE | J23: 46174 | N23: =IF(ISNUMBER(MATCH(C23,fact_inventaire!$E:$E,0)),"OK","MANQUANT") -> OK
A24: =A23+1 -> 23 | B24: =IF(ISNUMBER(SEARCH(" ",E24)), LEFT(UPPER(E24),2)&MID(UPPER(E24),SEARCH(" ",E24)+1,1), LEFT(UPPER(E24),3)) & TEXT(COUNTIF($E$2:E24,E24),"000") -> CAN005 | C24: 33 EXPORT CANETTE 0,5L | D24: =IFERROR(INDEX(dim_categories!$A:$A,MATCH(E24,dim_categories!$C:$C,0)),"") -> 6 | E24: Canette | F24: Canette | G24: 24 | H24: =G24/4 -> 6 | I24: TRUE | J24: 46174 | N24: =IF(ISNUMBER(MATCH(C24,fact_inventaire!$E:$E,0)),"OK","MANQUANT") -> OK
A25: =A24+1 -> 24 | B25: =IF(ISNUMBER(SEARCH(" ",E25)), LEFT(UPPER(E25),2)&MID(UPPER(E25),SEARCH(" ",E25)+1,1), LEFT(UPPER(E25),3)) & TEXT(COUNTIF($E$2:E25,E25),"000") -> CAN006 | C25: MALTA GUINESS CANETTE 0,5L | D25: =IFERROR(INDEX(dim_categories!$A:$A,MATCH(E25,dim_categories!$C:$C,0)),"") -> 6 | E25: Canette | F25: Canette | G25: 24 | H25: =G25/4 -> 6 | I25: TRUE | J25: 46174 | N25: =IF(ISNUMBER(MATCH(C25,fact_inventaire!$E:$E,0)),"OK","MANQUANT") -> OK
A26: =A25+1 -> 25 | B26: =IF(ISNUMBER(SEARCH(" ",E26)), LEFT(UPPER(E26),2)&MID(UPPER(E26),SEARCH(" ",E26)+1,1), LEFT(UPPER(E26),3)) & TEXT(COUNTIF($E$2:E26,E26),"000") -> COM001 | C26: BRIQUET FLAG 20PQTX50 | D26: =IFERROR(INDEX(dim_categories!$A:$A,MATCH(E26,dim_categories!$C:$C,0)),"") -> 7 | E26: Combustible | F26: Pièce | G26: 50 | H26: =G26/5 -> 10 | I26: TRUE | J26: 46174 | N26: =IF(ISNUMBER(MATCH(C26,fact_inventaire!$E:$E,0)),"OK","MANQUANT") -> OK
A27: =A26+1 -> 26 | B27: =IF(ISNUMBER(SEARCH(" ",E27)), LEFT(UPPER(E27),2)&MID(UPPER(E27),SEARCH(" ",E27)+1,1), LEFT(UPPER(E27),3)) & TEXT(COUNTIF($E$2:E27,E27),"000") -> COT001 | C27: TOMATE ROMA SACHET 50X70G | D27: =IFERROR(INDEX(dim_categories!$A:$A,MATCH(E27,dim_categories!$C:$C,0)),"") -> 8 | E27: Concentré Tomate | F27: Sachet | G27: 50 | H27: =G27/5 -> 10 | I27: TRUE | J27: 46174 | N27: =IF(ISNUMBER(MATCH(C27,fact_inventaire!$E:$E,0)),"OK","MANQUANT") -> OK
A28: =A27+1 -> 27 | B28: =IF(ISNUMBER(SEARCH(" ",E28)), LEFT(UPPER(E28),2)&MID(UPPER(E28),SEARCH(" ",E28)+1,1), LEFT(UPPER(E28),3)) & TEXT(COUNTIF($E$2:E28,E28),"000") -> CON001 | C28: BONBON TATOO POP X16 | D28: =IFERROR(INDEX(dim_categories!$A:$A,MATCH(E28,dim_categories!$C:$C,0)),"") -> 9 | E28: Confiserie | F28: Pièce | G28: 48 | H28: =G28/5 -> 9.6 | I28: TRUE | J28: 46174 | N28: =IF(ISNUMBER(MATCH(C28,fact_inventaire!$E:$E,0)),"OK","MANQUANT") -> OK
A29: =A28+1 -> 28 | B29: =IF(ISNUMBER(SEARCH(" ",E29)), LEFT(UPPER(E29),2)&MID(UPPER(E29),SEARCH(" ",E29)+1,1), LEFT(UPPER(E29),3)) & TEXT(COUNTIF($E$2:E29,E29),"000") -> CON002 | C29: BONBON MENTOS BTE 18 | D29: =IFERROR(INDEX(dim_categories!$A:$A,MATCH(E29,dim_categories!$C:$C,0)),"") -> 9 | E29: Confiserie | F29: Boîte | G29: 98 | H29: =G29/5 -> 19.6 | I29: TRUE | J29: 46174 | N29: =IF(ISNUMBER(MATCH(C29,fact_inventaire!$E:$E,0)),"OK","MANQUANT") -> OK
A30: =A29+1 -> 29 | B30: =IF(ISNUMBER(SEARCH(" ",E30)), LEFT(UPPER(E30),2)&MID(UPPER(E30),SEARCH(" ",E30)+1,1), LEFT(UPPER(E30),3)) & TEXT(COUNTIF($E$2:E30,E30),"000") -> CON001 | C30: SARDINE JOLY NON PIMENTE 125X50 | D30: =IFERROR(INDEX(dim_categories!$A:$A,MATCH(E30,dim_categories!$C:$C,0)),"") -> 10 | E30: Conserve | F30: Pièce | G30: 50 | H30: =G30/5 -> 10 | I30: TRUE | J30: 46174 | N30: =IF(ISNUMBER(MATCH(C30,fact_inventaire!$E:$E,0)),"OK","MANQUANT") -> OK
A31: =A30+1 -> 30 | B31: =IF(ISNUMBER(SEARCH(" ",E31)), LEFT(UPPER(E31),2)&MID(UPPER(E31),SEARCH(" ",E31)+1,1), LEFT(UPPER(E31),3)) & TEXT(COUNTIF($E$2:E31,E31),"000") -> CON001 | C31: BOUTEILLE CONSIGNE | D31: =IFERROR(INDEX(dim_categories!$A:$A,MATCH(E31,dim_categories!$C:$C,0)),"") -> 11 | E31: Consigne | F31: Pièce | G31: 1 | H31: 1 | I31: TRUE | J31: 46174 | N31: =IF(ISNUMBER(MATCH(C31,fact_inventaire!$E:$E,0)),"OK","MANQUANT") -> MANQUANT
A32: =A31+1 -> 31 | B32: =IF(ISNUMBER(SEARCH(" ",E32)), LEFT(UPPER(E32),2)&MID(UPPER(E32),SEARCH(" ",E32)+1,1), LEFT(UPPER(E32),3)) & TEXT(COUNTIF($E$2:E32,E32),"000") -> EAU001 | C32: EAU VITAL 10L | D32: =IFERROR(INDEX(dim_categories!$A:$A,MATCH(E32,dim_categories!$C:$C,0)),"") -> 12 | E32: Eau | F32: Bidon | G32: 1 | H32: 4 | I32: TRUE | J32: 46174 | N32: =IF(ISNUMBER(MATCH(C32,fact_inventaire!$E:$E,0)),"OK","MANQUANT") -> OK
A33: =A32+1 -> 32 | B33: =IF(ISNUMBER(SEARCH(" ",E33)), LEFT(UPPER(E33),2)&MID(UPPER(E33),SEARCH(" ",E33)+1,1), LEFT(UPPER(E33),3)) & TEXT(COUNTIF($E$2:E33,E33),"000") -> EAU002 | C33: EAU SUPERMONT 0,5L | D33: =IFERROR(INDEX(dim_categories!$A:$A,MATCH(E33,dim_categories!$C:$C,0)),"") -> 12 | E33: Eau | F33: Bouteille | G33: 12 | H33: =G33/1 -> 12 | I33: TRUE | J33: 46174 | N33: =IF(ISNUMBER(MATCH(C33,fact_inventaire!$E:$E,0)),"OK","MANQUANT") -> OK
A34: =A33+1 -> 33 | B34: =IF(ISNUMBER(SEARCH(" ",E34)), LEFT(UPPER(E34),2)&MID(UPPER(E34),SEARCH(" ",E34)+1,1), LEFT(UPPER(E34),3)) & TEXT(COUNTIF($E$2:E34,E34),"000") -> EAU003 | C34: EAU SUPERMONT 1,5L | D34: =IFERROR(INDEX(dim_categories!$A:$A,MATCH(E34,dim_categories!$C:$C,0)),"") -> 12 | E34: Eau | F34: Bouteille | G34: 6 | H34: =G34/1 -> 6 | I34: TRUE | J34: 46174 | N34: =IF(ISNUMBER(MATCH(C34,fact_inventaire!$E:$E,0)),"OK","MANQUANT") -> OK
A35: =A34+1 -> 34 | B35: =IF(ISNUMBER(SEARCH(" ",E35)), LEFT(UPPER(E35),2)&MID(UPPER(E35),SEARCH(" ",E35)+1,1), LEFT(UPPER(E35),3)) & TEXT(COUNTIF($E$2:E35,E35),"000") -> EAU004 | C35: EAU SUPERMONT 10L | D35: =IFERROR(INDEX(dim_categories!$A:$A,MATCH(E35,dim_categories!$C:$C,0)),"") -> 12 | E35: Eau | F35: Bouteille | G35: 10 | H35: =G35/1 -> 10 | I35: TRUE | J35: 46174 | N35: =IF(ISNUMBER(MATCH(C35,fact_inventaire!$E:$E,0)),"OK","MANQUANT") -> OK
A36: =A35+1 -> 35 | B36: =IF(ISNUMBER(SEARCH(" ",E36)), LEFT(UPPER(E36),2)&MID(UPPER(E36),SEARCH(" ",E36)+1,1), LEFT(UPPER(E36),3)) & TEXT(COUNTIF($E$2:E36,E36),"000") -> EAU005 | C36: EAU MINERAL OPUR 0,5L | D36: =IFERROR(INDEX(dim_categories!$A:$A,MATCH(E36,dim_categories!$C:$C,0)),"") -> 12 | E36: Eau | F36: Bouteille | G36: 12 | H36: =G36/1 -> 12 | I36: TRUE | J36: 46174 | N36: =IF(ISNUMBER(MATCH(C36,fact_inventaire!$E:$E,0)),"OK","MANQUANT") -> OK
A37: =A36+1 -> 36 | B37: =IF(ISNUMBER(SEARCH(" ",E37)), LEFT(UPPER(E37),2)&MID(UPPER(E37),SEARCH(" ",E37)+1,1), LEFT(UPPER(E37),3)) & TEXT(COUNTIF($E$2:E37,E37),"000") -> EAU006 | C37: EAU MINERAL OPUR 1,5L | D37: =IFERROR(INDEX(dim_categories!$A:$A,MATCH(E37,dim_categories!$C:$C,0)),"") -> 12 | E37: Eau | F37: Bouteille | G37: 6 | H37: =G37/1 -> 6 | I37: TRUE | J37: 46174 | N37: =IF(ISNUMBER(MATCH(C37,fact_inventaire!$E:$E,0)),"OK","MANQUANT") -> OK
A38: =A37+1 -> 37 | B38: =IF(ISNUMBER(SEARCH(" ",E38)), LEFT(UPPER(E38),2)&MID(UPPER(E38),SEARCH(" ",E38)+1,1), LEFT(UPPER(E38),3)) & TEXT(COUNTIF($E$2:E38,E38),"000") -> ELE001 | C38: AMPOULE REGRETTE | D38: =IFERROR(INDEX(dim_categories!$A:$A,MATCH(E38,dim_categories!$C:$C,0)),"") -> 13 | E38: Electricite | F38: Pièce | G38: 10 | H38: 1 | I38: TRUE | J38: 46174 | N38: =IF(ISNUMBER(MATCH(C38,fact_inventaire!$E:$E,0)),"OK","MANQUANT") -> OK
A39: =A38+1 -> 38 | B39: =IF(ISNUMBER(SEARCH(" ",E39)), LEFT(UPPER(E39),2)&MID(UPPER(E39),SEARCH(" ",E39)+1,1), LEFT(UPPER(E39),3)) & TEXT(COUNTIF($E$2:E39,E39),"000") -> ELE002 | C39: RALONGE ELECTRIQUE | D39: =IFERROR(INDEX(dim_categories!$A:$A,MATCH(E39,dim_categories!$C:$C,0)),"") -> 13 | E39: Electricite | F39: Pièce | G39: 10 | H39: 1 | I39: TRUE | J39: 46174 | N39: =IF(ISNUMBER(MATCH(C39,fact_inventaire!$E:$E,0)),"OK","MANQUANT") -> OK
A40: =A39+1 -> 39 | B40: =IF(ISNUMBER(SEARCH(" ",E40)), LEFT(UPPER(E40),2)&MID(UPPER(E40),SEARCH(" ",E40)+1,1), LEFT(UPPER(E40),3)) & TEXT(COUNTIF($E$2:E40,E40),"000") -> EMB001 | C40: PLASTIQUE | D40: =IFERROR(INDEX(dim_categories!$A:$A,MATCH(E40,dim_categories!$C:$C,0)),"") -> 14 | E40: Emballage | F40: Paquet | G40: 10 | H40: 1 | I40: TRUE | J40: 46174 | N40: =IF(ISNUMBER(MATCH(C40,fact_inventaire!$E:$E,0)),"OK","MANQUANT") -> OK
A41: =A40+1 -> 40 | B41: =IF(ISNUMBER(SEARCH(" ",E41)), LEFT(UPPER(E41),2)&MID(UPPER(E41),SEARCH(" ",E41)+1,1), LEFT(UPPER(E41),3)) & TEXT(COUNTIF($E$2:E41,E41),"000") -> ENT001 | C41: DETERGENT MADAR 25G Y156 | D41: =IFERROR(INDEX(dim_categories!$A:$A,MATCH(E41,dim_categories!$C:$C,0)),"") -> 15 | E41: Entretien | F41: Pièce | G41: 156 | H41: =G41/15 -> 10.4 | I41: TRUE | J41: 46174 | N41: =IF(ISNUMBER(MATCH(C41,fact_inventaire!$E:$E,0)),"OK","MANQUANT") -> OK
A42: =A41+1 -> 41 | B42: =IF(ISNUMBER(SEARCH(" ",E42)), LEFT(UPPER(E42),2)&MID(UPPER(E42),SEARCH(" ",E42)+1,1), LEFT(UPPER(E42),3)) & TEXT(COUNTIF($E$2:E42,E42),"000") -> ENT002 | C42: DETERGENT BRIL 30GX150 | D42: =IFERROR(INDEX(dim_categories!$A:$A,MATCH(E42,dim_categories!$C:$C,0)),"") -> 15 | E42: Entretien | F42: Pièce | G42: 150 | H42: =G42/15 -> 10 | I42: TRUE | J42: 46174 | N42: =IF(ISNUMBER(MATCH(C42,fact_inventaire!$E:$E,0)),"OK","MANQUANT") -> OK
A43: =A42+1 -> 42 | B43: =IF(ISNUMBER(SEARCH(" ",E43)), LEFT(UPPER(E43),2)&MID(UPPER(E43),SEARCH(" ",E43)+1,1), LEFT(UPPER(E43),3)) & TEXT(COUNTIF($E$2:E43,E43),"000") -> ENT003 | C43: CIRAGE LIQUIDE | D43: =IFERROR(INDEX(dim_categories!$A:$A,MATCH(E43,dim_categories!$C:$C,0)),"") -> 15 | E43: Entretien | F43: Pièce | G43: 10 | H43: 1 | I43: TRUE | J43: 46174 | N43: =IF(ISNUMBER(MATCH(C43,fact_inventaire!$E:$E,0)),"OK","MANQUANT") -> OK
A44: =A43+1 -> 43 | B44: =IF(ISNUMBER(SEARCH(" ",E44)), LEFT(UPPER(E44),2)&MID(UPPER(E44),SEARCH(" ",E44)+1,1), LEFT(UPPER(E44),3)) & TEXT(COUNTIF($E$2:E44,E44),"000") -> EPI001 | C44: SUCRE KFTY SACHET 12 XIKG | D44: =IFERROR(INDEX(dim_categories!$A:$A,MATCH(E44,dim_categories!$C:$C,0)),"") -> 16 | E44: Epicerie | F44: Paquet | G44: 12 | H44: =G44/4 -> 3 | I44: TRUE | J44: 46174 | N44: =IF(ISNUMBER(MATCH(C44,fact_inventaire!$E:$E,0)),"OK","MANQUANT") -> OK
A45: =A44+1 -> 44 | B45: =IF(ISNUMBER(SEARCH(" ",E45)), LEFT(UPPER(E45),2)&MID(UPPER(E45),SEARCH(" ",E45)+1,1), LEFT(UPPER(E45),3)) & TEXT(COUNTIF($E$2:E45,E45),"000") -> EPI002 | C45: NESCAFE COFFRET 9X1501 50 | D45: =IFERROR(INDEX(dim_categories!$A:$A,MATCH(E45,dim_categories!$C:$C,0)),"") -> 16 | E45: Epicerie | F45: Paquet | G45: 150 | H45: =G45/15 -> 10 | I45: TRUE | J45: 46174 | N45: =IF(ISNUMBER(MATCH(C45,fact_inventaire!$E:$E,0)),"OK","MANQUANT") -> OK
A46: =A45+1 -> 45 | B46: =IF(ISNUMBER(SEARCH(" ",E46)), LEFT(UPPER(E46),2)&MID(UPPER(E46),SEARCH(" ",E46)+1,1), LEFT(UPPER(E46),3)) & TEXT(COUNTIF($E$2:E46,E46),"000") -> EPI003 | C46: LAIT TOP MIL VANILLE SACHET 6 X50 | D46: =IFERROR(INDEX(dim_categories!$A:$A,MATCH(E46,dim_categories!$C:$C,0)),"") -> 16 | E46: Epicerie | F46: Paquet | G46: 50 | H46: =G46/5 -> 10 | I46: TRUE | J46: 46174 | N46: =IF(ISNUMBER(MATCH(C46,fact_inventaire!$E:$E,0)),"OK","MANQUANT") -> OK
A47: =A46+1 -> 46 | B47: =IF(ISNUMBER(SEARCH(" ",E47)), LEFT(UPPER(E47),2)&MID(UPPER(E47),SEARCH(" ",E47)+1,1), LEFT(UPPER(E47),3)) & TEXT(COUNTIF($E$2:E47,E47),"000") -> EPI004 | C47: HUILE MAYOR 15X1L | D47: =IFERROR(INDEX(dim_categories!$A:$A,MATCH(E47,dim_categories!$C:$C,0)),"") -> 16 | E47: Epicerie | F47: Bouteille | G47: 15 | H47: =G47/5 -> 3 | I47: TRUE | J47: 46174 | N47: =IF(ISNUMBER(MATCH(C47,fact_inventaire!$E:$E,0)),"OK","MANQUANT") -> OK
A48: =A47+1 -> 47 | B48: =IF(ISNUMBER(SEARCH(" ",E48)), LEFT(UPPER(E48),2)&MID(UPPER(E48),SEARCH(" ",E48)+1,1), LEFT(UPPER(E48),3)) & TEXT(COUNTIF($E$2:E48,E48),"000") -> FOU001 | C48: CAOUTCHOUC | D48: =IFERROR(INDEX(dim_categories!$A:$A,MATCH(E48,dim_categories!$C:$C,0)),"") -> 17 | E48: Fourniture | F48: Pièce | G48: 10 | H48: 1 | I48: TRUE | J48: 46174 | N48: =IF(ISNUMBER(MATCH(C48,fact_inventaire!$E:$E,0)),"OK","MANQUANT") -> OK
A49: =A48+1 -> 48 | B49: =IF(ISNUMBER(SEARCH(" ",E49)), LEFT(UPPER(E49),2)&MID(UPPER(E49),SEARCH(" ",E49)+1,1), LEFT(UPPER(E49),3)) & TEXT(COUNTIF($E$2:E49,E49),"000") -> FOU002 | C49: EPINGLE | D49: =IFERROR(INDEX(dim_categories!$A:$A,MATCH(E49,dim_categories!$C:$C,0)),"") -> 17 | E49: Fourniture | F49: Pièce | G49: 10 | H49: 1 | I49: TRUE | J49: 46174 | N49: =IF(ISNUMBER(MATCH(C49,fact_inventaire!$E:$E,0)),"OK","MANQUANT") -> OK
A50: =A49+1 -> 49 | B50: =IF(ISNUMBER(SEARCH(" ",E50)), LEFT(UPPER(E50),2)&MID(UPPER(E50),SEARCH(" ",E50)+1,1), LEFT(UPPER(E50),3)) & TEXT(COUNTIF($E$2:E50,E50),"000") -> FOU003 | C50: RÈGLE GRADUE | D50: =IFERROR(INDEX(dim_categories!$A:$A,MATCH(E50,dim_categories!$C:$C,0)),"") -> 17 | E50: Fourniture | F50: Pièce | G50: 10 | H50: 1 | I50: TRUE | J50: 46174 | N50: =IF(ISNUMBER(MATCH(C50,fact_inventaire!$E:$E,0)),"OK","MANQUANT") -> OK
A51: =A50+1 -> 50 | B51: =IF(ISNUMBER(SEARCH(" ",E51)), LEFT(UPPER(E51),2)&MID(UPPER(E51),SEARCH(" ",E51)+1,1), LEFT(UPPER(E51),3)) & TEXT(COUNTIF($E$2:E51,E51),"000") -> FOU004 | C51: TAILLE CRAYON | D51: =IFERROR(INDEX(dim_categories!$A:$A,MATCH(E51,dim_categories!$C:$C,0)),"") -> 17 | E51: Fourniture | F51: Pièce | G51: 10 | H51: 1 | I51: TRUE | J51: 46174 | N51: =IF(ISNUMBER(MATCH(C51,fact_inventaire!$E:$E,0)),"OK","MANQUANT") -> OK
A52: =A51+1 -> 51 | B52: =IF(ISNUMBER(SEARCH(" ",E52)), LEFT(UPPER(E52),2)&MID(UPPER(E52),SEARCH(" ",E52)+1,1), LEFT(UPPER(E52),3)) & TEXT(COUNTIF($E$2:E52,E52),"000") -> GUB001 | C52: GRAND GUINESS 0,65L | D52: =IFERROR(INDEX(dim_categories!$A:$A,MATCH(E52,dim_categories!$C:$C,0)),"") -> 18 | E52: Guinness Biere | F52: Bouteille | G52: 12 | H52: =G52/1 -> 12 | I52: TRUE | J52: 46174 | N52: =IF(ISNUMBER(MATCH(C52,fact_inventaire!$E:$E,0)),"OK","MANQUANT") -> OK
A53: =A52+1 -> 52 | B53: =IF(ISNUMBER(SEARCH(" ",E53)), LEFT(UPPER(E53),2)&MID(UPPER(E53),SEARCH(" ",E53)+1,1), LEFT(UPPER(E53),3)) & TEXT(COUNTIF($E$2:E53,E53),"000") -> GUB002 | C53: MALTA GUINESS 0,3L | D53: =IFERROR(INDEX(dim_categories!$A:$A,MATCH(E53,dim_categories!$C:$C,0)),"") -> 18 | E53: Guinness Biere | F53: Bouteille | G53: 24 | H53: =G53/1 -> 24 | I53: TRUE | J53: 46174 | N53: =IF(ISNUMBER(MATCH(C53,fact_inventaire!$E:$E,0)),"OK","MANQUANT") -> OK
A54: =A53+1 -> 53 | B54: =IF(ISNUMBER(SEARCH(" ",E54)), LEFT(UPPER(E54),2)&MID(UPPER(E54),SEARCH(" ",E54)+1,1), LEFT(UPPER(E54),3)) & TEXT(COUNTIF($E$2:E54,E54),"000") -> GUB003 | C54: ORIGI GUINESS 0,60L | D54: =IFERROR(INDEX(dim_categories!$A:$A,MATCH(E54,dim_categories!$C:$C,0)),"") -> 18 | E54: Guinness Biere | F54: Bouteille | G54: 12 | H54: =G54/1 -> 12 | I54: TRUE | J54: 46174 | N54: =IF(ISNUMBER(MATCH(C54,fact_inventaire!$E:$E,0)),"OK","MANQUANT") -> OK
A55: =A54+1 -> 54 | B55: =IF(ISNUMBER(SEARCH(" ",E55)), LEFT(UPPER(E55),2)&MID(UPPER(E55),SEARCH(" ",E55)+1,1), LEFT(UPPER(E55),3)) & TEXT(COUNTIF($E$2:E55,E55),"000") -> GUB004 | C55: PETIT GUINESS 0,35L | D55: =IFERROR(INDEX(dim_categories!$A:$A,MATCH(E55,dim_categories!$C:$C,0)),"") -> 18 | E55: Guinness Biere | F55: Bouteille | G55: 24 | H55: =G55/1 -> 24 | I55: TRUE | J55: 46174 | N55: =IF(ISNUMBER(MATCH(C55,fact_inventaire!$E:$E,0)),"OK","MANQUANT") -> OK
A56: =A55+1 -> 55 | B56: =IF(ISNUMBER(SEARCH(" ",E56)), LEFT(UPPER(E56),2)&MID(UPPER(E56),SEARCH(" ",E56)+1,1), LEFT(UPPER(E56),3)) & TEXT(COUNTIF($E$2:E56,E56),"000") -> GUB005 | C56: SMOOTH GUINESS 0,50L | D56: =IFERROR(INDEX(dim_categories!$A:$A,MATCH(E56,dim_categories!$C:$C,0)),"") -> 18 | E56: Guinness Biere | F56: Bouteille | G56: 15 | H56: =G56/1 -> 15 | I56: TRUE | J56: 46174 | N56: =IF(ISNUMBER(MATCH(C56,fact_inventaire!$E:$E,0)),"OK","MANQUANT") -> OK
A57: =A56+1 -> 56 | B57: =IF(ISNUMBER(SEARCH(" ",E57)), LEFT(UPPER(E57),2)&MID(UPPER(E57),SEARCH(" ",E57)+1,1), LEFT(UPPER(E57),3)) & TEXT(COUNTIF($E$2:E57,E57),"000") -> GUB006 | C57: SMOOTH GUINESS 0,65L | D57: =IFERROR(INDEX(dim_categories!$A:$A,MATCH(E57,dim_categories!$C:$C,0)),"") -> 18 | E57: Guinness Biere | F57: Bouteille | G57: 12 | H57: =G57/1 -> 12 | I57: TRUE | J57: 46174 | N57: =IF(ISNUMBER(MATCH(C57,fact_inventaire!$E:$E,0)),"OK","MANQUANT") -> OK
A58: =A57+1 -> 57 | B58: =IF(ISNUMBER(SEARCH(" ",E58)), LEFT(UPPER(E58),2)&MID(UPPER(E58),SEARCH(" ",E58)+1,1), LEFT(UPPER(E58),3)) & TEXT(COUNTIF($E$2:E58,E58),"000") -> HYG001 | C58: SAVON MAYOR 360G 60 | D58: =IFERROR(INDEX(dim_categories!$A:$A,MATCH(E58,dim_categories!$C:$C,0)),"") -> 19 | E58: Hygiene | F58: Pièce | G58: 60 | H58: =G58/10 -> 6 | I58: TRUE | J58: 46174 | N58: =IF(ISNUMBER(MATCH(C58,fact_inventaire!$E:$E,0)),"OK","MANQUANT") -> OK
A59: =A58+1 -> 58 | B59: =IF(ISNUMBER(SEARCH(" ",E59)), LEFT(UPPER(E59),2)&MID(UPPER(E59),SEARCH(" ",E59)+1,1), LEFT(UPPER(E59),3)) & TEXT(COUNTIF($E$2:E59,E59),"000") -> HYG002 | C59: SAVON AZUR 400G 60 | D59: =IFERROR(INDEX(dim_categories!$A:$A,MATCH(E59,dim_categories!$C:$C,0)),"") -> 19 | E59: Hygiene | F59: Pièce | G59: 60 | H59: =G59/10 -> 6 | I59: TRUE | J59: 46174 | N59: =IF(ISNUMBER(MATCH(C59,fact_inventaire!$E:$E,0)),"OK","MANQUANT") -> OK
A60: =A59+1 -> 59 | B60: =IF(ISNUMBER(SEARCH(" ",E60)), LEFT(UPPER(E60),2)&MID(UPPER(E60),SEARCH(" ",E60)+1,1), LEFT(UPPER(E60),3)) & TEXT(COUNTIF($E$2:E60,E60),"000") -> HYG003 | C60: SAVON PROTEX HERBAL12X6X150G | D60: =IFERROR(INDEX(dim_categories!$A:$A,MATCH(E60,dim_categories!$C:$C,0)),"") -> 19 | E60: Hygiene | F60: Pièce | G60: 6 | H60: =G60/3 -> 2 | I60: TRUE | J60: 46174 | N60: =IF(ISNUMBER(MATCH(C60,fact_inventaire!$E:$E,0)),"OK","MANQUANT") -> OK
A61: =A60+1 -> 60 | B61: =IF(ISNUMBER(SEARCH(" ",E61)), LEFT(UPPER(E61),2)&MID(UPPER(E61),SEARCH(" ",E61)+1,1), LEFT(UPPER(E61),3)) & TEXT(COUNTIF($E$2:E61,E61),"000") -> HYG004 | C61: SAVON SANTEX BLANC 12X690G | D61: =IFERROR(INDEX(dim_categories!$A:$A,MATCH(E61,dim_categories!$C:$C,0)),"") -> 19 | E61: Hygiene | F61: Pièce | G61: 6 | H61: =G61/3 -> 2 | I61: TRUE | J61: 46174 | N61: =IF(ISNUMBER(MATCH(C61,fact_inventaire!$E:$E,0)),"OK","MANQUANT") -> OK
A62: =A61+1 -> 61 | B62: =IF(ISNUMBER(SEARCH(" ",E62)), LEFT(UPPER(E62),2)&MID(UPPER(E62),SEARCH(" ",E62)+1,1), LEFT(UPPER(E62),3)) & TEXT(COUNTIF($E$2:E62,E62),"000") -> HYG005 | C62: SAVON DAUPHIN CLASSIQUE 6X6X200G | D62: =IFERROR(INDEX(dim_categories!$A:$A,MATCH(E62,dim_categories!$C:$C,0)),"") -> 19 | E62: Hygiene | F62: Pièce | G62: 6 | H62: =G62/3 -> 2 | I62: TRUE | J62: 46174 | N62: =IF(ISNUMBER(MATCH(C62,fact_inventaire!$E:$E,0)),"OK","MANQUANT") -> OK
A63: =A62+1 -> 62 | B63: =IF(ISNUMBER(SEARCH(" ",E63)), LEFT(UPPER(E63),2)&MID(UPPER(E63),SEARCH(" ",E63)+1,1), LEFT(UPPER(E63),3)) & TEXT(COUNTIF($E$2:E63,E63),"000") -> HYG006 | C63: BROSSE COLGATE ANTICAVITY HANGER 12X12 | D63: =IFERROR(INDEX(dim_categories!$A:$A,MATCH(E63,dim_categories!$C:$C,0)),"") -> 19 | E63: Hygiene | F63: Pièce | G63: 12 | H63: =G63/4 -> 3 | I63: TRUE | J63: 46174 | N63: =IF(ISNUMBER(MATCH(C63,fact_inventaire!$E:$E,0)),"OK","MANQUANT") -> OK
A64: =A63+1 -> 63 | B64: =IF(ISNUMBER(SEARCH(" ",E64)), LEFT(UPPER(E64),2)&MID(UPPER(E64),SEARCH(" ",E64)+1,1), LEFT(UPPER(E64),3)) & TEXT(COUNTIF($E$2:E64,E64),"000") -> HYG007 | C64: CURENDENT PEACOCK 50X12 | D64: =IFERROR(INDEX(dim_categories!$A:$A,MATCH(E64,dim_categories!$C:$C,0)),"") -> 19 | E64: Hygiene | F64: Pièce | G64: 12 | H64: =G64/4 -> 3 | I64: TRUE | J64: 46174 | N64: =IF(ISNUMBER(MATCH(C64,fact_inventaire!$E:$E,0)),"OK","MANQUANT") -> OK
A65: =A64+1 -> 64 | B65: =IF(ISNUMBER(SEARCH(" ",E65)), LEFT(UPPER(E65),2)&MID(UPPER(E65),SEARCH(" ",E65)+1,1), LEFT(UPPER(E65),3)) & TEXT(COUNTIF($E$2:E65,E65),"000") -> HYG008 | C65: PAPIER HYGIENIQUE SITA X48 | D65: =IFERROR(INDEX(dim_categories!$A:$A,MATCH(E65,dim_categories!$C:$C,0)),"") -> 19 | E65: Hygiene | F65: Pièce | G65: 48 | H65: =G65/5 -> 9.6 | I65: TRUE | J65: 46174 | N65: =IF(ISNUMBER(MATCH(C65,fact_inventaire!$E:$E,0)),"OK","MANQUANT") -> OK
A66: =A65+1 -> 65 | B66: =IF(ISNUMBER(SEARCH(" ",E66)), LEFT(UPPER(E66),2)&MID(UPPER(E66),SEARCH(" ",E66)+1,1), LEFT(UPPER(E66),3)) & TEXT(COUNTIF($E$2:E66,E66),"000") -> HYG009 | C66: BABOUCHE DE TOILETTE | D66: =IFERROR(INDEX(dim_categories!$A:$A,MATCH(E66,dim_categories!$C:$C,0)),"") -> 19 | E66: Hygiene | F66: Paire | G66: 12 | H66: 0 | I66: TRUE | J66: 46174 | N66: =IF(ISNUMBER(MATCH(C66,fact_inventaire!$E:$E,0)),"OK","MANQUANT") -> OK
A67: =A66+1 -> 66 | B67: =IF(ISNUMBER(SEARCH(" ",E67)), LEFT(UPPER(E67),2)&MID(UPPER(E67),SEARCH(" ",E67)+1,1), LEFT(UPPER(E67),3)) & TEXT(COUNTIF($E$2:E67,E67),"000") -> HYF001 | C67: SER VIETTE HYG AMIE 5X12X280MM | D67: =IFERROR(INDEX(dim_categories!$A:$A,MATCH(E67,dim_categories!$C:$C,0)),"") -> 20 | E67: Hygiène Féminine | F67: Paquet | G67: 12 | H67: =G67/4 -> 3 | I67: TRUE | J67: 46174 | N67: =IF(ISNUMBER(MATCH(C67,fact_inventaire!$E:$E,0)),"OK","MANQUANT") -> OK
A68: =A67+1 -> 67 | B68: =IF(ISNUMBER(SEARCH(" ",E68)), LEFT(UPPER(E68),2)&MID(UPPER(E68),SEARCH(" ",E68)+1,1), LEFT(UPPER(E68),3)) & TEXT(COUNTIF($E$2:E68,E68),"000") -> HYF002 | C68: SER HYG A+ JAUNE 4X6 | D68: =IFERROR(INDEX(dim_categories!$A:$A,MATCH(E68,dim_categories!$C:$C,0)),"") -> 20 | E68: Hygiène Féminine | F68: Paquet | G68: 6 | H68: =G68/5 -> 1.2 | I68: TRUE | J68: 46174 | N68: =IF(ISNUMBER(MATCH(C68,fact_inventaire!$E:$E,0)),"OK","MANQUANT") -> OK
A69: =A68+1 -> 68 | B69: =IF(ISNUMBER(SEARCH(" ",E69)), LEFT(UPPER(E69),2)&MID(UPPER(E69),SEARCH(" ",E69)+1,1), LEFT(UPPER(E69),3)) & TEXT(COUNTIF($E$2:E69,E69),"000") -> HYF003 | C69: SER VIETTE HYG SOFTCARE A+ 10PQTX6 NEW BLEU | D69: =IFERROR(INDEX(dim_categories!$A:$A,MATCH(E69,dim_categories!$C:$C,0)),"") -> 20 | E69: Hygiène Féminine | F69: Paquet | G69: 6 | H69: =G69/5 -> 1.2 | I69: TRUE | J69: 46174 | N69: =IF(ISNUMBER(MATCH(C69,fact_inventaire!$E:$E,0)),"OK","MANQUANT") -> OK
A70: =A69+1 -> 69 | B70: =IF(ISNUMBER(SEARCH(" ",E70)), LEFT(UPPER(E70),2)&MID(UPPER(E70),SEARCH(" ",E70)+1,1), LEFT(UPPER(E70),3)) & TEXT(COUNTIF($E$2:E70,E70),"000") -> INS001 | C70: INSECTICIDE SPIRALE ZERO MOUSTIQUE X60 | D70: =IFERROR(INDEX(dim_categories!$A:$A,MATCH(E70,dim_categories!$C:$C,0)),"") -> 21 | E70: Insecticide | F70: Paquet | G70: 60 | H70: =G70/10 -> 6 | I70: TRUE | J70: 46174 | N70: =IF(ISNUMBER(MATCH(C70,fact_inventaire!$E:$E,0)),"OK","MANQUANT") -> OK
A71: =A70+1 -> 70 | B71: =IF(ISNUMBER(SEARCH(" ",E71)), LEFT(UPPER(E71),2)&MID(UPPER(E71),SEARCH(" ",E71)+1,1), LEFT(UPPER(E71),3)) & TEXT(COUNTIF($E$2:E71,E71),"000") -> JUS001 | C71: JUS FRESHCO GOYAVE 24 X310ML | D71: =IFERROR(INDEX(dim_categories!$A:$A,MATCH(E71,dim_categories!$C:$C,0)),"") -> 22 | E71: Jus | F71: Bouteille | G71: 24 | H71: =G71/4 -> 6 | I71: TRUE | J71: 46174 | N71: =IF(ISNUMBER(MATCH(C71,fact_inventaire!$E:$E,0)),"OK","MANQUANT") -> OK
A72: =A71+1 -> 71 | B72: =IF(ISNUMBER(SEARCH(" ",E72)), LEFT(UPPER(E72),2)&MID(UPPER(E72),SEARCH(" ",E72)+1,1), LEFT(UPPER(E72),3)) & TEXT(COUNTIF($E$2:E72,E72),"000") -> JUS002 | C72: JUS TOP PAMOLEMOUS PET 1L | D72: =IFERROR(INDEX(dim_categories!$A:$A,MATCH(E72,dim_categories!$C:$C,0)),"") -> 22 | E72: Jus | F72: Bouteille | G72: 6 | H72: 6 | I72: TRUE | J72: 46174 | N72: =IF(ISNUMBER(MATCH(C72,fact_inventaire!$E:$E,0)),"OK","MANQUANT") -> OK
A73: =A72+1 -> 72 | B73: =IF(ISNUMBER(SEARCH(" ",E73)), LEFT(UPPER(E73),2)&MID(UPPER(E73),SEARCH(" ",E73)+1,1), LEFT(UPPER(E73),3)) & TEXT(COUNTIF($E$2:E73,E73),"000") -> JUS003 | C73: JUS TOP ORANGE PET 1L | D73: =IFERROR(INDEX(dim_categories!$A:$A,MATCH(E73,dim_categories!$C:$C,0)),"") -> 22 | E73: Jus | F73: Bouteille | G73: 6 | H73: 6 | I73: TRUE | J73: 46174 | N73: =IF(ISNUMBER(MATCH(C73,fact_inventaire!$E:$E,0)),"OK","MANQUANT") -> OK
A74: =A73+1 -> 73 | B74: =IF(ISNUMBER(SEARCH(" ",E74)), LEFT(UPPER(E74),2)&MID(UPPER(E74),SEARCH(" ",E74)+1,1), LEFT(UPPER(E74),3)) & TEXT(COUNTIF($E$2:E74,E74),"000") -> JUS004 | C74: JUS TOP GRENADINE PET 1L | D74: =IFERROR(INDEX(dim_categories!$A:$A,MATCH(E74,dim_categories!$C:$C,0)),"") -> 22 | E74: Jus | F74: Bouteille | G74: 6 | H74: 6 | I74: TRUE | J74: 46174 | N74: =IF(ISNUMBER(MATCH(C74,fact_inventaire!$E:$E,0)),"OK","MANQUANT") -> OK
A75: =A74+1 -> 74 | B75: =IF(ISNUMBER(SEARCH(" ",E75)), LEFT(UPPER(E75),2)&MID(UPPER(E75),SEARCH(" ",E75)+1,1), LEFT(UPPER(E75),3)) & TEXT(COUNTIF($E$2:E75,E75),"000") -> JUS005 | C75: JUS SABS VIMTO 1L | D75: =IFERROR(INDEX(dim_categories!$A:$A,MATCH(E75,dim_categories!$C:$C,0)),"") -> 22 | E75: Jus | F75: Bouteille | G75: 6 | H75: 6 | I75: TRUE | J75: 46174 | N75: =IF(ISNUMBER(MATCH(C75,fact_inventaire!$E:$E,0)),"OK","MANQUANT") -> OK
A76: =A75+1 -> 75 | B76: =IF(ISNUMBER(SEARCH(" ",E76)), LEFT(UPPER(E76),2)&MID(UPPER(E76),SEARCH(" ",E76)+1,1), LEFT(UPPER(E76),3)) & TEXT(COUNTIF($E$2:E76,E76),"000") -> JUS006 | C76: JUS SABS ORANGINA 1L | D76: =IFERROR(INDEX(dim_categories!$A:$A,MATCH(E76,dim_categories!$C:$C,0)),"") -> 22 | E76: Jus | F76: Bouteille | G76: 6 | H76: 6 | I76: TRUE | J76: 46174 | N76: =IF(ISNUMBER(MATCH(C76,fact_inventaire!$E:$E,0)),"OK","MANQUANT") -> OK
A77: =A76+1 -> 76 | B77: =IF(ISNUMBER(SEARCH(" ",E77)), LEFT(UPPER(E77),2)&MID(UPPER(E77),SEARCH(" ",E77)+1,1), LEFT(UPPER(E77),3)) & TEXT(COUNTIF($E$2:E77,E77),"000") -> JUS007 | C77: JUS PLANET TROPICAL 1,2L | D77: =IFERROR(INDEX(dim_categories!$A:$A,MATCH(E77,dim_categories!$C:$C,0)),"") -> 22 | E77: Jus | F77: Bouteille | G77: 6 | H77: 6 | I77: TRUE | J77: 46174 | N77: =IF(ISNUMBER(MATCH(C77,fact_inventaire!$E:$E,0)),"OK","MANQUANT") -> OK
A78: =A77+1 -> 77 | B78: =IF(ISNUMBER(SEARCH(" ",E78)), LEFT(UPPER(E78),2)&MID(UPPER(E78),SEARCH(" ",E78)+1,1), LEFT(UPPER(E78),3)) & TEXT(COUNTIF($E$2:E78,E78),"000") -> JUS008 | C78: JUS COCA COLA PET 1L | D78: =IFERROR(INDEX(dim_categories!$A:$A,MATCH(E78,dim_categories!$C:$C,0)),"") -> 22 | E78: Jus | F78: Bouteille | G78: 6 | H78: 6 | I78: TRUE | J78: 46174 | N78: =IF(ISNUMBER(MATCH(C78,fact_inventaire!$E:$E,0)),"OK","MANQUANT") -> OK
A79: =A78+1 -> 78 | B79: =IF(ISNUMBER(SEARCH(" ",E79)), LEFT(UPPER(E79),2)&MID(UPPER(E79),SEARCH(" ",E79)+1,1), LEFT(UPPER(E79),3)) & TEXT(COUNTIF($E$2:E79,E79),"000") -> JUS009 | C79: JUS TOP ANANAS PET 0,35L | D79: =IFERROR(INDEX(dim_categories!$A:$A,MATCH(E79,dim_categories!$C:$C,0)),"") -> 22 | E79: Jus | F79: Bouteille | G79: 12 | H79: =G79/1 -> 12 | I79: TRUE | J79: 46174 | N79: =IF(ISNUMBER(MATCH(C79,fact_inventaire!$E:$E,0)),"OK","MANQUANT") -> OK
A80: =A79+1 -> 79 | B80: =IF(ISNUMBER(SEARCH(" ",E80)), LEFT(UPPER(E80),2)&MID(UPPER(E80),SEARCH(" ",E80)+1,1), LEFT(UPPER(E80),3)) & TEXT(COUNTIF($E$2:E80,E80),"000") -> JUS010 | C80: JUS PLANET ORANGE 1,2L | D80: =IFERROR(INDEX(dim_categories!$A:$A,MATCH(E80,dim_categories!$C:$C,0)),"") -> 22 | E80: Jus | F80: Bouteille | G80: 6 | H80: =G80/1 -> 6 | I80: TRUE | J80: 46174 | N80: =IF(ISNUMBER(MATCH(C80,fact_inventaire!$E:$E,0)),"OK","MANQUANT") -> OK
A81: =A80+1 -> 80 | B81: =IF(ISNUMBER(SEARCH(" ",E81)), LEFT(UPPER(E81),2)&MID(UPPER(E81),SEARCH(" ",E81)+1,1), LEFT(UPPER(E81),3)) & TEXT(COUNTIF($E$2:E81,E81),"000") -> JUS011 | C81: JUS PLANET ORANGE 0,35L | D81: =IFERROR(INDEX(dim_categories!$A:$A,MATCH(E81,dim_categories!$C:$C,0)),"") -> 22 | E81: Jus | F81: Bouteille | G81: 12 | H81: =G81/1 -> 12 | I81: TRUE | J81: 46174 | N81: =IF(ISNUMBER(MATCH(C81,fact_inventaire!$E:$E,0)),"OK","MANQUANT") -> OK
A82: =A81+1 -> 81 | B82: =IF(ISNUMBER(SEARCH(" ",E82)), LEFT(UPPER(E82),2)&MID(UPPER(E82),SEARCH(" ",E82)+1,1), LEFT(UPPER(E82),3)) & TEXT(COUNTIF($E$2:E82,E82),"000") -> JUS012 | C82: JUS TOP ORANGE PET 0,35L | D82: =IFERROR(INDEX(dim_categories!$A:$A,MATCH(E82,dim_categories!$C:$C,0)),"") -> 22 | E82: Jus | F82: Bouteille | G82: 12 | H82: =G82/1 -> 12 | I82: TRUE | J82: 46174 | N82: =IF(ISNUMBER(MATCH(C82,fact_inventaire!$E:$E,0)),"OK","MANQUANT") -> OK
A83: =A82+1 -> 82 | B83: =IF(ISNUMBER(SEARCH(" ",E83)), LEFT(UPPER(E83),2)&MID(UPPER(E83),SEARCH(" ",E83)+1,1), LEFT(UPPER(E83),3)) & TEXT(COUNTIF($E$2:E83,E83),"000") -> JUS013 | C83: JUS BUBLE UP CHAPHAN 1,2L | D83: =IFERROR(INDEX(dim_categories!$A:$A,MATCH(E83,dim_categories!$C:$C,0)),"") -> 22 | E83: Jus | F83: Bouteille | G83: 6 | H83: =G83/1 -> 6 | I83: TRUE | J83: 46174 | N83: =IF(ISNUMBER(MATCH(C83,fact_inventaire!$E:$E,0)),"OK","MANQUANT") -> OK
A84: =A83+1 -> 83 | B84: =IF(ISNUMBER(SEARCH(" ",E84)), LEFT(UPPER(E84),2)&MID(UPPER(E84),SEARCH(" ",E84)+1,1), LEFT(UPPER(E84),3)) & TEXT(COUNTIF($E$2:E84,E84),"000") -> JUS014 | C84: JUS UCB PAMPLEMOUSSE PET 1L | D84: =IFERROR(INDEX(dim_categories!$A:$A,MATCH(E84,dim_categories!$C:$C,0)),"") -> 22 | E84: Jus | F84: Bouteille | G84: 6 | H84: =G84/1 -> 6 | I84: TRUE | J84: 46174 | N84: =IF(ISNUMBER(MATCH(C84,fact_inventaire!$E:$E,0)),"OK","MANQUANT") -> OK
A85: =A84+1 -> 84 | B85: =IF(ISNUMBER(SEARCH(" ",E85)), LEFT(UPPER(E85),2)&MID(UPPER(E85),SEARCH(" ",E85)+1,1), LEFT(UPPER(E85),3)) & TEXT(COUNTIF($E$2:E85,E85),"000") -> JUS015 | C85: JUS SABC DJINO COKTAIL PET 1L | D85: =IFERROR(INDEX(dim_categories!$A:$A,MATCH(E85,dim_categories!$C:$C,0)),"") -> 22 | E85: Jus | F85: Bouteille | G85: 6 | H85: =G85/1 -> 6 | I85: TRUE | J85: 46174 | N85: =IF(ISNUMBER(MATCH(C85,fact_inventaire!$E:$E,0)),"OK","MANQUANT") -> OK
A86: =A85+1 -> 85 | B86: =IF(ISNUMBER(SEARCH(" ",E86)), LEFT(UPPER(E86),2)&MID(UPPER(E86),SEARCH(" ",E86)+1,1), LEFT(UPPER(E86),3)) & TEXT(COUNTIF($E$2:E86,E86),"000") -> JUS016 | C86: JUS PLANET COKTAIL 1,2L | D86: =IFERROR(INDEX(dim_categories!$A:$A,MATCH(E86,dim_categories!$C:$C,0)),"") -> 22 | E86: Jus | F86: Bouteille | G86: 6 | H86: =G86/1 -> 6 | I86: TRUE | J86: 46174 | N86: =IF(ISNUMBER(MATCH(C86,fact_inventaire!$E:$E,0)),"OK","MANQUANT") -> OK
A87: =A86+1 -> 86 | B87: =IF(ISNUMBER(SEARCH(" ",E87)), LEFT(UPPER(E87),2)&MID(UPPER(E87),SEARCH(" ",E87)+1,1), LEFT(UPPER(E87),3)) & TEXT(COUNTIF($E$2:E87,E87),"000") -> JUS017 | C87: JUS TOP ANANAS BRASSERIE 1L | D87: =IFERROR(INDEX(dim_categories!$A:$A,MATCH(E87,dim_categories!$C:$C,0)),"") -> 22 | E87: Jus | F87: Bouteille | G87: 6 | H87: =G87/1 -> 6 | I87: TRUE | J87: 46174 | N87: =IF(ISNUMBER(MATCH(C87,fact_inventaire!$E:$E,0)),"OK","MANQUANT") -> OK
A88: =A87+1 -> 87 | B88: =IF(ISNUMBER(SEARCH(" ",E88)), LEFT(UPPER(E88),2)&MID(UPPER(E88),SEARCH(" ",E88)+1,1), LEFT(UPPER(E88),3)) & TEXT(COUNTIF($E$2:E88,E88),"000") -> JUS018 | C88: SMINOFF ICE DOUBLE BLACK 0,33L | D88: =IFERROR(INDEX(dim_categories!$A:$A,MATCH(E88,dim_categories!$C:$C,0)),"") -> 22 | E88: Jus | F88: Bouteille | G88: 12 | H88: =G88/1 -> 12 | I88: TRUE | J88: 46174 | N88: =IF(ISNUMBER(MATCH(C88,fact_inventaire!$E:$E,0)),"OK","MANQUANT") -> OK
A89: =A88+1 -> 88 | B89: =IF(ISNUMBER(SEARCH(" ",E89)), LEFT(UPPER(E89),2)&MID(UPPER(E89),SEARCH(" ",E89)+1,1), LEFT(UPPER(E89),3)) & TEXT(COUNTIF($E$2:E89,E89),"000") -> MOU001 | C89: LOTUS TIOF | D89: =IFERROR(INDEX(dim_categories!$A:$A,MATCH(E89,dim_categories!$C:$C,0)),"") -> 23 | E89: Mouchoir | F89: Pièce | G89: 250 | H89: =G89/25 -> 10 | I89: TRUE | J89: 46174 | N89: =IF(ISNUMBER(MATCH(C89,fact_inventaire!$E:$E,0)),"OK","MANQUANT") -> OK
A90: =A89+1 -> 89 | B90: =IF(ISNUMBER(SEARCH(" ",E90)), LEFT(UPPER(E90),2)&MID(UPPER(E90),SEARCH(" ",E90)+1,1), LEFT(UPPER(E90),3)) & TEXT(COUNTIF($E$2:E90,E90),"000") -> MUB001 | C90: MUX COCKTAIL MARGARITA | D90: =IFERROR(INDEX(dim_categories!$A:$A,MATCH(E90,dim_categories!$C:$C,0)),"") -> 24 | E90: Mux Biere | F90: Bouteille | G90: 12 | H90: 6 | I90: TRUE | J90: 46174 | N90: =IF(ISNUMBER(MATCH(C90,fact_inventaire!$E:$E,0)),"OK","MANQUANT") -> OK
A91: =A90+1 -> 90 | B91: =IF(ISNUMBER(SEARCH(" ",E91)), LEFT(UPPER(E91),2)&MID(UPPER(E91),SEARCH(" ",E91)+1,1), LEFT(UPPER(E91),3)) & TEXT(COUNTIF($E$2:E91,E91),"000") -> MUB002 | C91: MUX COCKTAIL GNITO MIX | D91: =IFERROR(INDEX(dim_categories!$A:$A,MATCH(E91,dim_categories!$C:$C,0)),"") -> 24 | E91: Mux Biere | F91: Bouteille | G91: 12 | H91: 6 | I91: TRUE | J91: 46174 | N91: =IF(ISNUMBER(MATCH(C91,fact_inventaire!$E:$E,0)),"OK","MANQUANT") -> OK
A92: =A91+1 -> 91 | B92: =IF(ISNUMBER(SEARCH(" ",E92)), LEFT(UPPER(E92),2)&MID(UPPER(E92),SEARCH(" ",E92)+1,1), LEFT(UPPER(E92),3)) & TEXT(COUNTIF($E$2:E92,E92),"000") -> MUB003 | C92: MUX COCKTAIL MOJITO | D92: =IFERROR(INDEX(dim_categories!$A:$A,MATCH(E92,dim_categories!$C:$C,0)),"") -> 24 | E92: Mux Biere | F92: Bouteille | G92: 12 | H92: 6 | I92: TRUE | J92: 46174 | N92: =IF(ISNUMBER(MATCH(C92,fact_inventaire!$E:$E,0)),"OK","MANQUANT") -> OK
A93: =A92+1 -> 92 | B93: =IF(ISNUMBER(SEARCH(" ",E93)), LEFT(UPPER(E93),2)&MID(UPPER(E93),SEARCH(" ",E93)+1,1), LEFT(UPPER(E93),3)) & TEXT(COUNTIF($E$2:E93,E93),"000") -> MUB004 | C93: MUX COCKTAIL HERBAL MIX | D93: =IFERROR(INDEX(dim_categories!$A:$A,MATCH(E93,dim_categories!$C:$C,0)),"") -> 24 | E93: Mux Biere | F93: Bouteille | G93: 12 | H93: 6 | I93: TRUE | J93: 46174 | N93: =IF(ISNUMBER(MATCH(C93,fact_inventaire!$E:$E,0)),"OK","MANQUANT") -> OK
A94: =A93+1 -> 93 | B94: =IF(ISNUMBER(SEARCH(" ",E94)), LEFT(UPPER(E94),2)&MID(UPPER(E94),SEARCH(" ",E94)+1,1), LEFT(UPPER(E94),3)) & TEXT(COUNTIF($E$2:E94,E94),"000") -> MUB005 | C94: MUX COCKTAIL WHISKO MIX | D94: =IFERROR(INDEX(dim_categories!$A:$A,MATCH(E94,dim_categories!$C:$C,0)),"") -> 24 | E94: Mux Biere | F94: Bouteille | G94: 12 | H94: 6 | I94: TRUE | J94: 46174 | N94: =IF(ISNUMBER(MATCH(C94,fact_inventaire!$E:$E,0)),"OK","MANQUANT") -> OK
A95: =A94+1 -> 94 | B95: =IF(ISNUMBER(SEARCH(" ",E95)), LEFT(UPPER(E95),2)&MID(UPPER(E95),SEARCH(" ",E95)+1,1), LEFT(UPPER(E95),3)) & TEXT(COUNTIF($E$2:E95,E95),"000") -> PAT001 | C95: SPAGHETTI SPAGHETTO 500G | D95: =IFERROR(INDEX(dim_categories!$A:$A,MATCH(E95,dim_categories!$C:$C,0)),"") -> 25 | E95: Pates | F95: Paquet | G95: 20 | H95: =G95/5 -> 4 | I95: TRUE | J95: 46174 | N95: =IF(ISNUMBER(MATCH(C95,fact_inventaire!$E:$E,0)),"OK","MANQUANT") -> OK
A96: =A95+1 -> 95 | B96: =IF(ISNUMBER(SEARCH(" ",E96)), LEFT(UPPER(E96),2)&MID(UPPER(E96),SEARCH(" ",E96)+1,1), LEFT(UPPER(E96),3)) & TEXT(COUNTIF($E$2:E96,E96),"000") -> PAT002 | C96: SPAGHETTI SPAGHETTO 250G | D96: =IFERROR(INDEX(dim_categories!$A:$A,MATCH(E96,dim_categories!$C:$C,0)),"") -> 25 | E96: Pates | F96: Paquet | G96: 40 | H96: =G96/10 -> 4 | I96: TRUE | J96: 46174 | N96: =IF(ISNUMBER(MATCH(C96,fact_inventaire!$E:$E,0)),"OK","MANQUANT") -> OK
A97: =A96+1 -> 96 | B97: =IF(ISNUMBER(SEARCH(" ",E97)), LEFT(UPPER(E97),2)&MID(UPPER(E97),SEARCH(" ",E97)+1,1), LEFT(UPPER(E97),3)) & TEXT(COUNTIF($E$2:E97,E97),"000") -> POM001 | C97: MENTHOLIN | D97: =IFERROR(INDEX(dim_categories!$A:$A,MATCH(E97,dim_categories!$C:$C,0)),"") -> 26 | E97: Pommade | F97: Pièce | G97: 10 | H97: 1 | I97: TRUE | J97: 46174 | N97: =IF(ISNUMBER(MATCH(C97,fact_inventaire!$E:$E,0)),"OK","MANQUANT") -> OK
A98: =A97+1 -> 97 | B98: =IF(ISNUMBER(SEARCH(" ",E98)), LEFT(UPPER(E98),2)&MID(UPPER(E98),SEARCH(" ",E98)+1,1), LEFT(UPPER(E98),3)) & TEXT(COUNTIF($E$2:E98,E98),"000") -> TAB001 | C98: CIGARETTE ASPEN IX50 | D98: =IFERROR(INDEX(dim_categories!$A:$A,MATCH(E98,dim_categories!$C:$C,0)),"") -> 27 | E98: Tabac | F98: Paquet | G98: 20 | H98: =G98/1 -> 20 | I98: TRUE | J98: 46174 | N98: =IF(ISNUMBER(MATCH(C98,fact_inventaire!$E:$E,0)),"OK","MANQUANT") -> OK
A99: =A98+1 -> 98 | B99: =IF(ISNUMBER(SEARCH(" ",E99)), LEFT(UPPER(E99),2)&MID(UPPER(E99),SEARCH(" ",E99)+1,1), LEFT(UPPER(E99),3)) & TEXT(COUNTIF($E$2:E99,E99),"000") -> TAB002 | C99: CIGARETTE BENSON 50X10 | D99: =IFERROR(INDEX(dim_categories!$A:$A,MATCH(E99,dim_categories!$C:$C,0)),"") -> 27 | E99: Tabac | F99: Paquet | G99: 20 | H99: =G99/1 -> 20 | I99: TRUE | J99: 46174 | N99: =IF(ISNUMBER(MATCH(C99,fact_inventaire!$E:$E,0)),"OK","MANQUANT") -> OK
A100: =A99+1 -> 99 | B100: =IF(ISNUMBER(SEARCH(" ",E100)), LEFT(UPPER(E100),2)&MID(UPPER(E100),SEARCH(" ",E100)+1,1), LEFT(UPPER(E100),3)) & TEXT(COUNTIF($E$2:E100,E100),"000") -> TAB003 | C100: CIGARETTE TIME GRIS X5O | D100: =IFERROR(INDEX(dim_categories!$A:$A,MATCH(E100,dim_categories!$C:$C,0)),"") -> 27 | E100: Tabac | F100: Paquet | G100: 20 | H100: =G100/1 -> 20 | I100: TRUE | J100: 46174 | N100: =IF(ISNUMBER(MATCH(C100,fact_inventaire!$E:$E,0)),"OK","MANQUANT") -> OK
...

Sheet dim_lignes_vente
A1: ligne_vente_id | B1: vente_id | C1: produit_id | D1: qte_vente | E1: pu_vente | F1: montant_ligne | G1: cout_unitaire | H1: cout_total | I1: nom_produit
A2: 1 | B2: 1 | C2: =IFERROR(_xlfn.XLOOKUP(I2,dim_produits!$C:$C,dim_produits!$A:$A,""),"") -> 9 | D2: 8 | E2: 750 | F2: =D2*E2 -> 6000 | G2: =_xlfn.XLOOKUP(I2,dim_lignes_achat!$L:$L,dim_lignes_achat!$H:$H,"Nicht gefunden",0) -> 650 | H2: =IF(ISNUMBER(G2),G2*D2,"") -> 5200 | I2: 33 EXPORT 0,65L | L2: =IF(ISNUMBER(MATCH(I2,dim_produits!$C:$C,0)),"OK","MANQUANT") -> OK
A3: =A2+1 -> 2 | B3: 1 | C3: =IFERROR(_xlfn.XLOOKUP(I3,dim_produits!$C:$C,dim_produits!$A:$A,""),"") -> 17 | D3: 3 | E3: 600 | F3: =D3*E3 -> 1800 | G3: =_xlfn.XLOOKUP(I3,dim_lignes_achat!$L:$L,dim_lignes_achat!$H:$H,"Nicht gefunden",0) -> 450 | H3: =IF(ISNUMBER(G3),G3*D3,"") -> 1350 | I3: MANYAN 0,65L | L3: =IF(ISNUMBER(MATCH(I3,dim_produits!$C:$C,0)),"OK","MANQUANT") -> OK
A4: =A3+1 -> 3 | B4: 1 | C4: =IFERROR(_xlfn.XLOOKUP(I4,dim_produits!$C:$C,dim_produits!$A:$A,""),"") -> 72 | D4: 3 | E4: 500 | F4: =D4*E4 -> 1500 | G4: =_xlfn.XLOOKUP(I4,dim_lignes_achat!$L:$L,dim_lignes_achat!$H:$H,"Nicht gefunden",0) -> 416.66667 | H4: =IF(ISNUMBER(G4),G4*D4,"") -> 1250 | I4: JUS TOP ORANGE PET 1L | L4: =IF(ISNUMBER(MATCH(I4,dim_produits!$C:$C,0)),"OK","MANQUANT") -> OK
A5: =A4+1 -> 4 | B5: 1 | C5: =IFERROR(_xlfn.XLOOKUP(I5,dim_produits!$C:$C,dim_produits!$A:$A,""),"") -> 56 | D5: 1 | E5: 900 | F5: =D5*E5 -> 900 | G5: =_xlfn.XLOOKUP(I5,dim_lignes_achat!$L:$L,dim_lignes_achat!$H:$H,"Nicht gefunden",0) -> 650 | H5: =IF(ISNUMBER(G5),G5*D5,"") -> 650 | I5: SMOOTH GUINESS 0,65L | L5: =IF(ISNUMBER(MATCH(I5,dim_produits!$C:$C,0)),"OK","MANQUANT") -> OK
A6: =A5+1 -> 5 | B6: 1 | C6: =IFERROR(_xlfn.XLOOKUP(I6,dim_produits!$C:$C,dim_produits!$A:$A,""),"") -> 54 | D6: 1 | E6: 800 | F6: =D6*E6 -> 800 | G6: =_xlfn.XLOOKUP(I6,dim_lignes_achat!$L:$L,dim_lignes_achat!$H:$H,"Nicht gefunden",0) -> 595.83333 | H6: =IF(ISNUMBER(G6),G6*D6,"") -> 595.83333 | I6: PETIT GUINESS 0,35L | L6: =IF(ISNUMBER(MATCH(I6,dim_produits!$C:$C,0)),"OK","MANQUANT") -> OK
A7: =A6+1 -> 6 | B7: 1 | C7: =IFERROR(_xlfn.XLOOKUP(I7,dim_produits!$C:$C,dim_produits!$A:$A,""),"") -> 52 | D7: 1 | E7: 600 | F7: =D7*E7 -> 600 | G7: =_xlfn.XLOOKUP(I7,dim_lignes_achat!$L:$L,dim_lignes_achat!$H:$H,"Nicht gefunden",0) -> 470.83333 | H7: =IF(ISNUMBER(G7),G7*D7,"") -> 470.83333 | I7: MALTA GUINESS 0,3L | L7: =IF(ISNUMBER(MATCH(I7,dim_produits!$C:$C,0)),"OK","MANQUANT") -> OK
A8: =A7+1 -> 7 | B8: 1 | C8: =IFERROR(_xlfn.XLOOKUP(I8,dim_produits!$C:$C,dim_produits!$A:$A,""),"") -> 18 | D8: 5 | E8: 750 | F8: =D8*E8 -> 3750 | G8: =_xlfn.XLOOKUP(I8,dim_lignes_achat!$L:$L,dim_lignes_achat!$H:$H,"Nicht gefunden",0) -> 650 | H8: =IF(ISNUMBER(G8),G8*D8,"") -> 3250 | I8: MUTZIG 0,65L | L8: =IF(ISNUMBER(MATCH(I8,dim_produits!$C:$C,0)),"OK","MANQUANT") -> OK
A9: =A8+1 -> 8 | B9: 2 | C9: =IFERROR(_xlfn.XLOOKUP(I9,dim_produits!$C:$C,dim_produits!$A:$A,""),"") -> 9 | D9: 2 | E9: 750 | F9: =D9*E9 -> 1500 | G9: =_xlfn.XLOOKUP(I9,dim_lignes_achat!$L:$L,dim_lignes_achat!$H:$H,"Nicht gefunden",0) -> 650 | H9: =IF(ISNUMBER(G9),G9*D9,"") -> 1300 | I9: 33 EXPORT 0,65L | L9: =IF(ISNUMBER(MATCH(I9,dim_produits!$C:$C,0)),"OK","MANQUANT") -> OK
A10: =A9+1 -> 9 | B10: 2 | C10: =IFERROR(_xlfn.XLOOKUP(I10,dim_produits!$C:$C,dim_produits!$A:$A,""),"") -> 17 | D10: 1 | E10: 600 | F10: =D10*E10 -> 600 | G10: =_xlfn.XLOOKUP(I10,dim_lignes_achat!$L:$L,dim_lignes_achat!$H:$H,"Nicht gefunden",0) -> 450 | H10: =IF(ISNUMBER(G10),G10*D10,"") -> 450 | I10: MANYAN 0,65L | L10: =IF(ISNUMBER(MATCH(I10,dim_produits!$C:$C,0)),"OK","MANQUANT") -> OK
A11: =A10+1 -> 10 | B11: 2 | C11: =IFERROR(_xlfn.XLOOKUP(I11,dim_produits!$C:$C,dim_produits!$A:$A,""),"") -> 72 | D11: 6 | E11: 500 | F11: =D11*E11 -> 3000 | G11: =_xlfn.XLOOKUP(I11,dim_lignes_achat!$L:$L,dim_lignes_achat!$H:$H,"Nicht gefunden",0) -> 416.66667 | H11: =IF(ISNUMBER(G11),G11*D11,"") -> 2500 | I11: JUS TOP ORANGE PET 1L | L11: =IF(ISNUMBER(MATCH(I11,dim_produits!$C:$C,0)),"OK","MANQUANT") -> OK
A12: =A11+1 -> 11 | B12: 2 | C12: =IFERROR(_xlfn.XLOOKUP(I12,dim_produits!$C:$C,dim_produits!$A:$A,""),"") -> 54 | D12: 6 | E12: 800 | F12: =D12*E12 -> 4800 | G12: =_xlfn.XLOOKUP(I12,dim_lignes_achat!$L:$L,dim_lignes_achat!$H:$H,"Nicht gefunden",0) -> 595.83333 | H12: =IF(ISNUMBER(G12),G12*D12,"") -> 3575 | I12: PETIT GUINESS 0,35L | L12: =IF(ISNUMBER(MATCH(I12,dim_produits!$C:$C,0)),"OK","MANQUANT") -> OK
A13: =A12+1 -> 12 | B13: 2 | C13: =IFERROR(_xlfn.XLOOKUP(I13,dim_produits!$C:$C,dim_produits!$A:$A,""),"") -> 16 | D13: 2 | E13: 750 | F13: =D13*E13 -> 1500 | G13: =_xlfn.XLOOKUP(I13,dim_lignes_achat!$L:$L,dim_lignes_achat!$H:$H,"Nicht gefunden",0) -> 650 | H13: =IF(ISNUMBER(G13),G13*D13,"") -> 1300 | I13: KADJI BIER 0,65L | L13: =IF(ISNUMBER(MATCH(I13,dim_produits!$C:$C,0)),"OK","MANQUANT") -> OK
A14: =A13+1 -> 13 | B14: 2 | C14: =IFERROR(_xlfn.XLOOKUP(I14,dim_produits!$C:$C,dim_produits!$A:$A,""),"") -> 12 | D14: 3 | E14: 750 | F14: =D14*E14 -> 2250 | G14: =_xlfn.XLOOKUP(I14,dim_lignes_achat!$L:$L,dim_lignes_achat!$H:$H,"Nicht gefunden",0) -> 650 | H14: =IF(ISNUMBER(G14),G14*D14,"") -> 1950 | I14: DOPPEL 0,65L | L14: =IF(ISNUMBER(MATCH(I14,dim_produits!$C:$C,0)),"OK","MANQUANT") -> OK
... A125: =A124+1 -> 124 | B125: 11 | C125: =IFERROR(_xlfn.XLOOKUP(I125,dim_produits!$C:$C,dim_produits!$A:$A,""),"") -> 52 | D125: 6 | E125: 600 | F125: =D125*E125 -> 3600 | G125: =_xlfn.XLOOKUP(I125,dim_lignes_achat!$L:$L,dim_lignes_achat!$H:$H,"Nicht gefunden",0) -> 470.83333 | H125: =IF(ISNUMBER(G125),G125*D125,"") -> 2825 | I125: MALTA GUINESS 0,3L | L125: =IF(ISNUMBER(MATCH(I125,dim_produits!$C:$C,0)),"OK","MANQUANT") -> OK
A126: =A125+1 -> 125 | B126: 11 | C126: =IFERROR(_xlfn.XLOOKUP(I126,dim_produits!$C:$C,dim_produits!$A:$A,""),"") -> 12 | D126: 5 | E126: =3750/5 -> 750 | F126: =D126*E126 -> 3750 | G126: =_xlfn.XLOOKUP(I126,dim_lignes_achat!$L:$L,dim_lignes_achat!$H:$H,"Nicht gefunden",0) -> 650 | H126: =IF(ISNUMBER(G126),G126*D126,"") -> 3250 | I126: DOPPEL 0,65L | L126: =IF(ISNUMBER(MATCH(I126,dim_produits!$C:$C,0)),"OK","MANQUANT") -> OK
A127: =A126+1 -> 126 | B127: 12 | C127: =IFERROR(_xlfn.XLOOKUP(I127,dim_produits!$C:$C,dim_produits!$A:$A,""),"") -> 88 | D127: 1 | E127: 100 | F127: =D127*E127 -> 100 | G127: =_xlfn.XLOOKUP(I127,dim_lignes_achat!$L:$L,dim_lignes_achat!$H:$H,"Nicht gefunden",0) -> 66 | H127: =IF(ISNUMBER(G127),G127*D127,"") -> 66 | I127: LOTUS TIOF | L127: =IF(ISNUMBER(MATCH(I127,dim_produits!$C:$C,0)),"OK","MANQUANT") -> OK
A128: =A127+1 -> 127 | B128: 12 | C128: =IFERROR(_xlfn.XLOOKUP(I128,dim_produits!$C:$C,dim_produits!$A:$A,""),"") -> 18 | D128: 1 | E128: 750 | F128: =D128*E128 -> 750 | G128: =_xlfn.XLOOKUP(I128,dim_lignes_achat!$L:$L,dim_lignes_achat!$H:$H,"Nicht gefunden",0) -> 650 | H128: =IF(ISNUMBER(G128),G128*D128,"") -> 650 | I128: MUTZIG 0,65L | L128: =IF(ISNUMBER(MATCH(I128,dim_produits!$C:$C,0)),"OK","MANQUANT") -> OK
A129: =A128+1 -> 128 | B129: 12 | C129: =IFERROR(_xlfn.XLOOKUP(I129,dim_produits!$C:$C,dim_produits!$A:$A,""),"") -> 12 | D129: 6 | E129: 750 | F129: =D129*E129 -> 4500 | G129: =_xlfn.XLOOKUP(I129,dim_lignes_achat!$L:$L,dim_lignes_achat!$H:$H,"Nicht gefunden",0) -> 650 | H129: =IF(ISNUMBER(G129),G129*D129,"") -> 3900 | I129: DOPPEL 0,65L | L129: =IF(ISNUMBER(MATCH(I129,dim_produits!$C:$C,0)),"OK","MANQUANT") -> OK
A130: =A129+1 -> 129 | B130: 12 | C130: =IFERROR(_xlfn.XLOOKUP(I130,dim_produits!$C:$C,dim_produits!$A:$A,""),"") -> 7 | D130: 10 | E130: 750 | F130: =D130*E130 -> 7500 | G130: =_xlfn.XLOOKUP(I130,dim_lignes_achat!$L:$L,dim_lignes_achat!$H:$H,"Nicht gefunden",0) -> 600 | H130: =IF(ISNUMBER(G130),G130*D130,"") -> 6000 | I130: BOSTER COLA 0,65L | L130: =IF(ISNUMBER(MATCH(I130,dim_produits!$C:$C,0)),"OK","MANQUANT") -> OK
A131: =A130+1 -> 130 | B131: 12 | C131: =IFERROR(_xlfn.XLOOKUP(I131,dim_produits!$C:$C,dim_produits!$A:$A,""),"") -> 54 | D131: 4 | E131: 800 | F131: =D131*E131 -> 3200 | G131: =_xlfn.XLOOKUP(I131,dim_lignes_achat!$L:$L,dim_lignes_achat!$H:$H,"Nicht gefunden",0) -> 595.83333 | H131: =IF(ISNUMBER(G131),G131*D131,"") -> 2383.3333 | I131: PETIT GUINESS 0,35L | L131: =IF(ISNUMBER(MATCH(I131,dim_produits!$C:$C,0)),"OK","MANQUANT") -> OK
A132: =A131+1 -> 131 | B132: 12 | C132: =IFERROR(_xlfn.XLOOKUP(I132,dim_produits!$C:$C,dim_produits!$A:$A,""),"") -> 52 | D132: 1 | E132: 600 | F132: =D132*E132 -> 600 | G132: =_xlfn.XLOOKUP(I132,dim_lignes_achat!$L:$L,dim_lignes_achat!$H:$H,"Nicht gefunden",0) -> 470.83333 | H132: =IF(ISNUMBER(G132),G132*D132,"") -> 470.83333 | I132: MALTA GUINESS 0,3L | L132: =IF(ISNUMBER(MATCH(I132,dim_produits!$C:$C,0)),"OK","MANQUANT") -> OK
A133: =A132+1 -> 132 | B133: 13 | C133: =IFERROR(_xlfn.XLOOKUP(I133,dim_produits!$C:$C,dim_produits!$A:$A,""),"") -> 17 | D133: 12 | E133: 600 | F133: =D133*E133 -> 7200 | G133: =_xlfn.XLOOKUP(I133,dim_lignes_achat!$L:$L,dim_lignes_achat!$H:$H,"Nicht gefunden",0) -> 450 | H133: =IF(ISNUMBER(G133),G133*D133,"") -> 5400 | I133: MANYAN 0,65L | L133: =IF(ISNUMBER(MATCH(I133,dim_produits!$C:$C,0)),"OK","MANQUANT") -> OK
A134: =A133+1 -> 133 | B134: 13 | C134: =IFERROR(_xlfn.XLOOKUP(I134,dim_produits!$C:$C,dim_produits!$A:$A,""),"") -> 9 | D134: 11 | E134: 750 | F134: =D134*E134 -> 8250 | G134: =_xlfn.XLOOKUP(I134,dim_lignes_achat!$L:$L,dim_lignes_achat!$H:$H,"Nicht gefunden",0) -> 650 | H134: =IF(ISNUMBER(G134),G134*D134,"") -> 7150 | I134: 33 EXPORT 0,65L | L134: =IF(ISNUMBER(MATCH(I134,dim_produits!$C:$C,0)),"OK","MANQUANT") -> OK
A135: =A134+1 -> 134 | B135: 13 | C135: =IFERROR(_xlfn.XLOOKUP(I135,dim_produits!$C:$C,dim_produits!$A:$A,""),"") -> 52 | D135: 3 | E135: 600 | F135: =D135*E135 -> 1800 | G135: =_xlfn.XLOOKUP(I135,dim_lignes_achat!$L:$L,dim_lignes_achat!$H:$H,"Nicht gefunden",0) -> 470.83333 | H135: =IF(ISNUMBER(G135),G135*D135,"") -> 1412.5 | I135: MALTA GUINESS 0,3L | L135: =IF(ISNUMBER(MATCH(I135,dim_produits!$C:$C,0)),"OK","MANQUANT") -> OK
A136: =A135+1 -> 135 | B136: 13 | C136: =IFERROR(_xlfn.XLOOKUP(I136,dim_produits!$C:$C,dim_produits!$A:$A,""),"") -> 74 | D136: 2 | E136: 800 | F136: =D136*E136 -> 1600 | G136: =_xlfn.XLOOKUP(I136,dim_lignes_achat!$L:$L,dim_lignes_achat!$H:$H,"Nicht gefunden",0) -> 700 | H136: =IF(ISNUMBER(G136),G136*D136,"") -> 1400 | I136: JUS SABS VIMTO 1L | L136: =IF(ISNUMBER(MATCH(I136,dim_produits!$C:$C,0)),"OK","MANQUANT") -> OK
A137: =A136+1 -> 136 | B137: 13 | C137: =IFERROR(_xlfn.XLOOKUP(I137,dim_produits!$C:$C,dim_produits!$A:$A,""),"") -> 7 | D137: 18 | E137: 750 | F137: =D137*E137 -> 13500 | G137: =_xlfn.XLOOKUP(I137,dim_lignes_achat!$L:$L,dim_lignes_achat!$H:$H,"Nicht gefunden",0) -> 600 | H137: =IF(ISNUMBER(G137),G137*D137,"") -> 10800 | I137: BOSTER COLA 0,65L | L137: =IF(ISNUMBER(MATCH(I137,dim_produits!$C:$C,0)),"OK","MANQUANT") -> OK
A138: =A137+1 -> 137 | B138: 13 | C138: =IFERROR(_xlfn.XLOOKUP(I138,dim_produits!$C:$C,dim_produits!$A:$A,""),"") -> 84 | D138: 1 | E138: 700 | F138: =D138*E138 -> 700 | G138: =_xlfn.XLOOKUP(I138,dim_lignes_achat!$L:$L,dim_lignes_achat!$H:$H,"Nicht gefunden",0) -> 583.33333 | H138: =IF(ISNUMBER(G138),G138*D138,"") -> 583.33333 | I138: JUS SABC DJINO COKTAIL PET 1L | L138: =IF(ISNUMBER(MATCH(I138,dim_produits!$C:$C,0)),"OK","MANQUANT") -> OK
... A399: =A398+1 -> 398 | B399: 25 | C399: =IFERROR(_xlfn.XLOOKUP(I399,dim_produits!$C:$C,dim_produits!$A:$A,""),"") -> 16 | D399: 2 | E399: 750 | F399: =D399*E399 -> 1500 | G399: =_xlfn.XLOOKUP(I399,dim_lignes_achat!$L:$L,dim_lignes_achat!$H:$H,"Nicht gefunden",0) -> 650 | H399: =IF(ISNUMBER(G399),G399*D399,"") -> 1300 | I399: KADJI BIER 0,65L | L399: =IF(ISNUMBER(MATCH(I399,dim_produits!$C:$C,0)),"OK","MANQUANT") -> OK

Sheet fact_ventes
A1: vente_id | B1: date_vente | C1: date_id | D1: vendeur_id | E1: total_vente
A2: 1 | B2: 46175 | C2: 46175 | D2: 10 | E2: =SUMIF(dim_lignes_vente!B:B,A2,dim_lignes_vente!F:F) -> 15350
A3: =A2+1 -> 2 | B3: 46176 | C3: 46176 | D3: 10 | E3: =SUMIF(dim_lignes_vente!B:B,A3,dim_lignes_vente!F:F) -> 17550
A4: =A3+1 -> 3 | B4: 46177 | C4: 46177 | D4: 10 | E4: =SUMIF(dim_lignes_vente!B:B,A4,dim_lignes_vente!F:F) -> 9550
A5: =A4+1 -> 4 | B5: 46178 | C5: 46178 | D5: 10 | E5: =SUMIF(dim_lignes_vente!B:B,A5,dim_lignes_vente!F:F) -> 9600
A6: =A5+1 -> 5 | B6: 46179 | C6: 46179 | D6: 10 | E6: =SUMIF(dim_lignes_vente!B:B,A6,dim_lignes_vente!F:F) -> 82750
A7: =A6+1 -> 6 | B7: 46180 | C7: 46180 | D7: 10 | E7: =SUMIF(dim_lignes_vente!B:B,A7,dim_lignes_vente!F:F) -> 70100
A8: =A7+1 -> 7 | B8: 46182 | C8: 46182 | D8: 10 | E8: =SUMIF(dim_lignes_vente!B:B,A8,dim_lignes_vente!F:F) -> 85400
A9: =A8+1 -> 8 | B9: 46183 | C9: 46183 | D9: 10 | E9: =SUMIF(dim_lignes_vente!B:B,A9,dim_lignes_vente!F:F) -> 34150
A10: =A9+1 -> 9 | B10: 46184 | C10: 46184 | D10: 10 | E10: =SUMIF(dim_lignes_vente!B:B,A10,dim_lignes_vente!F:F) -> 55850
A11: =A10+1 -> 10 | B11: 46185 | C11: 46185 | D11: 10 | E11: =SUMIF(dim_lignes_vente!B:B,A11,dim_lignes_vente!F:F) -> 12700
A12: =A11+1 -> 11 | B12: 46186 | C12: 46186 | D12: 10 | E12: =SUMIF(dim_lignes_vente!B:B,A12,dim_lignes_vente!F:F) -> 45000
A13: =A12+1 -> 12 | B13: 46187 | C13: 46187 | D13: 10 | E13: =SUMIF(dim_lignes_vente!B:B,A13,dim_lignes_vente!F:F) -> 16650
A14: =A13+1 -> 13 | B14: 46189 | C14: 46189 | D14: 10 | E14: =SUMIF(dim_lignes_vente!B:B,A14,dim_lignes_vente!F:F) -> 45200
... A26: =A25+1 -> 25 | B26: 46203 | C26: 46203 | D26: 10 | E26: =SUMIF(dim_lignes_vente!B:B,A26,dim_lignes_vente!F:F) -> 163325

Sheet dim_lignes_achat
A1: ligne_achat_id | B1: achat_id | C1: produit_id | D1: qte_cartons | E1: qte_par_carton | F1: quantite_achat | G1: pu_achat_carton | H1: pu_achat_piece | I1: total_achat | J1: date_fabrication | K1: date_peremption | L1: nom_produit
A2: 1 | B2: 1 | C2: =IFERROR(_xlfn.XLOOKUP(L2,dim_produits!$C:$C,dim_produits!$A:$A,""),"") -> 36 | D2: =F2/E2 -> 4.8333333 | E2: 6 | F2: 29 | G2: 1200 | H2: =G2/E2 -> 200 | I2: =G2*D2 -> 5800 | J2: 46143 | K2: 46265 | L2: EAU MINERAL OPUR 1,5L | N2: =IF(ISNUMBER(MATCH(L2,dim_produits!$C:$C,0)),"OK","MANQUANT") -> OK
A3: =A2+1 -> 2 | B3: 1 | C3: =IFERROR(_xlfn.XLOOKUP(L3,dim_produits!$C:$C,dim_produits!$A:$A,""),"") -> 90 | D3: =F3/E3 -> 1.0833333 | E3: 12 | F3: 13 | G3: 4960 | H3: =G3/E3 -> 413.33333 | I3: =G3*D3 -> 5373.3333 | J3: 46143 | K3: 46265 | L3: MUX COCKTAIL GNITO MIX | N3: =IF(ISNUMBER(MATCH(L3,dim_produits!$C:$C,0)),"OK","MANQUANT") -> OK
A4: =A3+1 -> 3 | B4: 1 | C4: =IFERROR(_xlfn.XLOOKUP(L4,dim_produits!$C:$C,dim_produits!$A:$A,""),"") -> 91 | D4: =F4/E4 -> 0.41666667 | E4: 12 | F4: 5 | G4: 4960 | H4: =G4/E4 -> 413.33333 | I4: =G4*D4 -> 2066.6667 | J4: 46143 | K4: 46265 | L4: MUX COCKTAIL MOJITO | N4: =IF(ISNUMBER(MATCH(L4,dim_produits!$C:$C,0)),"OK","MANQUANT") -> OK
A5: =A4+1 -> 4 | B5: 1 | C5: =IFERROR(_xlfn.XLOOKUP(L5,dim_produits!$C:$C,dim_produits!$A:$A,""),"") -> 79 | D5: =F5/E5 -> 3.6666667 | E5: 6 | F5: 22 | G5: 2400 | H5: =G5/E5 -> 400 | I5: =G5*D5 -> 8800 | J5: 46143 | K5: 46265 | L5: JUS PLANET ORANGE 1,2L | N5: =IF(ISNUMBER(MATCH(L5,dim_produits!$C:$C,0)),"OK","MANQUANT") -> OK
A6: =A5+1 -> 5 | B6: 1 | C6: =IFERROR(_xlfn.XLOOKUP(L6,dim_produits!$C:$C,dim_produits!$A:$A,""),"") -> 52 | D6: =F6/E6 -> 0.66666667 | E6: 24 | F6: 16 | G6: 11300 | H6: =G6/E6 -> 470.83333 | I6: =G6*D6 -> 7533.3333 | J6: 46143 | K6: 46265 | L6: MALTA GUINESS 0,3L | N6: =IF(ISNUMBER(MATCH(L6,dim_produits!$C:$C,0)),"OK","MANQUANT") -> OK
A7: =A6+1 -> 6 | B7: 1 | C7: =IFERROR(_xlfn.XLOOKUP(L7,dim_produits!$C:$C,dim_produits!$A:$A,""),"") -> 56 | D7: =F7/E7 -> 1 | E7: 15 | F7: 15 | G7: 9750 | H7: =G7/E7 -> 650 | I7: =G7*D7 -> 9750 | J7: 46143 | K7: 46265 | L7: SMOOTH GUINESS 0,65L | N7: =IF(ISNUMBER(MATCH(L7,dim_produits!$C:$C,0)),"OK","MANQUANT") -> OK
A8: =A7+1 -> 7 | B8: 1 | C8: =IFERROR(_xlfn.XLOOKUP(L8,dim_produits!$C:$C,dim_produits!$A:$A,""),"") -> 74 | D8: =F8/E8 -> 2.5 | E8: 6 | F8: 15 | G8: 4200 | H8: =G8/E8 -> 700 | I8: =F8*H8 -> 10500 | J8: 46143 | K8: 46265 | L8: JUS SABS VIMTO 1L | N8: =IF(ISNUMBER(MATCH(L8,dim_produits!$C:$C,0)),"OK","MANQUANT") -> OK
A9: =A8+1 -> 8 | B9: 1 | C9: =IFERROR(_xlfn.XLOOKUP(L9,dim_produits!$C:$C,dim_produits!$A:$A,""),"") -> 88 | D9: =F9/E9 -> 0.15 | E9: 100 | F9: 15 | G9: =H9*E9 -> 6600 | H9: 66 | I9: =F9*H9 -> 990 | J9: 46143 | K9: 46265 | L9: LOTUS TIOF | N9: =IF(ISNUMBER(MATCH(L9,dim_produits!$C:$C,0)),"OK","MANQUANT") -> OK
A10: =A9+1 -> 9 | B10: 1 | C10: =IFERROR(_xlfn.XLOOKUP(L10,dim_produits!$C:$C,dim_produits!$A:$A,""),"") -> 51 | D10: =F10/E10 -> 0.91666667 | E10: 12 | F10: 11 | G10: 11900 | H10: =G10/E10 -> 991.66667 | I10: =G10*D10 -> 10908.333 | J10: 46143 | K10: 46265 | L10: GRAND GUINESS 0,65L | N10: =IF(ISNUMBER(MATCH(L10,dim_produits!$C:$C,0)),"OK","MANQUANT") -> OK
A11: =A10+1 -> 10 | B11: 1 | C11: =IFERROR(_xlfn.XLOOKUP(L11,dim_produits!$C:$C,dim_produits!$A:$A,""),"") -> 5 | D11: =F11/E11 -> 1.1 | E11: 10 | F11: 11 | G11: 1999.98 | H11: =G11/E11 -> 199.998 | I11: =G11*D11 -> 2199.978 | J11: 46143 | K11: 46265 | L11: JUS REAKTOR DARK POWER PET 0,5L | N11: =IF(ISNUMBER(MATCH(L11,dim_produits!$C:$C,0)),"OK","MANQUANT") -> OK
A12: =A11+1 -> 11 | B12: 1 | C12: =IFERROR(_xlfn.XLOOKUP(L12,dim_produits!$C:$C,dim_produits!$A:$A,""),"") -> 72 | D12: =F12/E12 -> 1.1666667 | E12: 6 | F12: 7 | G12: 2500 | H12: =G12/E12 -> 416.66667 | I12: =G12*D12 -> 2916.6667 | J12: 46143 | K12: 46265 | L12: JUS TOP ORANGE PET 1L | N12: =IF(ISNUMBER(MATCH(L12,dim_produits!$C:$C,0)),"OK","MANQUANT") -> OK
A13: =A12+1 -> 12 | B13: 1 | C13: =IFERROR(_xlfn.XLOOKUP(L13,dim_produits!$C:$C,dim_produits!$A:$A,""),"") -> 12 | D13: =F13/E13 -> 0.5 | E13: 12 | F13: 6 | G13: 7800 | H13: =G13/E13 -> 650 | I13: =G13*D13 -> 3900 | J13: 46143 | K13: 46265 | L13: DOPPEL 0,65L | N13: =IF(ISNUMBER(MATCH(L13,dim_produits!$C:$C,0)),"OK","MANQUANT") -> OK
A14: =A13+1 -> 13 | B14: 1 | C14: =IFERROR(_xlfn.XLOOKUP(L14,dim_produits!$C:$C,dim_produits!$A:$A,""),"") -> 89 | D14: =F14/E14 -> 0.75 | E14: 12 | F14: 9 | G14: 6200 | H14: =G14/E14 -> 516.66667 | I14: =G14*D14 -> 4650 | J14: 46143 | K14: 46265 | L14: MUX COCKTAIL MARGARITA | N14: =IF(ISNUMBER(MATCH(L14,dim_produits!$C:$C,0)),"OK","MANQUANT") -> OK
A15: =A14+1 -> 14 | B15: 1 | C15: =IFERROR(_xlfn.XLOOKUP(L15,dim_produits!$C:$C,dim_produits!$A:$A,""),"") -> 52 | D15: =F15/E15 -> 0.20833333 | E15: 24 | F15: 5 | G15: 11300 | H15: =G15/E15 -> 470.83333 | I15: =G15*D15 -> 2354.1667 | J15: 46143 | K15: 46265 | L15: MALTA GUINESS 0,3L | N15: =IF(ISNUMBER(MATCH(L15,dim_produits!$C:$C,0)),"OK","MANQUANT") -> OK
A16: =A15+1 -> 15 | B16: 1 | C16: =IFERROR(_xlfn.XLOOKUP(L16,dim_produits!$C:$C,dim_produits!$A:$A,""),"") -> 11 | D16: =F16/E16 -> 0.25 | E16: 12 | F16: 3 | G16: 7800 | H16: =G16/E16 -> 650 | I16: =G16*D16 -> 1950 | J16: 46143 | K16: 46265 | L16: CASTEL 0,5L | N16: =IF(ISNUMBER(MATCH(L16,dim_produits!$C:$C,0)),"OK","MANQUANT") -> OK
A17: =A16+1 -> 16 | B17: 1 | C17: =IFERROR(_xlfn.XLOOKUP(L17,dim_produits!$C:$C,dim_produits!$A:$A,""),"") -> 16 | D17: =F17/E17 -> 0.25 | E17: 12 | F17: 3 | G17: 7800 | H17: =G17/E17 -> 650 | I17: =G17*D17 -> 1950 | J17: 46143 | K17: 46265 | L17: KADJI BIER 0,65L | N17: =IF(ISNUMBER(MATCH(L17,dim_produits!$C:$C,0)),"OK","MANQUANT") -> OK
A18: =A17+1 -> 17 | B18: 1 | C18: =IFERROR(_xlfn.XLOOKUP(L18,dim_produits!$C:$C,dim_produits!$A:$A,""),"") -> 10 | D18: =F18/E18 -> 0.16666667 | E18: 12 | F18: 2 | G18: 7150 | H18: =G18/E18 -> 595.83333 | I18: =G18*D18 -> 1191.6667 | J18: 46143 | K18: 46265 | L18: BEAUFORT ORDINAIRE 0,65L | N18: =IF(ISNUMBER(MATCH(L18,dim_produits!$C:$C,0)),"OK","MANQUANT") -> OK
A19: =A18+1 -> 18 | B19: 1 | C19: =IFERROR(_xlfn.XLOOKUP(L19,dim_produits!$C:$C,dim_produits!$A:$A,""),"") -> 9 | D19: =F19/E19 -> 0.083333333 | E19: 12 | F19: 1 | G19: 7800 | H19: =G19/E19 -> 650 | I19: =G19*D19 -> 650 | J19: 46143 | K19: 46265 | L19: 33 EXPORT 0,65L | N19: =IF(ISNUMBER(MATCH(L19,dim_produits!$C:$C,0)),"OK","MANQUANT") -> OK
A20: =A19+1 -> 19 | B20: 1 | C20: =IFERROR(_xlfn.XLOOKUP(L20,dim_produits!$C:$C,dim_produits!$A:$A,""),"") -> 13 | D20: =F20/E20 -> 1.5833333 | E20: 12 | F20: 19 | G20: =H20*E20 -> 8400 | H20: 700 | I20: =F20*H20 -> 13300 | J20: 46143 | K20: 46265 | L20: HARP BRASSERIE 0,6L | N20: =IF(ISNUMBER(MATCH(L20,dim_produits!$C:$C,0)),"OK","MANQUANT") -> OK
A21: =A20+1 -> 20 | B21: 1 | C21: =IFERROR(_xlfn.XLOOKUP(L21,dim_produits!$C:$C,dim_produits!$A:$A,""),"") -> 50 | D21: =F21/E21 -> 3.1666667 | E21: 12 | F21: 38 | G21: =H21*E21 -> 540 | H21: 45 | I21: =F21*H21 -> 1710 | J21: 46143 | K21: 46265 | L21: TAILLE CRAYON | N21: =IF(ISNUMBER(MATCH(L21,dim_produits!$C:$C,0)),"OK","MANQUANT") -> OK
A22: =A21+1 -> 21 | B22: 1 | C22: =IFERROR(_xlfn.XLOOKUP(L22,dim_produits!$C:$C,dim_produits!$A:$A,""),"") -> 47 | D22: =F22/E22 -> 1.0833333 | E22: 12 | F22: 13 | G22: =H22*E22 -> 1080 | H22: 90 | I22: =F22*H22 -> 1170 | J22: 46143 | K22: 46265 | L22: CAOUTCHOUC | N22: =IF(ISNUMBER(MATCH(L22,dim_produits!$C:$C,0)),"OK","MANQUANT") -> OK
A23: =A22+1 -> 22 | B23: 1 | C23: =IFERROR(_xlfn.XLOOKUP(L23,dim_produits!$C:$C,dim_produits!$A:$A,""),"") -> 96 | D23: =F23/E23 -> 1 | E23: 12 | F23: 12 | G23: =H23*E23 -> 540 | H23: 45 | I23: =F23*H23 -> 540 | J23: 46143 | K23: 46265 | L23: MENTHOLIN | N23: =IF(ISNUMBER(MATCH(L23,dim_produits!$C:$C,0)),"OK","MANQUANT") -> OK
A24: =A23+1 -> 23 | B24: 1 | C24: =IFERROR(_xlfn.XLOOKUP(L24,dim_produits!$C:$C,dim_produits!$A:$A,""),"") -> 48 | D24: =F24/E24 -> 0.75 | E24: 12 | F24: 9 | G24: =H24*E24 -> 1080 | H24: 90 | I24: =F24*H24 -> 810 | J24: 46143 | K24: 46265 | L24: EPINGLE | N24: =IF(ISNUMBER(MATCH(L24,dim_produits!$C:$C,0)),"OK","MANQUANT") -> OK
A25: =A24+1 -> 24 | B25: 1 | C25: =IFERROR(_xlfn.XLOOKUP(L25,dim_produits!$C:$C,dim_produits!$A:$A,""),"") -> 42 | D25: =F25/E25 -> 1 | E25: 6 | F25: 6 | G25: =H25*E25 -> 2700 | H25: 450 | I25: =F25*H25 -> 2700 | J25: 46143 | K25: 46265 | L25: CIRAGE LIQUIDE | N25: =IF(ISNUMBER(MATCH(L25,dim_produits!$C:$C,0)),"OK","MANQUANT") -> OK
A26: =A25+1 -> 25 | B26: 1 | C26: =IFERROR(_xlfn.XLOOKUP(L26,dim_produits!$C:$C,dim_produits!$A:$A,""),"") -> 49 | D26: =F26/E26 -> 0.25 | E26: 12 | F26: 3 | G26: =H26*E26 -> 2160 | H26: 180 | I26: =F26*H26 -> 540 | J26: 46143 | K26: 46265 | L26: RÈGLE GRADUE | N26: =IF(ISNUMBER(MATCH(L26,dim_produits!$C:$C,0)),"OK","MANQUANT") -> OK
A27: =A26+1 -> 26 | B27: 1 | C27: =IFERROR(_xlfn.XLOOKUP(L27,dim_produits!$C:$C,dim_produits!$A:$A,""),"") -> 37 | D27: =F27/E27 -> 0.25 | E27: 12 | F27: 3 | G27: =H27*E27 -> 10800 | H27: 900 | I27: =F27*H27 -> 2700 | J27: 46143 | K27: 46265 | L27: AMPOULE REGRETTE | N27: =IF(ISNUMBER(MATCH(L27,dim_produits!$C:$C,0)),"OK","MANQUANT") -> OK
A28: =A27+1 -> 27 | B28: 1 | C28: =IFERROR(_xlfn.XLOOKUP(L28,dim_produits!$C:$C,dim_produits!$A:$A,""),"") -> 65 | D28: =F28/E28 -> 0.16666667 | E28: 12 | F28: 2 | G28: =H28*E28 -> 5400 | H28: 450 | I28: =F28*H28 -> 900 | J28: 46143 | K28: 46265 | L28: BABOUCHE DE TOILETTE | N28: =IF(ISNUMBER(MATCH(L28,dim_produits!$C:$C,0)),"OK","MANQUANT") -> OK
A29: =A28+1 -> 28 | B29: 1 | C29: =IFERROR(_xlfn.XLOOKUP(L29,dim_produits!$C:$C,dim_produits!$A:$A,""),"") -> 38 | D29: =F29/E29 -> 0.33333333 | E29: 6 | F29: 2 | G29: =H29*E29 -> 13500 | H29: 2250 | I29: =F29*H29 -> 4500 | J29: 46143 | K29: 46265 | L29: RALONGE ELECTRIQUE | N29: =IF(ISNUMBER(MATCH(L29,dim_produits!$C:$C,0)),"OK","MANQUANT") -> OK
A30: =A29+1 -> 29 | B30: 1 | C30: =IFERROR(_xlfn.XLOOKUP(L30,dim_produits!$C:$C,dim_produits!$A:$A,""),"") -> 39 | D30: =F30/E30 -> 0.41666667 | E30: 12 | F30: 5 | G30: =H30*E30 -> 900 | H30: 75 | I30: =F30*H30 -> 375 | J30: 46143 | K30: 46265 | L30: PLASTIQUE | N30: =IF(ISNUMBER(MATCH(L30,dim_produits!$C:$C,0)),"OK","MANQUANT") -> OK
A31: =A30+1 -> 30 | B31: 1 | C31: =IFERROR(_xlfn.XLOOKUP(L31,dim_produits!$C:$C,dim_produits!$A:$A,""),"") -> 105 | D31: =F31/E31 -> 0.58333333 | E31: 12 | F31: 7 | G31: =H31*E31 -> 360 | H31: 30 | I31: =F31*H31 -> 210 | J31: 46143 | K31: 46265 | L31: TIGER RAZOR | N31: =IF(ISNUMBER(MATCH(L31,dim_produits!$C:$C,0)),"OK","MANQUANT") -> OK
A32: =A31+1 -> 31 | B32: 2 | C32: =IFERROR(_xlfn.XLOOKUP(L32,dim_produits!$C:$C,dim_produits!$A:$A,""),"") -> 9 | D32: 3 | E32: 12 | F32: =D32*E32 -> 36 | G32: 7200 | H32: =G32/E32 -> 600 | I32: =G32*D32 -> 21600 | J32: 46143 | K32: 46265 | L32: 33 EXPORT 0,65L | N32: =IF(ISNUMBER(MATCH(L32,dim_produits!$C:$C,0)),"OK","MANQUANT") -> OK
A33: =A32+1 -> 32 | B33: 2 | C33: =IFERROR(_xlfn.XLOOKUP(L33,dim_produits!$C:$C,dim_produits!$A:$A,""),"") -> 11 | D33: 2 | E33: 12 | F33: =D33*E33 -> 24 | G33: 7200 | H33: =G33/E33 -> 600 | I33: =G33*D33 -> 14400 | J33: 46143 | K33: 46265 | L33: CASTEL 0,5L | N33: =IF(ISNUMBER(MATCH(L33,dim_produits!$C:$C,0)),"OK","MANQUANT") -> OK
A34: =A33+1 -> 33 | B34: 2 | C34: =IFERROR(_xlfn.XLOOKUP(L34,dim_produits!$C:$C,dim_produits!$A:$A,""),"") -> 53 | D34: 2 | E34: 12 | F34: =D34*E34 -> 24 | G34: 7200 | H34: =G34/E34 -> 600 | I34: =G34*D34 -> 14400 | J34: 46143 | K34: 46265 | L34: ORIGI GUINESS 0,60L | N34: =IF(ISNUMBER(MATCH(L34,dim_produits!$C:$C,0)),"OK","MANQUANT") -> OK
A35: =A34+1 -> 34 | B35: 2 | C35: =IFERROR(_xlfn.XLOOKUP(L35,dim_produits!$C:$C,dim_produits!$A:$A,""),"") -> 54 | D35: 2 | E35: 24 | F35: =D35*E35 -> 48 | G35: 14300 | H35: =G35/E35 -> 595.83333 | I35: =G35*D35 -> 28600 | J35: 46143 | K35: 46265 | L35: PETIT GUINESS 0,35L | N35: =IF(ISNUMBER(MATCH(L35,dim_produits!$C:$C,0)),"OK","MANQUANT") -> OK
A36: =A35+1 -> 35 | B36: 2 | C36: =IFERROR(_xlfn.XLOOKUP(L36,dim_produits!$C:$C,dim_produits!$A:$A,""),"") -> 16 | D36: 2 | E36: 12 | F36: =D36*E36 -> 24 | G36: 7200 | H36: =G36/E36 -> 600 | I36: =G36*D36 -> 14400 | J36: 46143 | K36: 46265 | L36: KADJI BIER 0,65L | N36: =IF(ISNUMBER(MATCH(L36,dim_produits!$C:$C,0)),"OK","MANQUANT") -> OK
A37: =A36+1 -> 36 | B37: 2 | C37: =IFERROR(_xlfn.XLOOKUP(L37,dim_produits!$C:$C,dim_produits!$A:$A,""),"") -> 17 | D37: 1 | E37: 12 | F37: =D37*E37 -> 12 | G37: 5400 | H37: =G37/E37 -> 450 | I37: =G37*D37 -> 5400 | J37: 46143 | K37: 46265 | L37: MANYAN 0,65L | N37: =IF(ISNUMBER(MATCH(L37,dim_produits!$C:$C,0)),"OK","MANQUANT") -> OK
A38: =A37+1 -> 37 | B38: 3 | C38: =IFERROR(_xlfn.XLOOKUP(L38,dim_produits!$C:$C,dim_produits!$A:$A,""),"") -> 54 | D38: 2 | E38: 24 | F38: =D38*E38 -> 48 | G38: 14300 | H38: =G38/E38 -> 595.83333 | I38: =G38*D38 -> 28600 | J38: 46143 | K38: 46265 | L38: PETIT GUINESS 0,35L | N38: =IF(ISNUMBER(MATCH(L38,dim_produits!$C:$C,0)),"OK","MANQUANT") -> OK
A39: =A38+1 -> 38 | B39: 3 | C39: =IFERROR(_xlfn.XLOOKUP(L39,dim_produits!$C:$C,dim_produits!$A:$A,""),"") -> 51 | D39: 2 | E39: 12 | F39: =D39*E39 -> 24 | G39: 11900 | H39: =G39/E39 -> 991.66667 | I39: =G39*D39 -> 23800 | J39: 46143 | K39: 46265 | L39: GRAND GUINESS 0,65L | N39: =IF(ISNUMBER(MATCH(L39,dim_produits!$C:$C,0)),"OK","MANQUANT") -> OK
A40: =A39+1 -> 39 | B40: 3 | C40: =IFERROR(_xlfn.XLOOKUP(L40,dim_produits!$C:$C,dim_produits!$A:$A,""),"") -> 53 | D40: 3 | E40: 12 | F40: =D40*E40 -> 36 | G40: 7200 | H40: =G40/E40 -> 600 | I40: =G40*D40 -> 21600 | J40: 46143 | K40: 46265 | L40: ORIGI GUINESS 0,60L | N40: =IF(ISNUMBER(MATCH(L40,dim_produits!$C:$C,0)),"OK","MANQUANT") -> OK
A41: =A40+1 -> 40 | B41: 3 | C41: =IFERROR(_xlfn.XLOOKUP(L41,dim_produits!$C:$C,dim_produits!$A:$A,""),"") -> 52 | D41: 1 | E41: 24 | F41: =D41*E41 -> 24 | G41: 11300 | H41: =G41/E41 -> 470.83333 | I41: =G41*D41 -> 11300 | J41: 46143 | K41: 46265 | L41: MALTA GUINESS 0,3L | N41: =IF(ISNUMBER(MATCH(L41,dim_produits!$C:$C,0)),"OK","MANQUANT") -> OK
A42: =A41+1 -> 41 | B42: 3 | C42: =IFERROR(_xlfn.XLOOKUP(L42,dim_produits!$C:$C,dim_produits!$A:$A,""),"") -> 56 | D42: 2 | E42: 15 | F42: =D42*E42 -> 30 | G42: 9750 | H42: =G42/E42 -> 650 | I42: =G42*D42 -> 19500 | J42: 46143 | K42: 46265 | L42: SMOOTH GUINESS 0,65L | N42: =IF(ISNUMBER(MATCH(L42,dim_produits!$C:$C,0)),"OK","MANQUANT") -> OK
A43: =A42+1 -> 42 | B43: 3 | C43: =IFERROR(_xlfn.XLOOKUP(L43,dim_produits!$C:$C,dim_produits!$A:$A,""),"") -> 14 | D43: 1 | E43: 24 | F43: =D43*E43 -> 24 | G43: 13300 | H43: =G43/E43 -> 554.16667 | I43: =G43*D43 -> 13300 | J43: 46143 | K43: 46265 | L43: SMINOFF ICE ANANA 0,33L | N43: =IF(ISNUMBER(MATCH(L43,dim_produits!$C:$C,0)),"OK","MANQUANT") -> OK
... A94: =A93+1 -> 93 | B94: 11 | C94: =IFERROR(_xlfn.XLOOKUP(L94,dim_produits!$C:$C,dim_produits!$A:$A,""),"") -> 7 | D94: 3 | E94: 12 | F94: =D94*E94 -> 36 | G94: 7200 | H94: =G94/E94 -> 600 | I94: =G94*D94 -> 21600 | J94: 46143 | K94: 46265 | L94: BOSTER COLA 0,65L | N94: =IF(ISNUMBER(MATCH(L94,dim_produits!$C:$C,0)),"OK","MANQUANT") -> OK
A95: =A94+1 -> 94 | B95: 11 | C95: =IFERROR(_xlfn.XLOOKUP(L95,dim_produits!$C:$C,dim_produits!$A:$A,""),"") -> 30 | D95: =16800/200/12 -> 7 | E95: 12 | F95: =D95*E95 -> 84 | G95: 2400 | H95: =G95/E95 -> 200 | I95: =G95*D95 -> 16800 | J95: 46143 | K95: 46265 | L95: BOUTEILLE CONSIGNE | N95: =IF(ISNUMBER(MATCH(L95,dim_produits!$C:$C,0)),"OK","MANQUANT") -> OK
A96: =A95+1 -> 95 | B96: 12 | C96: =IFERROR(_xlfn.XLOOKUP(L96,dim_produits!$C:$C,dim_produits!$A:$A,""),"") -> 87 | D96: 1 | E96: 24 | F96: =D96*E96 -> 24 | G96: 13759 | H96: =G96/E96 -> 573.29167 | I96: =G96*D96 -> 13759 | J96: 46143 | K96: 46265 | L96: SMINOFF ICE DOUBLE BLACK 0,33L | N96: =IF(ISNUMBER(MATCH(L96,dim_produits!$C:$C,0)),"OK","MANQUANT") -> OK
A97: =A96+1 -> 96 | B97: 12 | C97: =IFERROR(_xlfn.XLOOKUP(L97,dim_produits!$C:$C,dim_produits!$A:$A,""),"") -> 54 | D97: 1 | E97: 24 | F97: =D97*E97 -> 24 | G97: 14300 | H97: =G97/E97 -> 595.83333 | I97: =G97*D97 -> 14300 | J97: 46143 | K97: 46265 | L97: PETIT GUINESS 0,35L | N97: =IF(ISNUMBER(MATCH(L97,dim_produits!$C:$C,0)),"OK","MANQUANT") -> OK
A98: =A97+1 -> 97 | B98: 12 | C98: =IFERROR(_xlfn.XLOOKUP(L98,dim_produits!$C:$C,dim_produits!$A:$A,""),"") -> 55 | D98: 1 | E98: 15 | F98: =D98*E98 -> 15 | G98: 9732 | H98: =G98/E98 -> 648.8 | I98: =G98*D98 -> 9732 | J98: 46143 | K98: 46265 | L98: SMOOTH GUINESS 0,50L | N98: =IF(ISNUMBER(MATCH(L98,dim_produits!$C:$C,0)),"OK","MANQUANT") -> OK
A99: =A98+1 -> 98 | B99: 12 | C99: =IFERROR(_xlfn.XLOOKUP(L99,dim_produits!$C:$C,dim_produits!$A:$A,""),"") -> 30 | D99: 1 | E99: 15 | F99: =D99*E99 -> 15 | G99: 3000 | H99: =G99/E99 -> 200 | I99: =G99*D99 -> 3000 | J99: 46143 | K99: 46265 | L99: BOUTEILLE CONSIGNE | N99: =IF(ISNUMBER(MATCH(L99,dim_produits!$C:$C,0)),"OK","MANQUANT") -> OK
A100: =A99+1 -> 99 | B100: 13 | C100: =IFERROR(_xlfn.XLOOKUP(L100,dim_produits!$C:$C,dim_produits!$A:$A,""),"") -> 19 | D100: 1 | E100: 24 | F100: =D100*E100 -> 24 | G100: 17500 | H100: =G100/E100 -> 729.16667 | I100: =G100*D100 -> 17500 | J100: 46109 | K100: 46592 | L100: BOSTER COLA CANETTE 0,5L | N100: =IF(ISNUMBER(MATCH(L100,dim_produits!$C:$C,0)),"OK","MANQUANT") -> OK
A101: =A100+1 -> 100 | B101: 13 | C101: =IFERROR(_xlfn.XLOOKUP(L101,dim_produits!$C:$C,dim_produits!$A:$A,""),"") -> 20 | D101: 1 | E101: 24 | F101: =D101*E101 -> 24 | G101: 16000 | H101: =G101/E101 -> 666.66667 | I101: =G101*D101 -> 16000 | J101: 46109 | K101: 46520 | L101: BEAUFORT ORDINAIRE CANETTE 0,5L | N101: =IF(ISNUMBER(MATCH(L101,dim_produits!$C:$C,0)),"OK","MANQUANT") -> OK
A102: =A101+1 -> 101 | B102: 13 | C102: =IFERROR(_xlfn.XLOOKUP(L102,dim_produits!$C:$C,dim_produits!$A:$A,""),"") -> 21 | D102: 1 | E102: 24 | F102: =D102*E102 -> 24 | G102: 16000 | H102: =G102/E102 -> 666.66667 | I102: =G102*D102 -> 16000 | J102: 46109 | K102: 46535 | L102: MUTZIG CANETTE 0,5L | N102: =IF(ISNUMBER(MATCH(L102,dim_produits!$C:$C,0)),"OK","MANQUANT") -> OK
A103: =A102+1 -> 102 | B103: 13 | C103: =IFERROR(_xlfn.XLOOKUP(L103,dim_produits!$C:$C,dim_produits!$A:$A,""),"") -> 22 | D103: 1 | E103: 24 | F103: =D103*E103 -> 24 | G103: 16000 | H103: =G103/E103 -> 666.66667 | I103: =G103*D103 -> 16000 | J103: 46109 | K103: 46550 | L103: CASTEL CANETTE 0,5L | N103: =IF(ISNUMBER(MATCH(L103,dim_produits!$C:$C,0)),"OK","MANQUANT") -> OK
A104: =A103+1 -> 103 | B104: 13 | C104: =IFERROR(_xlfn.XLOOKUP(L104,dim_produits!$C:$C,dim_produits!$A:$A,""),"") -> 23 | D104: 1 | E104: 24 | F104: =D104*E104 -> 24 | G104: 16000 | H104: =G104/E104 -> 666.66667 | I104: =G104*D104 -> 16000 | J104: 46109 | K104: 46474 | L104: 33 EXPORT CANETTE 0,5L | N104: =IF(ISNUMBER(MATCH(L104,dim_produits!$C:$C,0)),"OK","MANQUANT") -> OK
A105: =A104+1 -> 104 | B105: 13 | C105: =IFERROR(_xlfn.XLOOKUP(L105,dim_produits!$C:$C,dim_produits!$A:$A,""),"") -> 24 | D105: 1 | E105: 24 | F105: =D105*E105 -> 24 | G105: 8000 | H105: =G105/E105 -> 333.33333 | I105: =G105*D105 -> 8000 | J105: 46109 | K105: 46474 | L105: MALTA GUINESS CANETTE 0,5L | N105: =IF(ISNUMBER(MATCH(L105,dim_produits!$C:$C,0)),"OK","MANQUANT") -> OK
A106: =A105+1 -> 105 | B106: 13 | C106: =IFERROR(_xlfn.XLOOKUP(L106,dim_produits!$C:$C,dim_produits!$A:$A,""),"") -> 100 | D106: 1 | E106: 12 | F106: =D106*E106 -> 12 | G106: 20000 | H106: =G106/E106 -> 1666.6667 | I106: =G106*D106 -> 20000 | J106: 46109 | K106: 46474 | L106: PERLADO | N106: =IF(ISNUMBER(MATCH(L106,dim_produits!$C:$C,0)),"OK","MANQUANT") -> OK
A107: =A106+1 -> 106 | B107: 14 | C107: =IFERROR(_xlfn.XLOOKUP(L107,dim_produits!$C:$C,dim_produits!$A:$A,""),"") -> 6 | D107: 12 | E107: 10 | F107: =D107*E107 -> 120 | G107: 3799.92 | H107: =G107/E107 -> 379.992 | I107: =G107*D107 -> 45599.04 | J107: 46094 | K107: 46359 | L107: JUS REAKTOR GOLD POWER 0,5L | N107: =IF(ISNUMBER(MATCH(L107,dim_produits!$C:$C,0)),"OK","MANQUANT") -> OK
... A172: =A171+1 -> 171 | B172: 18 | C172: =IFERROR(_xlfn.XLOOKUP(L172,dim_produits!$C:$C,dim_produits!$A:$A,""),"") -> 17 | D172: 2 | E172: 12 | F172: =D172*E172 -> 24 | G172: 5400 | H172: =G172/E172 -> 450 | I172: =G172*D172 -> 10800 | J172: 45920 | K172: 46650 | L172: MANYAN 0,65L | N172: =IF(ISNUMBER(MATCH(L172,dim_produits!$C:$C,0)),"OK","MANQUANT") -> OK
I180: =SUM(I2:I172) -> 2002938.6

Sheet fact_achats
A1: achat_id | B1: date_achat | C1: date_id | D1: numero_facture | E1: acheteur_id | F1: frais_enlevement | G1: total_facture | H1: type_achat
A2: 1 | B2: 46173 | C2: 46173 | D2: =IF(A2=1,"STK-INIT-001","FAC-"&TEXT(A2-1,"0000")) -> STK-INIT-001 | E2: 1 | F2: 0 | G2: =SUMIF(dim_lignes_achat!B:B,A2,dim_lignes_achat!I:I)+F2 -> 112939.14 | H2: Stock initial
A3: =A2+1 -> 2 | B3: 46174 | C3: 46174 | D3: =IF(A3=1,"STK-INIT-001","FAC-"&TEXT(A3-1,"0000")) -> FAC-0001 | E3: 1 | F3: 8400 | G3: =SUMIF(dim_lignes_achat!B:B,A3,dim_lignes_achat!I:I)+F3 -> 107200 | H3: Achat fournisseur
A4: =A3+1 -> 3 | B4: 46176 | C4: 46176 | D4: =IF(A4=1,"STK-INIT-001","FAC-"&TEXT(A4-1,"0000")) -> FAC-0002 | E4: 1 | F4: 9300 | G4: =SUMIF(dim_lignes_achat!B:B,A4,dim_lignes_achat!I:I)+F4 -> 127400 | H4: Achat fournisseur
A5: =A4+1 -> 4 | B5: 46177 | C5: 46177 | D5: =IF(A5=1,"STK-INIT-001","FAC-"&TEXT(A5-1,"0000")) -> FAC-0003 | E5: 1 | F5: 2400 | G5: =SUMIF(dim_lignes_achat!B:B,A5,dim_lignes_achat!I:I)+F5 -> 27000 | H5: Achat fournisseur
A6: =A5+1 -> 5 | B6: 46179 | C6: 46179 | D6: =IF(A6=1,"STK-INIT-001","FAC-"&TEXT(A6-1,"0000")) -> FAC-0004 | E6: 1 | F6: 0 | G6: =SUMIF(dim_lignes_achat!B:B,A6,dim_lignes_achat!I:I)+F6 -> 70700 | H6: Achat fournisseur
A7: =A6+1 -> 6 | B7: 46182 | C7: 46182 | D7: =IF(A7=1,"STK-INIT-001","FAC-"&TEXT(A7-1,"0000")) -> FAC-0005 | E7: 1 | F7: 5700 | G7: =SUMIF(dim_lignes_achat!B:B,A7,dim_lignes_achat!I:I)+F7 -> 71300 | H7: Achat fournisseur
A8: =A7+1 -> 7 | B8: 46184 | C8: 46184 | D8: =IF(A8=1,"STK-INIT-001","FAC-"&TEXT(A8-1,"0000")) -> FAC-0006 | E8: 1 | F8: 9043 | G8: =SUMIF(dim_lignes_achat!B:B,A8,dim_lignes_achat!I:I)+F8 -> 151798 | H8: Achat fournisseur
A9: =A8+1 -> 8 | B9: 46189 | C9: 46189 | D9: =IF(A9=1,"STK-INIT-001","FAC-"&TEXT(A9-1,"0000")) -> FAC-0007 | E9: 1 | F9: 9644 | G9: =SUMIF(dim_lignes_achat!B:B,A9,dim_lignes_achat!I:I)+F9 -> 137199 | H9: Achat fournisseur
A10: =A9+1 -> 9 | B10: 46190 | C10: 46190 | D10: =IF(A10=1,"STK-INIT-001","FAC-"&TEXT(A10-1,"0000")) -> FAC-0008 | E10: 1 | F10: 4900 | G10: =SUMIF(dim_lignes_achat!B:B,A10,dim_lignes_achat!I:I)+F10 -> 57000 | H10: Achat fournisseur
A11: =A10+1 -> 10 | B11: 46192 | C11: 46192 | D11: =IF(A11=1,"STK-INIT-001","FAC-"&TEXT(A11-1,"0000")) -> FAC-0009 | E11: 1 | F11: 0 | G11: =SUMIF(dim_lignes_achat!B:B,A11,dim_lignes_achat!I:I)+F11 -> 24800 | H11: Achat fournisseur
A12: =A11+1 -> 11 | B12: 46192 | C12: 46192 | D12: =IF(A12=1,"STK-INIT-001","FAC-"&TEXT(A12-1,"0000")) -> FAC-0010 | E12: 1 | F12: 28800 | G12: =SUMIF(dim_lignes_achat!B:B,A12,dim_lignes_achat!I:I)+F12 -> 383600 | H12: Achat fournisseur
A13: =A12+1 -> 12 | B13: 46193 | C13: 46193 | D13: =IF(A13=1,"STK-INIT-001","FAC-"&TEXT(A13-1,"0000")) -> FAC-0011 | E13: 1 | F13: 3209 | G13: =SUMIF(dim_lignes_achat!B:B,A13,dim_lignes_achat!I:I)+F13 -> 44000 | H13: Achat fournisseur
A14: =A13+1 -> 13 | B14: 46194 | C14: 46194 | D14: =IF(A14=1,"STK-INIT-001","FAC-"&TEXT(A14-1,"0000")) -> FAC-0012 | E14: 1 | F14: 0 | G14: =SUMIF(dim_lignes_achat!B:B,A14,dim_lignes_achat!I:I)+F14 -> 109500 | H14: Achat fournisseur
... A19: =A18+1 -> 18 | B19: 46201 | C19: 46201 | D19: =IF(A19=1,"STK-INIT-001","FAC-"&TEXT(A19-1,"0000")) -> FAC-0017 | E19: 1 | F19: 4200 | G19: =SUMIF(dim_lignes_achat!B:B,A19,dim_lignes_achat!I:I)+F19 -> 51000 | H19: Achat fournisseur

Sheet fact_depenses
A1: depense_id | B1: date_depense | C1: date_id | D1: categorie_depense | E1: montant | F1: motif | G1: utilisateur
A2: 1 | B2: 46174 | C2: 46174 | D2: Salaire | E2: 50000 | F2: Paiement des employés | G2: Charly
A3: =A2+1 -> 2 | B3: 46174 | C3: 46174 | D3: Fournitures | E3: 3000 | F3: verre | G3: Achil
A4: =A3+1 -> 3 | B4: 46176 | C4: 46176 | D4: Transport | E4: 1500 | F4: Taxi | G4: Charly
A5: =A4+1 -> 4 | B5: 46178 | C5: 46178 | D5: Transport | E5: 2500 | F5: Taxi | G5: Charly
A6: =A5+1 -> 5 | B6: 46184 | C6: 46184 | D6: Abonnement | E6: 10000 | F6: Canal plus | G6: Achil
A7: =A6+1 -> 6 | B7: 46193 | C7: 46193 | D7: Immobilisation | E7: 90000 | F7: 20 chaise Prima | G7: Girandoux
A8: =A7+1 -> 7 | B8: 46193 | C8: 46193 | D8: Transport | E8: 5000 | F8: taxi | G8: Charly
A9: =A8+1 -> 8 | B9: 46201 | C9: 46201 | D9: Frais de personnel | E9: 2000 | F9: Repas offert au contrôleur lors d'une inspection ou d'une mission. Ce n'est pas une marchandise. | G9: Charly
A10: =A9+1 -> 9 | B10: 46203 | C10: 46203 | D10: Électricité | E10: 8000 | F10: Dépense liée à la consommation d'électricité du magasin. | G10: Charly

Sheet dim_pertes
A1: perte_id | B1: date_perte | C1: date_id | D1: produit_id | E1: qte_perte | F1: motif_perte | G1: valeur_unitaire | H1: valeur_totale | I1: utilisateur | J1: nom_produit
A2: 1 | B2: 46197 | C2: 46197 | D2: =IFERROR(_xlfn.XLOOKUP(J2,dim_produits!$C:$C,dim_produits!$A:$A,""),"") -> 52 | E2: 2 | F2: Périmé | G2: =_xlfn.XLOOKUP(J2,dim_lignes_achat!$L:$L,dim_lignes_achat!$H:$H,"Nicht gefunden",0) -> 470.83333 | H2: =E2*G2 -> 941.66667 | I2: Archile | J2: MALTA GUINESS 0,3L
A3: =A2+1 -> 2 | B3: 46197 | C3: 46197 | D3: =IFERROR(_xlfn.XLOOKUP(J3,dim_produits!$C:$C,dim_produits!$A:$A,""),"") -> 42 | E3: 6 | F3: Périmé | G3: =_xlfn.XLOOKUP(J3,dim_lignes_achat!$L:$L,dim_lignes_achat!$H:$H,"Nicht gefunden",0) -> 450 | H3: =E3*G3 -> 2700 | I3: Archile | J3: CIRAGE LIQUIDE
A4: =A3+1 -> 3 | B4: 46197 | C4: 46197 | D4: =IFERROR(_xlfn.XLOOKUP(J4,dim_produits!$C:$C,dim_produits!$A:$A,""),"") -> 47 | E4: 13 | F4: Périmé | G4: =_xlfn.XLOOKUP(J4,dim_lignes_achat!$L:$L,dim_lignes_achat!$H:$H,"Nicht gefunden",0) -> 90 | H4: =E4*G4 -> 1170 | I4: Archile | J4: CAOUTCHOUC
A5: =A4+1 -> 4 | B5: 46197 | C5: 46197 | D5: =IFERROR(_xlfn.XLOOKUP(J5,dim_produits!$C:$C,dim_produits!$A:$A,""),"") -> 49 | E5: 3 | F5: Périmé | G5: =_xlfn.XLOOKUP(J5,dim_lignes_achat!$L:$L,dim_lignes_achat!$H:$H,"Nicht gefunden",0) -> 180 | H5: =E5*G5 -> 540 | I5: Archile | J5: RÈGLE GRADUE
A6: =A5+1 -> 5 | B6: 46197 | C6: 46197 | D6: =IFERROR(_xlfn.XLOOKUP(J6,dim_produits!$C:$C,dim_produits!$A:$A,""),"") -> 96 | E6: 12 | F6: Périmé | G6: =_xlfn.XLOOKUP(J6,dim_lignes_achat!$L:$L,dim_lignes_achat!$H:$H,"Nicht gefunden",0) -> 45 | H6: =E6*G6 -> 540 | I6: Archile | J6: MENTHOLIN
A7: =A6+1 -> 6 | B7: 46197 | C7: 46197 | D7: =IFERROR(_xlfn.XLOOKUP(J7,dim_produits!$C:$C,dim_produits!$A:$A,""),"") -> 95 | E7: 5 | F7: Perce | G7: =_xlfn.XLOOKUP(J7,dim_lignes_achat!$L:$L,dim_lignes_achat!$H:$H,"Nicht gefunden",0) -> 172.5 | H7: =E7*G7 -> 862.5 | I7: Archile | J7: SPAGHETTI SPAGHETTO 250G
A8: =A7+1 -> 7 | B8: 46197 | C8: 46197 | D8: =IFERROR(_xlfn.XLOOKUP(J8,dim_produits!$C:$C,dim_produits!$A:$A,""),"") -> 17 | E8: 1 | F8: Vole | G8: =_xlfn.XLOOKUP(J8,dim_lignes_achat!$L:$L,dim_lignes_achat!$H:$H,"Nicht gefunden",0) -> 450 | H8: =E8*G8 -> 450 | I8: Archile | J8: MANYAN 0,65L
A9: =A8+1 -> 8 | B9: 46197 | C9: 46197 | D9: =IFERROR(_xlfn.XLOOKUP(J9,dim_produits!$C:$C,dim_produits!$A:$A,""),"") -> 5 | E9: 1 | F9: Vole | G9: =_xlfn.XLOOKUP(J9,dim_lignes_achat!$L:$L,dim_lignes_achat!$H:$H,"Nicht gefunden",0) -> 199.998 | H9: =E9*G9 -> 199.998 | I9: Archile | J9: JUS REAKTOR DARK POWER PET 0,5L

Sheet dim_acheteurs
A1: acheteur_id | B1: nom_acheteur
A2: 1 | B2: Charle
A3: 2 | B3: Achile
A4: 3 | B4: Christian

Sheet dim_vendeurs
A1: vendeur_id | B1: nom_vendeur
A2: 10 | B2: Achille

Sheet fact_tresorerie
A1: mouvement_id | B1: date_mouvement | C1: date_id | D1: type_mouvement | E1: montant | F1: description | G1: utilisateur
A2: 1 | B2: 46174 | C2: 46174 | D2: Apport | E2: 339900 | F2: Reste mois Mai | G2: Charly
A3: =A2+1 -> 2 | B3: 46192 | C3: 46192 | D3: Apport | E3: 510000 | F3: Reapprovisionnement initial de la boutique | G3: Girandoux
A4: =A3+1 -> 3 | B4: 46195 | C4: 46195 | D4: Apport | E4: 700000 | F4: Reapprovisionnement initial de la boutique | G4: Girandoux
A5: 4 | B5: 46204 | C5: 46204 | D5: Apport | E5: 100000 | F5: Reapprovisionnement initial de la boutique | G5: Girandoux

Sheet fact_inventaire
A1: inventaire_id | B1: date_inventaire | C1: date_id | D1: produit_id | E1: nom_produit | F1: total_acheter | G1: total_vendu | H1: qte_perte | I1: stock_theorique | J1: stock_physique | K1: ecart | L1: valeur_ecart | M1: cout_unitaire | N1: commentaire | O1: utilisateur | P1: dans dim_produit | Q1: dans dim_lignes_achat
A2: 1 | B2: 46204 | C2: 46204 | D2: =IFERROR(_xlfn.XLOOKUP(E2,dim_produits!$C:$C,dim_produits!$A:$A,""),"") -> 1 | E2: CUBE MAGGI ETOILE 25 X100X4G | F2: =IF(E2="","",SUMIF(dim_lignes_achat!$L:$L,E2,dim_lignes_achat!$F:$F)) -> 100 | G2: =IF(E2="","",SUMIF(dim_lignes_vente!$I:$I,E2,dim_lignes_vente!$D:$D)) -> 0 | H2: =IF(E2="","",SUMIF(dim_pertes!$J:$J,E2,dim_pertes!$E:$E)) -> 0 | I2: =IF(E2="","",N(F2)-N(G2)-N(H2)) -> 100 | J2: 100 | K2: =IF(E2="","",N(J2)-N(I2)) -> 0 | L2: =IF(E2="","",K2*M2) -> 0 | M2: =IFERROR(_xlfn.XLOOKUP(E2,dim_lignes_achat!$L:$L,dim_lignes_achat!$H:$H,"",0,-1),"") -> 8.5 | N2: Inventur Juli | O2: Achile/Christian | P2: =IF(ISNUMBER(MATCH(E2,dim_produits!$C:$C,0)),"OK","MANQUANT") -> OK | Q2: =IF(ISNUMBER(MATCH(E2,dim_lignes_achat!$L:$L,0)),"OK","MANQUANT") -> OK
A3: =A2+1 -> 2 | B3: 46204 | C3: 46204 | D3: =IFERROR(_xlfn.XLOOKUP(E3,dim_produits!$C:$C,dim_produits!$A:$A,""),"") -> 2 | E3: BISCUIT PARLE G 4X60X14G | F3: =IF(E3="","",SUMIF(dim_lignes_achat!$L:$L,E3,dim_lignes_achat!$F:$F)) -> 240 | G3: =IF(E3="","",SUMIF(dim_lignes_vente!$I:$I,E3,dim_lignes_vente!$D:$D)) -> 11 | H3: =IF(E3="","",SUMIF(dim_pertes!$J:$J,E3,dim_pertes!$E:$E)) -> 0 | I3: =IF(E3="","",N(F3)-N(G3)-N(H3)) -> 229 | J3: 240 | K3: =IF(E3="","",N(J3)-N(I3)) -> 11 | L3: =IF(E3="","",K3*M3) -> 206.25 | M3: =IFERROR(_xlfn.XLOOKUP(E3,dim_lignes_achat!$L:$L,dim_lignes_achat!$H:$H,"",0,-1),"") -> 18.75 | N3: Inventur Juli | O3: Achile/Christian | P3: =IF(ISNUMBER(MATCH(E3,dim_produits!$C:$C,0)),"OK","MANQUANT") -> OK | Q3: =IF(ISNUMBER(MATCH(E3,dim_lignes_achat!$L:$L,0)),"OK","MANQUANT") -> OK
A4: =A3+1 -> 3 | B4: 46204 | C4: 46204 | D4: =IFERROR(_xlfn.XLOOKUP(E4,dim_produits!$C:$C,dim_produits!$A:$A,""),"") -> 3 | E4: BISCUIT PARLE G 31 56 3X120 | F4: =IF(E4="","",SUMIF(dim_lignes_achat!$L:$L,E4,dim_lignes_achat!$F:$F)) -> 120 | G4: =IF(E4="","",SUMIF(dim_lignes_vente!$I:$I,E4,dim_lignes_vente!$D:$D)) -> 0 | H4: =IF(E4="","",SUMIF(dim_pertes!$J:$J,E4,dim_pertes!$E:$E)) -> 0 | I4: =IF(E4="","",N(F4)-N(G4)-N(H4)) -> 120 | J4: 108 | K4: =IF(E4="","",N(J4)-N(I4)) -> -12 | L4: =IF(E4="","",K4*M4) -> -480 | M4: =IFERROR(_xlfn.XLOOKUP(E4,dim_lignes_achat!$L:$L,dim_lignes_achat!$H:$H,"",0,-1),"") -> 40 | N4: Inventur Juli | O4: Achile/Christian | P4: =IF(ISNUMBER(MATCH(E4,dim_produits!$C:$C,0)),"OK","MANQUANT") -> OK | Q4: =IF(ISNUMBER(MATCH(E4,dim_lignes_achat!$L:$L,0)),"OK","MANQUANT") -> OK
A5: =A4+1 -> 4 | B5: 46204 | C5: 46204 | D5: =IFERROR(_xlfn.XLOOKUP(E5,dim_produits!$C:$C,dim_produits!$A:$A,""),"") -> 4 | E5: BISCUIT ABC X120 | F5: =IF(E5="","",SUMIF(dim_lignes_achat!$L:$L,E5,dim_lignes_achat!$F:$F)) -> 120 | G5: =IF(E5="","",SUMIF(dim_lignes_vente!$I:$I,E5,dim_lignes_vente!$D:$D)) -> 29 | H5: =IF(E5="","",SUMIF(dim_pertes!$J:$J,E5,dim_pertes!$E:$E)) -> 0 | I5: =IF(E5="","",N(F5)-N(G5)-N(H5)) -> 91 | J5: 93 | K5: =IF(E5="","",N(J5)-N(I5)) -> 2 | L5: =IF(E5="","",K5*M5) -> 78.333333 | M5: =IFERROR(_xlfn.XLOOKUP(E5,dim_lignes_achat!$L:$L,dim_lignes_achat!$H:$H,"",0,-1),"") -> 39.166667 | N5: Inventur Juli | O5: Achile/Christian | P5: =IF(ISNUMBER(MATCH(E5,dim_produits!$C:$C,0)),"OK","MANQUANT") -> OK | Q5: =IF(ISNUMBER(MATCH(E5,dim_lignes_achat!$L:$L,0)),"OK","MANQUANT") -> OK
A6: =A5+1 -> 5 | B6: 46204 | C6: 46204 | D6: =IFERROR(_xlfn.XLOOKUP(E6,dim_produits!$C:$C,dim_produits!$A:$A,""),"") -> 6 | E6: JUS REAKTOR GOLD POWER 0,5L | F6: =IF(E6="","",SUMIF(dim_lignes_achat!$L:$L,E6,dim_lignes_achat!$F:$F)) -> 120 | G6: =IF(E6="","",SUMIF(dim_lignes_vente!$I:$I,E6,dim_lignes_vente!$D:$D)) -> 10 | H6: =IF(E6="","",SUMIF(dim_pertes!$J:$J,E6,dim_pertes!$E:$E)) -> 0 | I6: =IF(E6="","",N(F6)-N(G6)-N(H6)) -> 110 | J6: 110 | K6: =IF(E6="","",N(J6)-N(I6)) -> 0 | L6: =IF(E6="","",K6*M6) -> 0 | M6: =IFERROR(_xlfn.XLOOKUP(E6,dim_lignes_achat!$L:$L,dim_lignes_achat!$H:$H,"",0,-1),"") -> 379.992 | N6: Inventur Juli | O6: Achile/Christian | P6: =IF(ISNUMBER(MATCH(E6,dim_produits!$C:$C,0)),"OK","MANQUANT") -> OK | Q6: =IF(ISNUMBER(MATCH(E6,dim_lignes_achat!$L:$L,0)),"OK","MANQUANT") -> OK
A7: =A6+1 -> 6 | B7: 46204 | C7: 46204 | D7: =IFERROR(_xlfn.XLOOKUP(E7,dim_produits!$C:$C,dim_produits!$A:$A,""),"") -> 5 | E7: JUS REAKTOR DARK POWER PET 0,5L | F7: =IF(E7="","",SUMIF(dim_lignes_achat!$L:$L,E7,dim_lignes_achat!$F:$F)) -> 71 | G7: =IF(E7="","",SUMIF(dim_lignes_vente!$I:$I,E7,dim_lignes_vente!$D:$D)) -> 8 | H7: =IF(E7="","",SUMIF(dim_pertes!$J:$J,E7,dim_pertes!$E:$E)) -> 1 | I7: =IF(E7="","",N(F7)-N(G7)-N(H7)) -> 62 | J7: 56 | K7: =IF(E7="","",N(J7)-N(I7)) -> -6 | L7: =IF(E7="","",K7*M7) -> -1199.988 | M7: =IFERROR(_xlfn.XLOOKUP(E7,dim_lignes_achat!$L:$L,dim_lignes_achat!$H:$H,"",0,-1),"") -> 199.998 | N7: Inventur Juli | O7: Achile/Christian | P7: =IF(ISNUMBER(MATCH(E7,dim_produits!$C:$C,0)),"OK","MANQUANT") -> OK | Q7: =IF(ISNUMBER(MATCH(E7,dim_lignes_achat!$L:$L,0)),"OK","MANQUANT") -> OK
A8: =A7+1 -> 7 | B8: 46204 | C8: 46204 | D8: =IFERROR(_xlfn.XLOOKUP(E8,dim_produits!$C:$C,dim_produits!$A:$A,""),"") -> 7 | E8: BOSTER COLA 0,65L | F8: =IF(E8="","",SUMIF(dim_lignes_achat!$L:$L,E8,dim_lignes_achat!$F:$F)) -> 144 | G8: =IF(E8="","",SUMIF(dim_lignes_vente!$I:$I,E8,dim_lignes_vente!$D:$D)) -> 100 | H8: =IF(E8="","",SUMIF(dim_pertes!$J:$J,E8,dim_pertes!$E:$E)) -> 0 | I8: =IF(E8="","",N(F8)-N(G8)-N(H8)) -> 44 | J8: 48 | K8: =IF(E8="","",N(J8)-N(I8)) -> 4 | L8: =IF(E8="","",K8*M8) -> 2400 | M8: =IFERROR(_xlfn.XLOOKUP(E8,dim_lignes_achat!$L:$L,dim_lignes_achat!$H:$H,"",0,-1),"") -> 600 | N8: Inventur Juli | O8: Achile/Christian | P8: =IF(ISNUMBER(MATCH(E8,dim_produits!$C:$C,0)),"OK","MANQUANT") -> OK | Q8: =IF(ISNUMBER(MATCH(E8,dim_lignes_achat!$L:$L,0)),"OK","MANQUANT") -> OK
A9: =A8+1 -> 8 | B9: 46204 | C9: 46204 | D9: =IFERROR(_xlfn.XLOOKUP(E9,dim_produits!$C:$C,dim_produits!$A:$A,""),"") -> 9 | E9: 33 EXPORT 0,65L | F9: =IF(E9="","",SUMIF(dim_lignes_achat!$L:$L,E9,dim_lignes_achat!$F:$F)) -> 325 | G9: =IF(E9="","",SUMIF(dim_lignes_vente!$I:$I,E9,dim_lignes_vente!$D:$D)) -> 356 | H9: =IF(E9="","",SUMIF(dim_pertes!$J:$J,E9,dim_pertes!$E:$E)) -> 0 | I9: =IF(E9="","",N(F9)-N(G9)-N(H9)) -> -31 | J9: 16 | K9: =IF(E9="","",N(J9)-N(I9)) -> 47 | L9: =IF(E9="","",K9*M9) -> 28200 | M9: =IFERROR(_xlfn.XLOOKUP(E9,dim_lignes_achat!$L:$L,dim_lignes_achat!$H:$H,"",0,-1),"") -> 600 | N9: Inventur Juli | O9: Achile/Christian | P9: =IF(ISNUMBER(MATCH(E9,dim_produits!$C:$C,0)),"OK","MANQUANT") -> OK | Q9: =IF(ISNUMBER(MATCH(E9,dim_lignes_achat!$L:$L,0)),"OK","MANQUANT") -> OK
A10: =A9+1 -> 9 | B10: 46204 | C10: 46204 | D10: =IFERROR(_xlfn.XLOOKUP(E10,dim_produits!$C:$C,dim_produits!$A:$A,""),"") -> 10 | E10: BEAUFORT ORDINAIRE 0,65L | F10: =IF(E10="","",SUMIF(dim_lignes_achat!$L:$L,E10,dim_lignes_achat!$F:$F)) -> 44 | G10: =IF(E10="","",SUMIF(dim_lignes_vente!$I:$I,E10,dim_lignes_vente!$D:$D)) -> 61 | H10: =IF(E10="","",SUMIF(dim_pertes!$J:$J,E10,dim_pertes!$E:$E)) -> 0 | I10: =IF(E10="","",N(F10)-N(G10)-N(H10)) -> -17 | J10: 1 | K10: =IF(E10="","",N(J10)-N(I10)) -> 18 | L10: =IF(E10="","",K10*M10) -> 10725 | M10: =IFERROR(_xlfn.XLOOKUP(E10,dim_lignes_achat!$L:$L,dim_lignes_achat!$H:$H,"",0,-1),"") -> 595.83333 | N10: Inventur Juli | O10: Achile/Christian | P10: =IF(ISNUMBER(MATCH(E10,dim_produits!$C:$C,0)),"OK","MANQUANT") -> OK | Q10: =IF(ISNUMBER(MATCH(E10,dim_lignes_achat!$L:$L,0)),"OK","MANQUANT") -> OK
A11: =A10+1 -> 10 | B11: 46204 | C11: 46204 | D11: =IFERROR(_xlfn.XLOOKUP(E11,dim_produits!$C:$C,dim_produits!$A:$A,""),"") -> 11 | E11: CASTEL 0,5L | F11: =IF(E11="","",SUMIF(dim_lignes_achat!$L:$L,E11,dim_lignes_achat!$F:$F)) -> 159 | G11: =IF(E11="","",SUMIF(dim_lignes_vente!$I:$I,E11,dim_lignes_vente!$D:$D)) -> 119 | H11: =IF(E11="","",SUMIF(dim_pertes!$J:$J,E11,dim_pertes!$E:$E)) -> 0 | I11: =IF(E11="","",N(F11)-N(G11)-N(H11)) -> 40 | J11: 6 | K11: =IF(E11="","",N(J11)-N(I11)) -> -34 | L11: =IF(E11="","",K11*M11) -> -20400 | M11: =IFERROR(_xlfn.XLOOKUP(E11,dim_lignes_achat!$L:$L,dim_lignes_achat!$H:$H,"",0,-1),"") -> 600 | N11: Inventur Juli | O11: Achile/Christian | P11: =IF(ISNUMBER(MATCH(E11,dim_produits!$C:$C,0)),"OK","MANQUANT") -> OK | Q11: =IF(ISNUMBER(MATCH(E11,dim_lignes_achat!$L:$L,0)),"OK","MANQUANT") -> OK
A12: =A11+1 -> 11 | B12: 46204 | C12: 46204 | D12: =IFERROR(_xlfn.XLOOKUP(E12,dim_produits!$C:$C,dim_produits!$A:$A,""),"") -> 12 | E12: DOPPEL 0,65L | F12: =IF(E12="","",SUMIF(dim_lignes_achat!$L:$L,E12,dim_lignes_achat!$F:$F)) -> 66 | G12: =IF(E12="","",SUMIF(dim_lignes_vente!$I:$I,E12,dim_lignes_vente!$D:$D)) -> 56 | H12: =IF(E12="","",SUMIF(dim_pertes!$J:$J,E12,dim_pertes!$E:$E)) -> 0 | I12: =IF(E12="","",N(F12)-N(G12)-N(H12)) -> 10 | J12: 24 | K12: =IF(E12="","",N(J12)-N(I12)) -> 14 | L12: =IF(E12="","",K12*M12) -> 8400 | M12: =IFERROR(_xlfn.XLOOKUP(E12,dim_lignes_achat!$L:$L,dim_lignes_achat!$H:$H,"",0,-1),"") -> 600 | N12: Inventur Juli | O12: Achile/Christian | P12: =IF(ISNUMBER(MATCH(E12,dim_produits!$C:$C,0)),"OK","MANQUANT") -> OK | Q12: =IF(ISNUMBER(MATCH(E12,dim_lignes_achat!$L:$L,0)),"OK","MANQUANT") -> OK
A13: =A12+1 -> 12 | B13: 46204 | C13: 46204 | D13: =IFERROR(_xlfn.XLOOKUP(E13,dim_produits!$C:$C,dim_produits!$A:$A,""),"") -> 13 | E13: HARP BRASSERIE 0,6L | F13: =IF(E13="","",SUMIF(dim_lignes_achat!$L:$L,E13,dim_lignes_achat!$F:$F)) -> 19 | G13: =IF(E13="","",SUMIF(dim_lignes_vente!$I:$I,E13,dim_lignes_vente!$D:$D)) -> 1 | H13: =IF(E13="","",SUMIF(dim_pertes!$J:$J,E13,dim_pertes!$E:$E)) -> 0 | I13: =IF(E13="","",N(F13)-N(G13)-N(H13)) -> 18 | J13: 18 | K13: =IF(E13="","",N(J13)-N(I13)) -> 0 | L13: =IF(E13="","",K13*M13) -> 0 | M13: =IFERROR(_xlfn.XLOOKUP(E13,dim_lignes_achat!$L:$L,dim_lignes_achat!$H:$H,"",0,-1),"") -> 700 | N13: Inventur Juli | O13: Achile/Christian | P13: =IF(ISNUMBER(MATCH(E13,dim_produits!$C:$C,0)),"OK","MANQUANT") -> OK | Q13: =IF(ISNUMBER(MATCH(E13,dim_lignes_achat!$L:$L,0)),"OK","MANQUANT") -> OK
A14: =A13+1 -> 13 | B14: 46204 | C14: 46204 | D14: =IFERROR(_xlfn.XLOOKUP(E14,dim_produits!$C:$C,dim_produits!$A:$A,""),"") -> 14 | E14: SMINOFF ICE ANANA 0,33L | F14: =IF(E14="","",SUMIF(dim_lignes_achat!$L:$L,E14,dim_lignes_achat!$F:$F)) -> 120 | G14: =IF(E14="","",SUMIF(dim_lignes_vente!$I:$I,E14,dim_lignes_vente!$D:$D)) -> 36 | H14: =IF(E14="","",SUMIF(dim_pertes!$J:$J,E14,dim_pertes!$E:$E)) -> 0 | I14: =IF(E14="","",N(F14)-N(G14)-N(H14)) -> 84 | J14: 45 | K14: =IF(E14="","",N(J14)-N(I14)) -> -39 | L14: =IF(E14="","",K14*M14) -> -21612.5 | M14: =IFERROR(_xlfn.XLOOKUP(E14,dim_lignes_achat!$L:$L,dim_lignes_achat!$H:$H,"",0,-1),"") -> 554.16667 | N14: Inventur Juli | O14: Achile/Christian | P14: =IF(ISNUMBER(MATCH(E14,dim_produits!$C:$C,0)),"OK","MANQUANT") -> OK | Q14: =IF(ISNUMBER(MATCH(E14,dim_lignes_achat!$L:$L,0)),"OK","MANQUANT") -> OK
... A104: =A103+1 -> 103 | B104: 46204 | C104: 46204 | D104: =IFERROR(_xlfn.XLOOKUP(E104,dim_produits!$C:$C,dim_produits!$A:$A,""),"") -> 55 | E104: SMOOTH GUINESS 0,50L | F104: =IF(E104="","",SUMIF(dim_lignes_achat!$L:$L,E104,dim_lignes_achat!$F:$F)) -> 15 | G104: =IF(E104="","",SUMIF(dim_lignes_vente!$I:$I,E104,dim_lignes_vente!$D:$D)) -> 20 | H104: =IF(E104="","",SUMIF(dim_pertes!$J:$J,E104,dim_pertes!$E:$E)) -> 0 | I104: =IF(E104="","",N(F104)-N(G104)-N(H104)) -> -5 | J104: 3 | K104: =IF(E104="","",N(J104)-N(I104)) -> 8 | L104: =IF(E104="","",K104*M104) -> 5190.4 | M104: =IFERROR(_xlfn.XLOOKUP(E104,dim_lignes_achat!$L:$L,dim_lignes_achat!$H:$H,"",0,-1),"") -> 648.8 | N104: Inventur Juli | O104: Achile/Christian | P104: =IF(ISNUMBER(MATCH(E104,dim_produits!$C:$C,0)),"OK","MANQUANT") -> OK | Q104: =IF(ISNUMBER(MATCH(E104,dim_lignes_achat!$L:$L,0)),"OK","MANQUANT") -> OK
F105: =IF(E105="","",SUMIF(dim_lignes_achat!$L:$L,E105,dim_lignes_achat!$F:$F))

Sheet iventaire_1
A1: nom_produit | B1: Nom Corrige | C1: nom_categorie | D1: unité | E1: date_fabrication | F1: date_peremption | G1: stock_theorique | H1: stock_physique | I1: ecart | L1: total_acheter | M1: total_vendu
A2: CUBE MAGGI ETOILE 25 X100X4G | C2: Assaisonnement | D2: Cube | E2: 46143 | H2: 100
A3: BISCUIT PARLE G 4X60X14G | C3: Biscuits | D3: Pièce | E3: 46143 | H3: 240
A4: BISCUIT PARLE G 31 56 3X120 | C4: Biscuits | D4: Pièce | E4: 46143 | H4: 108
A5: BISCUIT ABC X120 | C5: Biscuits | D5: Pièce | E5: 46143 | H5: 93
A6: JUS ERNERGISANTE REAKTOR 0,5L | C6: Boisson Energisante | D6: Canette | E6: 46143 | H6: 110
A7: JUS REAKTOR DARK POWER PET 0,5L | C7: Boisson Energisante | D7: Canette | E7: 46143 | H7: 56
A8: BOSTER COLA 0,65L | C8: Boisson Gazeuse | D8: Bouteille | E8: 46143 | H8: 48
A9: BOSTER DJIM TONIC 0,65L | B9: achte apres inventaire | C9: Boisson Gazeuse | D9: Bouteille | E9: 46143 | H9: 0
A10: 33 EXPORT 0,65L | C10: Brasserie Biere | D10: Bouteille | E10: 46143 | H10: 16
A11: BEAUFORT ORDINAIRE 0,65L | C11: Brasserie Biere | D11: Bouteille | E11: 46143 | H11: 1
A12: CASTEL 0,5L | C12: Brasserie Biere | D12: Bouteille | E12: 46143 | H12: 6
A13: DOPPEL 0,65L | C13: Brasserie Biere | D13: Bouteille | E13: 46143 | H13: 24
A14: HARP BRASSERIE 0,6L | C14: Brasserie Biere | D14: Bouteille | E14: 46143 | H14: 18
A15: SMINOFF ICE ANANA 0,33L | C15: Brasserie Biere | D15: Bouteille | E15: 46143 | H15: 45
A16: ISEMBECK 0,65L | C16: Brasserie Biere | D16: Bouteille | E16: 46143 | H16: 22
A17: KAGI BIER 0,65L | C17: Brasserie Biere | D17: Bouteille | E17: 46143 | H17: 1
A18: MANYAN 0,65L | C18: Brasserie Biere | D18: Bouteille | E18: 46143 | H18: 22
A19: MUTZIG 0,65L | C19: Brasserie Biere | D19: Bouteille | E19: 46143 | H19: 10
A20: BOSTER COLA CANETTE 0,5L | C20: Canette | D20: Canette | E20: 46143 | H20: 23
A21: BEAUFORT ORDINAIRE CANETTE 0,5L | C21: Canette | D21: Canette | E21: 46143 | H21: 24
... A30: SARDINE JOLY NON PIMENTE 125X50 | C30: Conserve | D30: Pièce | E30: 46143 | H30: 45
A31: BOUTEILLE CONSIGNE | C31: Consigne | D31: Pièce | E31: 46143
A32: EAU VITAL 10L | B32: 10-7=3 comen zero | C32: Eau | D32: Bidon | E32: 46143 | H32: 0
A33: EAU SUPERMONT 0,5L | C33: Eau | D33: Bouteille | E33: 46143 | H33: 24
A34: EAU SUPERMONT 1,5L | C34: Eau | D34: Bouteille | E34: 46143 | H34: 18
A35: EAU SUPERMONT 10L | C35: Eau | D35: Bouteille | E35: 46143 | H35: 7
A36: EAU MINERAL OPUR 0,5L | C36: Eau | D36: Bouteille | E36: 46143 | H36: 24
A37: EAU MINERAL OPUR 1,5L | C37: Eau | D37: Bouteille | E37: 46143 | H37: 51
A38: EAU OPUR 1,5L | B38: meme non : EAU MINERAL OPUR 1,5L | C38: Eau | D38: Bouteille | E38: 46143 | H38: 0
A39: EAU PLANETE 1,5L | B39: denir in ventai 22 -0=22 nesite pas | C39: Eau | D39: Bouteille | E39: 46143 | H39: 0
A40: AMPOULE REGRETTE | C40: Electricite | D40: Pièce | E40: 46143 | H40: 3
A41: RALONGE ELECTRIQUE | B41: il dit reste tj 2 dans | C41: Electricite | D41: Pièce | E41: 46143 | H41: 2
A42: PLASTIQUE | B42: commen 5-1=4 | C42: Emballage | D42: Paquet | E42: 46143 | H42: 0
A43: DETERGENT MADAR 25G Y156 | C43: Entretien | D43: Pièce | E43: 46143 | H43: 146
A44: DETERGENT BRIL 30GX150 | C44: Entretien | D44: Pièce | E44: 46143 | H44: 130
A45: CIRAGE LIQUIDE | B45: il y avais 6 perime | C45: Entretien | D45: Pièce | E45: 46143
A46: SUCRE KFTY SACHET 12 XIKG | C46: Epicerie | D46: Paquet | E46: 46143 | H46: 10
A47: NESCAFE COFFRET 9X1501 50 | C47: Epicerie | D47: Paquet | E47: 46143 | H47: 145
A48: LAIT TOP MIL VANILLE SACHET 6 X50 | C48: Epicerie | D48: Paquet | E48: 46143 | H48: 278
A49: HUILE MAYOR 15X1L | C49: Epicerie | D49: Bouteille | E49: 46143 | H49: 14
A50: CAOUTCHOUC | B50: il y avais 13 pireme | C50: Fourniture | D50: Pièce | E50: 46143 | H50: 0
A51: EPINGLE | C51: Fourniture | D51: Pièce | E51: 46143 | H51: 8
A52: RÈGLE GRADUE | B52: il y avais 3 perime | C52: Fourniture | D52: Pièce | E52: 46143 | H52: 0
A53: TAILLE CRAYON | C53: Fourniture | D53: Pièce | E53: 46143 | H53: 32
A54: GRAND GUINESS 0,65L | C54: Guinness Biere | D54: Bouteille | E54: 46143 | H54: 31
A55: MALTA GUINESS 0,3L | C55: Guinness Biere | D55: Bouteille | E55: 46143 | H55: 108
A56: ORIGI GUINESS 0,60L | C56: Guinness Biere | D56: Bouteille | E56: 46143 | H56: 97
A57: ORUIM GUINNESS 0,65L | C57: Guinness Biere | D57: Bouteille | E57: 46143 | H57: 0
A58: PETIT GUINESS 0,35L | C58: Guinness Biere | D58: Bouteille | E58: 46143 | H58: 107
A59: SMOOTH GUINESS 0,65L | B59: comment 0? | C59: Guinness Biere | D59: Bouteille | E59: 46143 | H59: 0
A60: SAVON MAYOR 360G 60 | C60: Hygiene | D60: Pièce | E60: 46143 | H60: 60
A61: SAVON AZUR 400G 60 | C61: Hygiene | D61: Pièce | E61: 46143 | H61: 58
A62: SAVON PROTEX HERBAL12X6X150G | C62: Hygiene | D62: Pièce | E62: 46143 | H62: 6
A63: SAVON SANTEX BLANC 12X690G | C63: Hygiene | D63: Pièce | E63: 46143 | H63: 6
A64: SAVON DAUPHIN CLASSIQUE 6X6X200G | C64: Hygiene | D64: Pièce | E64: 46143 | H64: 6
A65: BROSSE COLGATE ANTICAVITY HANGER 12X12 | C65: Hygiene | D65: Pièce | E65: 46143 | H65: 11
A66: CURENDENT PEACOCK 50X12 | C66: Hygiene | D66: Pièce | E66: 46143 | H66: 9
A67: PAPIER HYGIENIQUE SITA X48 | C67: Hygiene | D67: Pièce | E67: 46143 | H67: 46
A68: BABOUCHE DE TOILETTE | C68: Hygiene | D68: Paire | E68: 46143 | H68: 2
A69: SER VIETTE HYG AMIE 5X12X280MM | C69: Hygiène Féminine | D69: Paquet | E69: 46143 | H69: 12
A70: SER HYG A+ JAUNE 4X6 | C70: Hygiène Féminine | D70: Paquet | E70: 46143 | H70: 6
A71: SER VIETTE HYG SOFTCARE A+ 10PQTX6 NEW BLEU | C71: Hygiène Féminine | D71: Paquet | E71: 46143 | H71: 6
... A80: JUS COCA COLA PET 1L | C80: Jus | D80: Bouteille | E80: 46109 | H80: 30
A81: JUS TOP ANANAS PET 0,35L | B81: commen zero elle na pas ete vendu et elle a ette achete sur la f13 | C81: Jus | D81: Bouteille | E81: 46143 | H81: 0
A82: JUS PLANET ORANGE 1,2L | C82: Jus | D82: Bouteille | E82: 46143 | H82: 34
A83: JUS PLANET ORANGE 0,35L | C83: Jus | D83: Bouteille | E83: 46143 | H83: 12
A84: JUS TOP ORANGE PET 0,35L | C84: Jus | D84: Bouteille | E84: 46143 | H84: 10
A85: JUS BUBLE UP CHAPHAN 1,2L | C85: Jus | D85: Bouteille | E85: 46094 | H85: 35
A86: JUS UCB PAMPLEMOUSSE PET 1L | C86: Jus | D86: Bouteille | E86: 46143 | H86: 34
A87: JUS SABC DJINO COKTAIL PET 1L | C87: Jus | D87: Bouteille | E87: 46143 | H87: 22
A88: JUS PLANET COKTAIL 1,2L | C88: Jus | D88: Bouteille | E88: 46143 | H88: 23
A89: JUS ANANAS BRASSERIE 1L | B89: JUS TOP ANANAS BRASSERIE 1L commen zero elle a ete ven du ceulemen 1 bouteil sur 6 | C89: Jus | D89: Bouteille | E89: 46143
A90: JUS GRENADINE 1L | C90: Jus | D90: Bouteille | E90: 46143 | H90: 22
A91: JUS DJINO BRASSERIE 1L | C91: Jus | D91: Bouteille | E91: 46143 | H91: 22
A92: JUS ORANGE BRASSERIE 1L | C92: Jus | D92: Bouteille | E92: 46143 | H92: 27
A93: SMINOFF ICE DOUBLE BLACK 0,33L | C93: Jus | D93: Bouteille | E93: 46143 | H93: 46
A94: LOTUS TIOF | B94: il y avais 15 - 14 = 1 reste | C94: Mouchoir | D94: Pièce | E94: 46143 | H94: 0
A95: MUX COCKTAIL MARGARITA | C95: Mux Biere | D95: Bouteille | E95: 46143 | H95: 8
A96: MUX COCKTAIL GNITO MIX | C96: Mux Biere | D96: Bouteille | E96: 46143 | H96: 2
A97: MUX COCKTAIL MOJITO | C97: Mux Biere | D97: Bouteille | E97: 46143 | H97: 5
A98: MUX COCKTAIL HERBAL MIX | B98: commen sapelle quand tu vend? Il y devai avoir encore | C98: Mux Biere | D98: Bouteille | E98: 46143
A99: MUX COCKTAIL WHISKO MIX | B99: sur un otre non? | C99: Mux Biere | D99: Bouteille | E99: 46143
A100: SPAGHETTI SPAGHETTO 500G | C100: Pates | D100: Paquet | E100: 46143 | H100: 16
A101: SPAGHETTI SPAGHETTO 250G | C101: Pates | D101: Paquet | E101: 46109 | H101: 35
A102: MENTHOLIN | B102: il y avais 12 dernier inventaire rien vendu perime | C102: Pommade | D102: Pièce | E102: 46143
A103: CIGARETTE ASPEN IX50 | C103: Tabac | D103: Paquet | E103: 46109 | H103: =9*20 -> 180
A104: CIGARETTE BENSON 50X10 | C104: Tabac | D104: Paquet | E104: 46109 | H104: =9*20+15 -> 195
A105: CIGARETTE TIME GRIS X5O | C105: Tabac | D105: Paquet | E105: 46143 | H105: =9*20+7 -> 187
A106: PERLADO | C106: Vin | D106: Bouteille | E106: 46143 | H106: 11
A107: VIN ROUGE EL VINO I2XIL | C107: Vin | D107: Bouteille | E107: 46143 | H107: 12
A108: VIN BLANC EL VINO 12X1L | C108: Vin | D108: Bouteille | E108: 46094 | H108: 11
A109: VIN FIESTA ROUOE 12XL | C109: Vin | D109: Bouteille | E109: 46094 | H109: 12
A110: VIN ROUGE BARON DE RIBERA I2XIL | C110: Vin | D110: Bouteille | E110: 46094 | H110: 12
A111: TIGER RAZOR | E111: 46094 | H111: 4
A112: SMOOTH GUINESS 0,50L | B112: pas sur lite | H112: 3
A114: BOUTEILLE Braserie | H114: 563
A115: BOUTEILLE Smooth 0,50 L | H115: 28
A116: BOUTEILLE SMOOTH 0,65L | H116: 25
A117: BOUTEILLE GRAND GUINESS | H117: 165
...

Sheet liste_boutique (3)
A1: nom_produit | B1: categorie | C1: unité | D1: qte_cartons | E1: qte_par_carton | F1: quantite_achat | G1: pu_achat_carton | H1: pu_achat_piece | I1: total_achat | J1: date_fabrication | K1: date_peremption | L1: pu_vente_piece
A2: BOSTER COLA CANETTE 0,5L | B2: Canette | C2: Canette | D2: 1 | E2: 24 | F2: =D2*E2 -> 24 | G2: 17500 | H2: =G2/E2 -> 729.16667 | I2: =H2*F2 -> 17500 | J2: 46109 | K2: 46592 | L2: 800
A3: BEAUFORT ORDINAIRE CANETTE 0,5L | B3: Canette | C3: Canette | D3: 1 | E3: 24 | F3: =D3*E3 -> 24 | G3: 16000 | H3: =G3/E3 -> 666.66667 | I3: =H3*F3 -> 16000 | J3: 46109 | K3: 46520 | L3: 750
A4: MUTZIG CANETTE 0,5L | B4: Canette | C4: Canette | D4: 1 | E4: 24 | F4: =D4*E4 -> 24 | G4: 16000 | H4: =G4/E4 -> 666.66667 | I4: =H4*F4 -> 16000 | J4: 46109 | K4: 46535 | L4: 750
A5: CASTEL CANETTE 0,5L | B5: Canette | C5: Canette | D5: 1 | E5: 24 | F5: =D5*E5 -> 24 | G5: 16000 | H5: =G5/E5 -> 666.66667 | I5: =H5*F5 -> 16000 | J5: 46109 | K5: 46550 | L5: 750
A6: 33 EXPORT CANETTE 0,5L | B6: Canette | C6: Canette | D6: 1 | E6: 24 | F6: =D6*E6 -> 24 | G6: 16000 | H6: =G6/E6 -> 666.66667 | I6: =H6*F6 -> 16000 | J6: 46109 | K6: 46474 | L6: 750
A7: MALTA GUINESS CANETTE 0,5L | B7: Canette | C7: Canette | D7: 1 | E7: 24 | F7: =D7*E7 -> 24 | G7: 8000 | H7: =G7/E7 -> 333.33333 | I7: =H7*F7 -> 8000 | J7: 46109 | K7: 46474 | L7: 500
A8: PERLADO | B8: Vin | C8: Bouteille | D8: 1 | E8: 12 | F8: =D8*E8 -> 12 | G8: 20000 | H8: =G8/E8 -> 1666.6667 | I8: =H8*F8 -> 20000 | J8: 46109 | K8: 46474 | L8: 2000
A9: SARDINE JOLY NON PIMENTE 125X50 | B9: Conserve | C9: Pièce | D9: 1 | E9: 50 | F9: =D9*E9 -> 50 | G9: 18500 | H9: =G9/E9 -> 370 | I9: =H9*F9 -> 18500 | J9: 45882 | K9: 47343 | L9: 500
A10: JUS ERNERGISANTE REAKTOR 0,5L | B10: Boisson_Energisante | C10: Canette | D10: 12 | E10: 10 | F10: =D10*E10 -> 120 | G10: =H10*D10 -> 3799.92 | H10: 316.66 | I10: =H10*F10 -> 37999.2 | J10: 46094 | K10: 46359 | L10: 500
A11: JUS TOP PAMOLEMOUS PET 1L | B11: Jus | C11: Bouteille | D11: =F11/E11 -> 6 | E11: 6 | F11: 36 | G11: =H11*D11 -> 2199.96 | H11: 366.66 | I11: =H11*F11 -> 13199.76 | J11: 46094 | K11: 46272 | L11: 500
A12: JUS TOP ORANGE PET 1L | B12: Jus | C12: Bouteille | D12: =F12/E12 -> 6 | E12: 6 | F12: 36 | G12: =H12*D12 -> 2199.96 | H12: 366.66 | I12: =H12*F12 -> 13199.76 | J12: 46094 | K12: 46360 | L12: 500
A13: JUS TOP GRENADINE PET 1L | B13: Jus | C13: Bouteille | D13: =F13/E13 -> 6 | E13: 6 | F13: 36 | G13: =H13*D13 -> 2199.96 | H13: 366.66 | I13: =H13*F13 -> 13199.76 | J13: 46094 | K13: 46364 | L13: 500
A14: JUS REAKTOR DARK POWER PET 0,5L | B14: Boisson_Energisante | C14: Canette | D14: 6 | E14: 10 | F14: =D14*E14 -> 60 | G14: =H14*D14 -> 1999.98 | H14: 333.33 | I14: =H14*F14 -> 19999.8 | J14: 46094 | K14: 46344 | L14: 500
A15: JUS SABS VIMTO 1L | B15: Jus | C15: Bouteille | D15: =F15/E15 -> 5 | E15: 6 | F15: 30 | G15: =H15*E15 -> 3720 | H15: 620 | I15: =H15*F15 -> 18600 | J15: 46094 | K15: 46367
A16: JUS SABS ORANGINA 1L | B16: Jus | C16: Bouteille | D16: =F16/E16 -> 6 | E16: 6 | F16: 36 | G16: =H16*E16 -> 3900 | H16: 650 | I16: =H16*F16 -> 23400 | J16: 46094 | K16: 46365 | L16: 800
A17: EAU VITAL 10L | B17: Eau | C17: Bidon | D17: 10 | E17: 1 | F17: 10 | G17: =H17*E17 -> 900 | H17: 900 | I17: =H17*F17 -> 9000 | J17: 46094 | K17: 46523 | L17: 1000
A18: JUS PLANET TROPICAL 1,2L | B18: Jus | C18: Bouteille | D18: 5 | E18: 6 | F18: 30 | G18: =H18*E18 -> 2349.96 | H18: 391.66 | I18: =H18*F18 -> 11749.8 | J18: 46158 | K18: 46493 | L18: 500
A19: JUS COCA COLA PET 1L | B19: Jus | C19: Bouteille | D19: 6 | E19: 6 | F19: 36 | G19: =H19*E19 -> 3300 | H19: 550 | I19: =H19*F19 -> 19800 | J19: 46158 | K19: 46335 | L19: 700
A20: JUS TOP ANANAS PET 0,35L | B20: Jus | C20: Bouteille | D20: 1 | E20: 12 | F20: 12 | G20: =H20*E20 -> 2899.92 | H20: 241.66 | I20: =H20*F20 -> 2899.92 | J20: 46158 | K20: 46367 | L20: 250
A21: JUS PLANET ORANGE 1,2L | B21: Jus | C21: Bouteille | D21: 6 | E21: 6 | F21: 36 | G21: =H21*E21 -> 2349.96 | H21: 391.66 | I21: =H21*F21 -> 14099.76 | J21: 46058 | K21: 46392 | L21: 500
A22: JUS PLANET ORANGE 0,35L | B22: Jus | C22: Bouteille | D22: 1 | E22: 12 | F22: 12 | G22: =H22*E22 -> 2352 | H22: 196 | I22: =H22*F22 -> 2352 | J22: 46095 | K22: 46370 | L22: 250
A23: JUS TOP ORANGE PET 0,35L | B23: Jus | C23: Bouteille | D23: 12 | E23: 12 | F23: 12 | G23: =H23*E23 -> 2899.92 | H23: 241.66 | I23: =H23*F23 -> 2899.92 | J23: 46153 | K23: 46123 | L23: 500
A24: JUS BUBLE UP CHAPHAN 1,2L | B24: Jus | C24: Bouteille | D24: 6 | E24: 6 | F24: 36 | G24: =H24*E24 -> 2349.96 | H24: 391.66 | I24: =H24*F24 -> 14099.76 | J24: 46083 | K24: 46267 | L24: 650
A25: JUS UCB PAMPLEMOUSSE PET 1L | B25: Jus | C25: Bouteille | D25: 7 | E25: 6 | F25: 36 | G25: =H25*E25 -> 3249.96 | H25: 541.66 | I25: =H25*F25 -> 19499.76 | J25: 46083 | K25: 46340 | L25: 700
A26: JUS SABC DJINO COKTAIL PET 1L | B26: Jus | C26: Bouteille | D26: 7 | E26: 6 | F26: 36 | G26: =H26*E26 -> 3249.96 | H26: 541.66 | I26: =H26*F26 -> 19499.76 | J26: 46185 | K26: 46154 | L26: 500
A27: JUS PLANET COKTAIL 1,2L | B27: Jus | C27: Bouteille | D27: 5 | E27: 6 | F27: 30 | G27: =H27*E27 -> 2349.96 | H27: 391.66 | I27: =H27*F27 -> 11749.8 | J27: 46188 | K27: 46550 | L27: 500
A28: EAU SUPERMONT 0,5L | B28: Eau | C28: Bouteille | D28: 2 | E28: 12 | F28: 24 | G28: =H28*E28 -> 1899.96 | H28: 158.33 | I28: =H28*F28 -> 3799.92 | J28: 46188 | K28: 46553 | L28: 200
... A30: EAU SUPERMONT 10L | B30: Eau | C30: Bouteille | D30: 1 | E30: 10 | F30: 10 | G30: =H30*E30 -> 10000 | H30: 1000 | I30: =H30*F30 -> 10000 | J30: 46160 | K30: 46556 | L30: 1100
A31: EAU MINERAL OPUR 0,5L | B31: Eau | C31: Bouteille | D31: 2 | E31: 12 | F31: 24 | G31: =H31*E31 -> 1699.92 | H31: 141.66 | I31: =H31*F31 -> 3399.84 | J31: 46175 | K31: 46547
A32: EAU MINERAL OPUR 1,5L | B32: Eau | C32: Bouteille | D32: 10 | E32: 6 | F32: 60 | G32: =H32*E32 -> 1200 | H32: 200 | I32: =H32*F32 -> 12000 | J32: 46187 | K32: 46552 | L32: 300
A33: SPAGHETTI SPAGHETTO 500G | B33: Pates | C33: Paquet | D33: 1 | E33: 20 | F33: =D33*E33 -> 20 | G33: 6800 | H33: =G33/E33 -> 340 | I33: =H33*F33 -> 6800 | J33: 46105 | K33: 46835 | L33: 400
A34: SPAGHETTI SPAGHETTO 2500G | B34: Pates | C34: Paquet | D34: 1 | E34: 40 | F34: =D34*E34 -> 40 | G34: 6900 | H34: =G34/E34 -> 172.5 | I34: =H34*F34 -> 6900 | J34: 46047 | K34: 46776 | L34: 250
A35: SAVON MAYOR 360G 60 | B35: Hygiene | C35: Pièce | D35: 1 | E35: 60 | F35: 60 | G35: 17500 | H35: =G35/E35 -> 291.66667 | I35: =H35*F35 -> 17500 | L35: 350
A36: SAVON AZUR 400G 60 | B36: Hygiene | C36: Pièce | D36: 1 | E36: 60 | F36: 60 | G36: 20000 | H36: =G36/E36 -> 333.33333 | I36: =H36*F36 -> 20000 | L36: 400
A37: SAVON PROTEX HERBAL12X6X150G | B37: Hygiene | C37: Pièce | D37: 1 | E37: 6 | F37: =D37*E37 -> 6 | G37: 5000 | H37: =G37/E37 -> 833.33333 | I37: =H37*F37 -> 5000 | K37: 46813 | L37: 950
A38: SAVON SANTEX BLANC 12X690G | B38: Hygiene | C38: Pièce | D38: 1 | E38: 6 | F38: 6 | G38: 1500 | H38: =G38/E38 -> 250 | I38: =H38*F38 -> 1500 | J38: 46145 | K38: 46876 | L38: 400
A39: SAVON DAUPHIN CLASSIQUE 6X6X200G | B39: Hygiene | C39: Pièce | D39: 1 | E39: 6 | F39: 6 | G39: 3500 | H39: =G39/E39 -> 583.33333 | I39: =H39*F39 -> 3500 | L39: 700
A40: DETERGENT MADAR 25G Y156 | B40: Entretien | C40: Pièce | D40: 1 | E40: 156 | F40: 156 | G40: 5500 | H40: =G40/E40 -> 35.25641 | I40: =H40*F40 -> 5500 | J40: 46082 | L40: 50
A41: DETERGENT BRIL 30GX150 | B41: Entretien | C41: Pièce | D41: 1 | E41: 150 | F41: 150 | G41: 5600 | H41: =G41/E41 -> 37.333333 | I41: =H41*F41 -> 5600 | J41: 46351 | K41: 47812 | L41: 50
A42: BROSSE COLGATE ANTICAVITY HANGER 12X12 | B42: Hygiene | C42: Pièce | D42: 1 | E42: 12 | F42: 12 | G42: 2300 | H42: =G42/E42 -> 191.66667 | I42: =H42*F42 -> 2300 | J42: 46259 | K42: 49550 | L42: 250
A43: CIGARETTE ASPEN IX50 | B43: Tabac | C43: Paquet | D43: 10 | E43: 20 | F43: 200 | G43: 3800 | H43: =G43/F43 -> 19 | I43: =H43*F43 -> 3800 | J43: 46023 | K43: 46569 | L43: 25
A44: CIGARETTE BENSON 50X10 | B44: Tabac | C44: Paquet | D44: 10 | E44: 20 | F44: 200 | G44: 7800 | H44: =G44/F44 -> 39 | I44: =H44*F44 -> 7800 | J44: 45992 | K44: 46722 | L44: 50
A45: BRIQUET FLAG 20PQTX50 | B45: Combustible | C45: Pièce | D45: 1 | E45: 50 | F45: 50 | G45: 2500 | H45: =G45/F45 -> 50 | I45: =H45*F45 -> 2500 | K45: 46722 | L45: 100
A46: CURENDENT PEACOCK 50X12 | B46: Hygiene | C46: Pièce | D46: 1 | E46: 12 | F46: 12 | G46: 850 | H46: =G46/F46 -> 70.833333 | I46: =H46*F46 -> 850 | K46: 46722 | L46: 100
A47: SUCRE KFTY SACHET 12 XIKG | B47: Epicerie | C47: Paquet | D47: 1 | E47: 12 | F47: 12 | G47: 7500 | H47: =G47/F47 -> 625 | I47: =H47*F47 -> 7500 | K47: 46722 | L47: 850
A48: NESCAFE COFFRET 9X1501 50 | B48: Epicerie | C48: Paquet | D48: 1 | E48: 150 | F48: 150 | G48: 8500 | H48: =G48/F48 -> 56.666667 | I48: =H48*F48 -> 8500 | J48: 46009 | K48: 46556 | L48: 75
A49: CIGARETTE TIME GRIS X5O | B49: Tabac | C49: Paquet | D49: 10 | E49: 20 | F49: 200 | G49: 4000 | H49: =G49/F49 -> 20 | I49: =H49*F49 -> 4000 | J49: 46023 | K49: 46569 | L49: 25
A50: LAIT TOP MIL VANILLE SACHET 6 X50 | B50: Epicerie | C50: Paquet | D50: 6 | E50: 50 | F50: 300 | G50: 12000 | H50: =G50/F50 -> 40 | I50: =H50*F50 -> 12000 | J50: 46159 | K50: 46524 | L50: 50
A51: BISCUIT PARLE G 4X60X14G | B51: Biscuits | C51: Pièce | D51: 1 | E51: 240 | F51: 240 | G51: 4500 | H51: =G51/F51 -> 18.75 | I51: =H51*F51 -> 4500 | J51: 46143 | K51: 46507 | L51: 25
A52: BISCUIT PARLE G 31 56 3X120 | B52: Biscuits | C52: Pièce | D52: 1 | E52: 120 | F52: 120 | G52: 4800 | H52: =G52/F52 -> 40 | I52: =H52*F52 -> 4800 | J52: 46143 | K52: 46507 | L52: 50
A53: BISCUIT ABC X120 | B53: Biscuits | C53: Pièce | D53: 1 | E53: 12 | F53: 120 | G53: 4700 | H53: =G53/F53 -> 39.166667 | I53: =H53*F53 -> 4700 | K53: 46447 | L53: 50
A54: PAPIER HYGIENIQUE SITA X48 | B54: Hygiene | C54: Pièce | D54: 1 | E54: 48 | F54: 48 | G54: 11500 | H54: =G54/E54 -> 239.58333 | I54: =H54*F54 -> 11500 | L54: 200
A55: VIN ROUGE EL VINO I2XIL | B55: Vin | C55: Bouteille | D55: 1 | E55: 12 | F55: 12 | G55: 11500 | H55: =G55/E55 -> 958.33333 | I55: =H55*F55 -> 11500 | L55: 1200
A56: VIN BLANC EL VINO 12X1L | B56: Vin | C56: Bouteille | D56: 1 | E56: 12 | F56: 12 | G56: 12000 | H56: =G56/E56 -> 1000 | I56: =H56*F56 -> 12000 | J56: 46137 | L56: 1200
A57: VIN FIESTA ROUOE 12XL | B57: Vin | C57: Bouteille | D57: 1 | E57: 12 | F57: 12 | G57: 11500 | H57: =G57/E57 -> 958.33333 | I57: =H57*F57 -> 11500 | J57: 46045 | L57: 1200
A58: VIN ROUGE BARON DE RIBERA I2XIL | B58: Vin | C58: Bouteille | D58: 1 | E58: 12 | F58: 12 | G58: 7500 | H58: =G58/E58 -> 625 | I58: =H58*F58 -> 7500 | L58: 1200
A59: HUILE MAYOR 15X1L | B59: Epicerie | C59: Bouteille | D59: 1 | E59: 15 | F59: 1 | G59: 21000 | H59: =G59/E59 -> 1400 | I59: =H59*F59 -> 1400 | J59: 46101 | K59: 46914 | L59: 1500
A60: TOMATE ROMA SACHET 50X70G | B60: Concentré de Tomate | C60: Sachet | D60: 1 | E60: 50 | F60: 50 | G60: 4300 | H60: =G60/E60 -> 86 | I60: =H60*F60 -> 4300 | J60: 46038 | K60: 46874 | L60: 100
A61: BONBON TATOO POP X16 | B61: Confiserie | C61: Pièce | D61: 1 | E61: 48 | F61: 48 | G61: 1800 | H61: =G61/E61 -> 37.5 | I61: =H61*F61 -> 1800 | J61: 45809 | K61: 46508 | L61: 50
A62: SER VIETTE HYG AMIE 5X12X280MM | B62: Hygiène Féminine | C62: Paquet | D62: 1 | E62: 12 | F62: 12 | G62: 6700 | H62: =G62/E62 -> 558.33333 | I62: =H62*F62 -> 6700 | J62: 45818 | K62: 46913 | L62: 650
A63: SER HYG A+ JAUNE 4X6 | B63: Hygiène Féminine | C63: Paquet | D63: 1 | E63: 6 | F63: 6 | G63: 2500 | H63: =G63/E63 -> 416.66667 | I63: =H63*F63 -> 2500 | J63: 46163 | K63: 47258 | L63: 600
A64: SER VIETTE HYG SOFTCARE A+ 10PQTX6 NEW BLEU | B64: Hygiène Féminine | C64: Paquet | D64: 1 | E64: 6 | F64: 6 | G64: 2500 | H64: =G64/E64 -> 416.66667 | I64: =H64*F64 -> 2500 | J64: 46093 | K64: 47188 | L64: 600
A65: CUBE MAGGI ETOILE 25 X100X4G | B65: Assaisonnement | C65: Cube | D65: 1 | E65: 100 | F65: 100 | G65: 850 | H65: =G65/E65 -> 8.5 | I65: =H65*F65 -> 850 | J65: 46113 | K65: 46592 | L65: =25/2 -> 12.5
A66: BONBON MENTOS BTE 18 | B66: Confiserie | C66: Boîte | D66: 1 | E66: 98 | F66: 98 | G66: 1300 | H66: =G66/E66 -> 13.265306 | I66: =H66*F66 -> 1300 | J66: 45993 | K66: 46539 | L66: 25
A67: JUS FRESHCO GOYAVE 24 X310ML | B67: Boisson | C67: Bouteille | D67: 1 | E67: 24 | F67: 24 | G67: 7800 | H67: =G67/E67 -> 325 | I67: =H67*F67 -> 7800 | J67: 46190 | K67: 46555 | L67: 350
A68: INSECTICIDE SPIRALE ZERO MOUSTIQUE X60 | B68: Insecticide | C68: Paquet | D68: 1 | E68: 60 | F68: 60 | G68: 11500 | H68: =G68/E68 -> 191.66667 | I68: =H68*F68 -> 11500 | J68: 45920 | K68: 47015 | L68: 400
A69: 33 EXPORT 0,65L | B69: Brasserie_Biere | C69: Bouteille | E69: 12 | F69: =D69*E69 -> 0 | H69: =G69/E69 -> 0 | I69: =H69*F69 -> 0
A70: AMPOULE REGRETTE | B70: Electricite | C70: Pièce | F70: =D70*E70 -> 0 | H70: =G70/E70 -> #DIV/0! | I70: =H70*F70 -> #DIV/0!
A71: BABOUCHE DE TOILETTE | B71: Hygiene | C71: Paire | E71: 12 | F71: =D71*E71 -> 0 | H71: =G71/E71 -> 0 | I71: =H71*F71 -> 0
A72: BEAUFORT ORDINAIRE 0,65L | B72: Brasserie_Biere | C72: Bouteille | E72: 12 | F72: =D72*E72 -> 0 | H72: =G72/E72 -> 0 | I72: =H72*F72 -> 0
A73: BOSTER COLA 0,65L | B73: Boisson_Gazeuse | C73: Bouteille | E73: 12 | F73: =D73*E73 -> 0 | H73: =G73/E73 -> 0 | I73: =H73*F73 -> 0
A74: BOSTER DJIM TONIC 0,65L | B74: Boisson_Gazeuse | C74: Bouteille | E74: 12 | F74: =D74*E74 -> 0 | H74: =G74/E74 -> 0 | I74: =H74*F74 -> 0
A75: BOUTEILLE CONSIGNE | B75: Consigne | C75: Pièce | E75: 1 | F75: =D75*E75 -> 0 | H75: =G75/E75 -> 0 | I75: =H75*F75 -> 0
A76: CAOUTCHOUC | B76: Fourniture | C76: Pièce | F76: =D76*E76 -> 0 | H76: =G76/E76 -> #DIV/0! | I76: =H76*F76 -> #DIV/0!
A77: CASTEL 0,5L | B77: Brasserie_Biere | C77: Bouteille | E77: 12 | F77: =D77*E77 -> 0 | H77: =G77/E77 -> 0 | I77: =H77*F77 -> 0
A78: CIRAGE LIQUIDE | B78: Entretien | C78: Pièce | F78: =D78*E78 -> 0 | H78: =G78/E78 -> #DIV/0! | I78: =H78*F78 -> #DIV/0!
A79: DOPPEL 0,65L | B79: Brasserie_Biere | C79: Bouteille | E79: 12 | F79: =D79*E79 -> 0 | H79: =G79/E79 -> 0 | I79: =H79*F79 -> 0
A80: EPINGLE | B80: Fourniture | C80: Pièce | F80: =D80*E80 -> 0 | H80: =G80/E80 -> #DIV/0! | I80: =H80*F80 -> #DIV/0!
A81: GRAND GUINESS 0,65L | B81: Guinness_Biere | C81: Bouteille | E81: 12 | F81: =D81*E81 -> 0 | H81: =G81/E81 -> 0 | I81: =H81*F81 -> 0
A82: HARP BRASSERIE 0,6L | B82: Brasserie_Biere | C82: Bouteille | E82: 12 | F82: =D82*E82 -> 0 | H82: =G82/E82 -> 0 | I82: =H82*F82 -> 0
A83: ICE BLACK ET ANANA 0,65L | B83: Brasserie_Biere | C83: Bouteille | E83: 12 | F83: =D83*E83 -> 0 | H83: =G83/E83 -> 0 | I83: =H83*F83 -> 0
A84: ISEMBECK 0,65L | B84: Brasserie_Biere | C84: Bouteille | E84: 12 | F84: =D84*E84 -> 0 | H84: =G84/E84 -> 0 | I84: =H84*F84 -> 0
A85: JUS ANANAS BRASSERIE 1L | B85: Jus | C85: Bouteille | E85: 6 | F85: =D85*E85 -> 0 | H85: =G85/E85 -> 0 | I85: =H85*F85 -> 0
A86: JUS GRENADINE 1L | B86: Jus | C86: Bouteille | E86: 6 | F86: =D86*E86 -> 0 | H86: =G86/E86 -> 0 | I86: =H86*F86 -> 0
A87: JUS TOP 1L | B87: Jus | C87: Bouteille | E87: 6 | F87: =D87*E87 -> 0 | H87: =G87/E87 -> 0 | I87: =H87*F87 -> 0
A88: KAGI BIER 0,65L | B88: Brasserie_Biere | C88: Bouteille | E88: 12 | F88: =D88*E88 -> 0 | H88: =G88/E88 -> 0 | I88: =H88*F88 -> 0
A89: LOTUS TIOF | B89: Mouchoir | C89: Pièce | E89: 250 | F89: =D89*E89 -> 0 | H89: =G89/E89 -> 0 | I89: =H89*F89 -> 0
A90: MALTA GUINESS 0,3L | B90: Guinness_Biere | C90: Bouteille | E90: 24 | F90: =D90*E90 -> 0 | H90: =G90/E90 -> 0 | I90: =H90*F90 -> 0
A91: MANYAN 0,65L | B91: Brasserie_Biere | C91: Bouteille | E91: 12 | F91: =D91*E91 -> 0 | H91: =G91/E91 -> 0 | I91: =H91*F91 -> 0
A92: MENTHOLIN | B92: Pommade | C92: Pièce | F92: =D92*E92 -> 0 | H92: =G92/E92 -> #DIV/0! | I92: =H92*F92 -> #DIV/0!
A93: MUTZIG 0,65L | B93: Brasserie_Biere | C93: Bouteille | E93: 12
A94: MUX HERTAL 0,65L | B94: Mux_Biere | C94: Bouteille | E94: 12 | F94: =D94*E94 -> 0 | H94: =G94/E94 -> 0 | I94: =H94*F94 -> 0
A95: MUX WISKI 0,65L | B95: Mux_Biere | C95: Bouteille | E95: 12 | F95: =D95*E95 -> 0 | H95: =G95/E95 -> 0 | I95: =H95*F95 -> 0
A96: ORIGI GUINESS 0,65L | B96: Guinness_Biere | C96: Bouteille | E96: 12 | F96: =D96*E96 -> 0 | H96: =G96/E96 -> 0 | I96: =H96*F96 -> 0
A97: ORUIM GUINNESS 0,65L | B97: Guinness_Biere | C97: Bouteille | E97: 12 | F97: =D97*E97 -> 0 | H97: =G97/E97 -> 0 | I97: =H97*F97 -> 0
A98: PETIT GUINESS 0,35L | B98: Guinness_Biere | C98: Bouteille | E98: 24 | F98: =D98*E98 -> 0 | H98: =G98/E98 -> 0 | I98: =H98*F98 -> 0
A99: PLASTIQUE | B99: Emballage | C99: Paquet | F99: =D99*E99 -> 0 | H99: =G99/E99 -> #DIV/0! | I99: =H99*F99 -> #DIV/0!
A100: RALONGE ELECTRIQUE | B100: Electricite | C100: Pièce | F100: =D100*E100 -> 0 | H100: =G100/E100 -> #DIV/0! | I100: =H100*F100 -> #DIV/0!
A101: RÈGLE GRADUE | B101: Fourniture | C101: Pièce | F101: =D101*E101 -> 0 | H101: =G101/E101 -> #DIV/0! | I101: =H101*F101 -> #DIV/0!
...
